Workbook

Sheet Navigation Pane
B2: Click on a sheet name to navigate directly to that sheet.
B4: Financial Model Layout -
B5: Valuation
B6: Scenario Analysis
B7: Asumption Sheet
B8: Balance Sheet
B9: Income Statement
B10: Cash Flow Statement
B11: Revenue Model
B12: Cost Model
B13: Capex Schedule
B14: Depreciation & Finance Cost Schedule
... B19: Once on the sheet, click on the top-left cell (A1) of the sheet (i.e., the sheet name) to return to this page.

Sheet Valuation
A1: Valuation
A2: Figures in Lakhs ,expect otherwise stated
A3: Particular/Years | B3: Comments | C3: 2021-22 A | D3: 2022-23 A | E3: 2023-24 A | F3: 2024-25 A | G3: 2025-26 E | H3: 2026-27 E | I3: 2027-28 E | J3: 2028-29 E | K3: 2029-30 E
A4: DCF Method
A5: Cash flow from Operations | C5: =CFS!C31 -> 9442.52 | D5: =CFS!D31 -> 9343.03 | E5: =CFS!E31 -> 9324.54 | F5: =CFS!F31 -> 33119.56 | G5: =CFS!G31 -> 30438.285 | H5: =CFS!H31 -> 30188.747 | I5: =CFS!I31 -> 33273.052 | J5: =CFS!J31 -> 39151.891 | K5: =CFS!K31 -> 42967.403
A6: =CFS!A51 -> Interest paid | C6: =CFS!C51 -> -94.63 | D6: =CFS!D51 -> -62.22 | E6: =CFS!E51 -> -298.92 | F6: =CFS!F51 -> -88.23 | G6: =CFS!G51 -> -153.11296 | H6: =CFS!H51 -> -144.20856 | I6: =CFS!I51 -> -137.96847 | J6: =CFS!J51 -> -133.5955 | K6: =CFS!K51 -> -130.53098
A7: Cash flow from Investing | C7: =CFS!C41 -> -63029.27 | D7: =CFS!D41 -> -14814.25 | E7: =CFS!E41 -> 1659.42 | F7: =CFS!F41 -> -22060.2 | G7: =CFS!G41 -> -23469.615 | H7: =CFS!H41 -> -22587.572 | I7: =CFS!I41 -> -21107.614 | J7: =CFS!J41 -> 2397.1459 | K7: =CFS!K41 -> 5555.1186
A8: Net Borrowings | B8: Issue - Repayment | C8: =CFS!C46+CFS!C47 -> 0 | D8: =CFS!D46+CFS!D47 -> 0 | E8: =CFS!E46+CFS!E47 -> -140.06 | F8: =CFS!F46+CFS!F47 -> -165.02 | G8: =CFS!G46+CFS!G47 -> 0 | H8: =CFS!H46+CFS!H47 -> 0 | I8: =CFS!I46+CFS!I47 -> 0 | J8: =CFS!J46+CFS!J47 -> 0 | K8: =CFS!K46+CFS!K47 -> 0
A9: Free Cash flow to Equity | C9: =SUM(C5:C8) -> -53681.38 | D9: =SUM(D5:D8) -> -5533.44 | E9: =SUM(E5:E8) -> 10544.98 | F9: =SUM(F5:F8) -> 10806.11 | G9: =SUM(G5:G8) -> 6815.5567 | H9: =SUM(H5:H8) -> 7456.9666 | I9: =SUM(I5:I8) -> 12027.47 | J9: =SUM(J5:J8) -> 41415.442 | K9: =SUM(K5:K8) -> 48391.99
A11: Risk Free Rate | B11: ='Assumption Sheet'!B149 -> 0.0603
A12: Beta | B12: ='Assumption Sheet'!B150 -> 0.59
A13: Equity Risk Premium | B13: ='Assumption Sheet'!B151 -> 0.0708
A14: Cost of Equity | B14: =B11+(B12*B13) -> 0.102072
A16: Growth Rate at terminal year | B16: ='Assumption Sheet'!B152 -> 0.05
A18: Date | G18: 46112 | H18: 46477 | I18: 46843 | J18: 47208 | K18: 47573
A19: FCFE | G19: =G9 -> 6815.5567 | H19: =H9 -> 7456.9666 | I19: =I9 -> 12027.47 | J19: =J9 -> 41415.442 | K19: =K9 -> 48391.99
A20: Terminal Value | K20: =(K19*(1+B16))/(B14-B16) -> 975794.86
A21: Total Cash flow | G21: =SUM(G19:G20) -> 6815.5567 | H21: =SUM(H19:H20) -> 7456.9666 | I21: =SUM(I19:I20) -> 12027.47 | J21: =SUM(J19:J20) -> 41415.442 | K21: =SUM(K19:K20) -> 1024186.9
A23: Value of the Company | B23: =XNPV(B14,G21:K21,G18:K18) -> 748517.19
A24: Shares O/s | B24: 1928.09
A26: Value Per Share | B26: =B23/B24 -> 388.21693

Sheet Scenario Analysis 
A1: Scenario Analysis
A2: Figures in Lakhs ,expect otherwise stated
A3: Particular/Years | B3: Comments | C3: 2021-22 A | D3: 2022-23 A | E3: 2023-24 A | F3: 2024-25 A | G3: 2025-26 E | H3: 2026-27 E | I3: 2027-28 E | J3: 2028-29 E | K3: 2029-30 E
A5: =Valuation!A26 -> Value Per Share | B5: =Valuation!B26 -> 388.21693
A7: Y-o-Y Growth in Sale in Quantity of Products | B7: 2
A8: Best Scenario | C8: ='Assumption Sheet'!C8 -> - | D8: ='Assumption Sheet'!D8 -> 0.39900249 | E8: ='Assumption Sheet'!E8 -> 0.2228164 | F8: ='Assumption Sheet'!F8 -> -0.36734694 | G8: -0.05 | H8: -0.05 | I8: -0.05 | J8: -0.05 | K8: -0.05
A9: Base Scenario | B9: Mgmnt Guidance- Mgmnt will not focus much on this segment and rather focus on music segment | C9: ='Assumption Sheet'!C8 -> - | D9: ='Assumption Sheet'!D8 -> 0.39900249 | E9: ='Assumption Sheet'!E8 -> 0.2228164 | F9: ='Assumption Sheet'!F8 -> -0.36734694 | G9: -0.2 | H9: -0.2 | I9: -0.2 | J9: -0.2 | K9: -0.2
A10: Worst Scenario | C10: ='Assumption Sheet'!C8 -> - | D10: ='Assumption Sheet'!D8 -> 0.39900249 | E10: ='Assumption Sheet'!E8 -> 0.2228164 | F10: ='Assumption Sheet'!F8 -> -0.36734694 | G10: -0.4 | H10: -0.4 | I10: -0.4 | J10: -0.4 | K10: -0.4
A13: Y-o-Y Increase in Revenue per song of Songs After 2021 | B13: 2
A14: Best Scenario | C14: ='Assumption Sheet'!C22 -> 0 | D14: ='Assumption Sheet'!D22 -> 0 | E14: ='Assumption Sheet'!E22 -> -0.25654146 | F14: ='Assumption Sheet'!F22 -> 0.091999196 | G14: 0.2 | H14: 0.25 | I14: 0.15 | J14: 0.13 | K14: 0.14 | P14: 1
A15: Base Scenario | B15: Expicit- Agressive investment till FY 2027 | C15: ='Assumption Sheet'!C22 -> 0 | D15: ='Assumption Sheet'!D22 -> 0 | E15: ='Assumption Sheet'!E22 -> -0.25654146 | F15: ='Assumption Sheet'!F22 -> 0.091999196 | G15: 0.15 | H15: 0.2 | I15: 0.1 | J15: 0.08 | K15: 0.09 | P15: 2
A16: Worst Scenario | C16: ='Assumption Sheet'!C22 -> 0 | D16: ='Assumption Sheet'!D22 -> 0 | E16: ='Assumption Sheet'!E22 -> -0.25654146 | F16: ='Assumption Sheet'!F22 -> 0.091999196 | G16: 0.1 | H16: 0.15 | I16: 0.05 | J16: 0.03 | K16: 0.04 | P16: 3
A19: Y-o-Y Growth in music Segment | B19: 2
A20: Best Scenario | C20: ='Assumption Sheet'!C25 -> 0 | D20: ='Assumption Sheet'!D25 -> 0.15947794 | E20: ='Assumption Sheet'!E25 -> 0.1847445 | F20: ='Assumption Sheet'!F25 -> 0.21817235 | G20: 0.3 | H20: 0.3 | I20: 0.3 | J20: 0.3 | K20: 0.3
A21: Base Scenario | B21: Mgmnt Guidance | C21: ='Assumption Sheet'!C25 -> 0 | D21: ='Assumption Sheet'!D25 -> 0.15947794 | E21: ='Assumption Sheet'!E25 -> 0.1847445 | F21: ='Assumption Sheet'!F25 -> 0.21817235 | G21: 0.21 | H21: 0.21 | I21: 0.21 | J21: 0.21 | K21: 0.21
A22: Worst Scenario | C22: ='Assumption Sheet'!C25 -> 0 | D22: ='Assumption Sheet'!D25 -> 0.15947794 | E22: ='Assumption Sheet'!E25 -> 0.1847445 | F22: ='Assumption Sheet'!F25 -> 0.21817235 | G22: 0.15 | H22: 0.15 | I22: 0.15 | J22: 0.15 | K22: 0.15
A24: Y-o-Y Growth in Video Segment | B24: 3
A25: Best Scenario | C25: ='Assumption Sheet'!C28 -> - | D25: ='Assumption Sheet'!D28 -> 0.059298007 | E25: ='Assumption Sheet'!E28 -> 0.068260207 | F25: ='Assumption Sheet'!F28 -> 0.65688473 | G25: 0.4 | H25: 0.4 | I25: 0.4 | J25: 0.4 | K25: 0.4
A26: Base Scenario | B26: Mgmnt Guidance | C26: ='Assumption Sheet'!C28 -> - | D26: ='Assumption Sheet'!D28 -> 0.059298007 | E26: ='Assumption Sheet'!E28 -> 0.068260207 | F26: ='Assumption Sheet'!F28 -> 0.65688473 | G26: 0.25 | H26: 0.25 | I26: 0.25 | J26: 0.25 | K26: 0.25
A27: Worst Scenario | C27: ='Assumption Sheet'!C28 -> - | D27: ='Assumption Sheet'!D28 -> 0.059298007 | E27: ='Assumption Sheet'!E28 -> 0.068260207 | F27: ='Assumption Sheet'!F28 -> 0.65688473 | G27: 0.15 | H27: 0.15 | I27: 0.15 | J27: 0.15 | K27: 0.15
A30: Y-o-Y Growth in Events Segment | B30: 3
A31: Best Scenario | C31: 0 | D31: 0 | E31: -0.72543641 | F31: 20.220619 | G31: 0.4 | H31: 0.4 | I31: 0.4 | J31: 0.4 | K31: 0.4
A32: Base Scenario | C32: 0 | D32: 0 | E32: -0.72543641 | F32: 20.220619 | G32: 0.15 | H32: 0.15 | I32: 0.15 | J32: 0.15 | K32: 0.15
A33: Worst Scenario | C33: 0 | D33: 0 | E33: -0.72543641 | F33: 20.220619 | G33: -0.1 | H33: -0.1 | I33: -0.1 | J33: -0.1 | K33: -0.1
A35: Aquistion of Music | B35: 2
A36: Best Scenario | B36: Mgmnt Guidance - 1000 Cr. Investment between 2025 to 2027 and then increase in Intangible asset at inflation rate of 6%. Therefore, 827.81 Cr in next 2 years | C36: ='Assumption Sheet'!C97 -> 5209.07 | D36: ='Assumption Sheet'!D97 -> 7200.22 | E36: ='Assumption Sheet'!E97 -> 9882.27 | F36: ='Assumption Sheet'!F97 -> 17218.87 | G36: 41390.565 | H36: 41390.565 | I36: 7486.15 | J36: =I36*(1+6%) -> 7935.319 | K36: =J36*(1+6%) -> 8411.4381
A37: Base Scenario | B37: Out of 1000 Cr, 172.19 Cr is invested remaning 827.81Cr over 3 years | C37: ='Assumption Sheet'!C97 -> 5209.07 | D37: ='Assumption Sheet'!D97 -> 7200.22 | E37: ='Assumption Sheet'!E97 -> 9882.27 | F37: ='Assumption Sheet'!F97 -> 17218.87 | G37: 27593.71 | H37: 27593.71 | I37: 27593.71 | J37: 7486.15 | K37: =J37*(1+6%) -> 7935.319
A38: Worst Scenario | B38: Out of 1000 Cr, 172.19 Cr is invested remaning 827.81Cr over 4 years | C38: ='Assumption Sheet'!C97 -> 5209.07 | D38: ='Assumption Sheet'!D97 -> 7200.22 | E38: ='Assumption Sheet'!E97 -> 9882.27 | F38: ='Assumption Sheet'!F97 -> 17218.87 | G38: 20695.283 | H38: 20695.283 | I38: 20695.283 | J38: 20695.283 | K38: 7486.15
A40: Growth Rate | B40: 2
A41: Best Scenario | B41: 0.07
A42: Base Scenario | B42: 0.05
A43: Worst Scenario | B43: 0.03
A46: Thesis
A47: Right for 60 years | B47: 5 year payback
A48: Gen Ai for video
A49: Spotify will be a paid app eventually | B49: 0.1 Paisa per stream for free , 0.50 paisa per stream for paid
A50: Focus on short video , reels format are trending
A51: Annuity type structure
A52: Old Songs collection
A54: Anti thesis
A55: Carvaan business

Sheet Assumption Sheet
A1: Assumption Sheet
A2: Figures in Lakhs ,expect otherwise stated
A3: Particular/Years | B3: Comments | C3: 2021-22 A | D3: 2022-23 A | E3: 2023-24 A | F3: 2024-25 A | G3: 2025-26 E | H3: 2026-27 E | I3: 2027-28 E | J3: 2028-29 E | K3: 2029-30 E
A5: Revenue Model
A7: ='Revenue Model'!A18 -> Sale of product
A8: ='Revenue Model'!A21 -> Y-o-Y Growth in Sale in Quantity of Products | B8: Mgmnt Guidance- Mgmnt will not focus much on this segment and rather focus on music segment | C8: ='Revenue Model'!C21 -> - | D8: ='Revenue Model'!D21 -> 0.39900249 | E8: ='Revenue Model'!E21 -> 0.2228164 | F8: ='Revenue Model'!F21 -> -0.36734694 | G8: =CHOOSE('Scenario Analysis '!$B$7,'Scenario Analysis '!G8,'Scenario Analysis '!G9,'Scenario Analysis '!G10) -> -0.2 | H8: =CHOOSE('Scenario Analysis '!$B$7,'Scenario Analysis '!H8,'Scenario Analysis '!H9,'Scenario Analysis '!H10) -> -0.2 | I8: =CHOOSE('Scenario Analysis '!$B$7,'Scenario Analysis '!I8,'Scenario Analysis '!I9,'Scenario Analysis '!I10) -> -0.2 | J8: =CHOOSE('Scenario Analysis '!$B$7,'Scenario Analysis '!J8,'Scenario Analysis '!J9,'Scenario Analysis '!J10) -> -0.2 | K8: =CHOOSE('Scenario Analysis '!$B$7,'Scenario Analysis '!K8,'Scenario Analysis '!K9,'Scenario Analysis '!K10) -> -0.2
A9: ='Revenue Model'!A22 -> Y-o-Y Growth in Average Selling Price of Products | B9: Mgmnt Guidance- Mgmnt will not focus much on this segment and rather focus on music segment | C9: ='Revenue Model'!C22 -> - | D9: ='Revenue Model'!D22 -> -0.10290123 | E9: ='Revenue Model'!E22 -> -0.16933017 | F9: ='Revenue Model'!F22 -> -0.0056007884 | G9: -0.2 | H9: -0.2 | I9: -0.2 | J9: -0.2 | K9: -0.2
A11: License Fees- Music
A12: ='Revenue Model'!A42 -> Era wise Segment (YoY Growth in Revenue)
A13: ='Revenue Model'!A44 -> 2001-2020 | B13: Mgmnt Guidance | C13: ='Revenue Model'!C44 -> - | D13: ='Revenue Model'!D44 -> -0.39997017 | E13: ='Revenue Model'!E44 -> 0.042213282 | F13: ='Revenue Model'!F44 -> -0.051684909 | G13: 0.06 | H13: 0.06 | I13: 0.06 | J13: 0.06 | K13: 0.06
A14: ='Revenue Model'!A45 -> 1981-2000 | B14: Mgmnt Guidance | C14: ='Revenue Model'!C45 -> - | D14: ='Revenue Model'!D45 -> -0.076877182 | E14: ='Revenue Model'!E45 -> 0.097066613 | F14: ='Revenue Model'!F45 -> 0.013511754 | G14: 0.06 | H14: 0.06 | I14: 0.06 | J14: 0.06 | K14: 0.06
A15: ='Revenue Model'!A46 -> 1961-1980 | B15: Mgmnt Guidance | C15: ='Revenue Model'!C46 -> - | D15: ='Revenue Model'!D46 -> 0.084672907 | E15: ='Revenue Model'!E46 -> -0.021151772 | F15: ='Revenue Model'!F46 -> 0.036034237 | G15: 0.06 | H15: 0.06 | I15: 0.06 | J15: 0.06 | K15: 0.06
A16: ='Revenue Model'!A47 -> Till 1960 | B16: Explicit | C16: ='Revenue Model'!C47 -> - | D16: ='Revenue Model'!D47 -> 0.0048808775 | E16: ='Revenue Model'!E47 -> 0.31015071 | F16: ='Revenue Model'!F47 -> 0.12612417 | G16: 0.04 | H16: 0.04 | I16: 0.04 | J16: 0.04 | K16: 0.04
A18: ='Revenue Model'!A65 -> Y-o-Y Increase in Number of Songs After 2021 | C18: ='Revenue Model'!C65 -> - | D18: ='Revenue Model'!D65 -> 0.12 | E18: ='Revenue Model'!E65 -> 0.104 | F18: ='Revenue Model'!F65 -> 0.056 | G18: =G19*G20 -> 0.06 | H18: =H19*H20 -> 0.066 | I18: =I19*I20 -> 0.046 | J18: =J19*J20 -> 0.048 | K18: =K19*K20 -> 0.05
A19: % of New Content Acquried by Saregama | B19: Mgmnt Guidance- 30% till FY 2027 | C19: - | D19: - | E19: - | F19: - | G19: 0.3 | H19: 0.3 | I19: 0.2 | J19: 0.2 | K19: 0.2
A20: New Songs made per Year (In Lkahs) | B20: Report by EY | C20: - | D20: - | E20: - | F20: - | G20: 0.2 | H20: 0.22 | I20: 0.23 | J20: 0.24 | K20: 0.25
A22: ='Revenue Model'!A75 -> Y-o-Y Increase in Revenue per song of Songs After 2021 | C22: ='Revenue Model'!C75 -> 0 | D22: ='Revenue Model'!D75 -> 0 | E22: ='Revenue Model'!E75 -> -0.25654146 | F22: ='Revenue Model'!F75 -> 0.091999196 | G22: =CHOOSE('Scenario Analysis '!$B$13,'Scenario Analysis '!G14,'Scenario Analysis '!G15,'Scenario Analysis '!G16) -> 0.15 | H22: =CHOOSE('Scenario Analysis '!$B$13,'Scenario Analysis '!H14,'Scenario Analysis '!H15,'Scenario Analysis '!H16) -> 0.2 | I22: =CHOOSE('Scenario Analysis '!$B$13,'Scenario Analysis '!I14,'Scenario Analysis '!I15,'Scenario Analysis '!I16) -> 0.1 | J22: =CHOOSE('Scenario Analysis '!$B$13,'Scenario Analysis '!J14,'Scenario Analysis '!J15,'Scenario Analysis '!J16) -> 0.08 | K22: =CHOOSE('Scenario Analysis '!$B$13,'Scenario Analysis '!K14,'Scenario Analysis '!K15,'Scenario Analysis '!K16) -> 0.09
A24: Artist Management
A25: ='Revenue Model'!A79 -> Y-o-Y Growth in music Segment | C25: ='Revenue Model'!C79 -> 0 | D25: ='Revenue Model'!D79 -> 0.15947794 | E25: ='Revenue Model'!E79 -> 0.1847445 | F25: ='Revenue Model'!F79 -> 0.21817235 | G25: =CHOOSE('Scenario Analysis '!$B$19,'Scenario Analysis '!G20,'Scenario Analysis '!G21,'Scenario Analysis '!G22) -> 0.21 | H25: =CHOOSE('Scenario Analysis '!$B$19,'Scenario Analysis '!H20,'Scenario Analysis '!H21,'Scenario Analysis '!H22) -> 0.21 | I25: =CHOOSE('Scenario Analysis '!$B$19,'Scenario Analysis '!I20,'Scenario Analysis '!I21,'Scenario Analysis '!I22) -> 0.21 | J25: =CHOOSE('Scenario Analysis '!$B$19,'Scenario Analysis '!J20,'Scenario Analysis '!J21,'Scenario Analysis '!J22) -> 0.21 | K25: =CHOOSE('Scenario Analysis '!$B$19,'Scenario Analysis '!K20,'Scenario Analysis '!K21,'Scenario Analysis '!K22) -> 0.21
A27: Income from videos
A28: ='Revenue Model'!A83 -> Y-o-Y Growth in Video Segment | C28: ='Revenue Model'!C83 -> - | D28: ='Revenue Model'!D83 -> 0.059298007 | E28: ='Revenue Model'!E83 -> 0.068260207 | F28: ='Revenue Model'!F83 -> 0.65688473 | G28: =CHOOSE('Scenario Analysis '!$B$24,'Scenario Analysis '!G25,'Scenario Analysis '!G26,'Scenario Analysis '!G27) -> 0.15 | H28: =CHOOSE('Scenario Analysis '!$B$24,'Scenario Analysis '!H25,'Scenario Analysis '!H26,'Scenario Analysis '!H27) -> 0.15 | I28: =CHOOSE('Scenario Analysis '!$B$24,'Scenario Analysis '!I25,'Scenario Analysis '!I26,'Scenario Analysis '!I27) -> 0.15 | J28: =CHOOSE('Scenario Analysis '!$B$24,'Scenario Analysis '!J25,'Scenario Analysis '!J26,'Scenario Analysis '!J27) -> 0.15 | K28: =CHOOSE('Scenario Analysis '!$B$24,'Scenario Analysis '!K25,'Scenario Analysis '!K26,'Scenario Analysis '!K27) -> 0.15
A30: Income from events
A31: ='Revenue Model'!A86 -> Y-o-Y Growth in Events Segment | B31: Expilict- Lumpier segment of the business. | C31: ='Revenue Model'!C86 -> 0 | D31: ='Revenue Model'!D86 -> 0 | E31: ='Revenue Model'!E86 -> -0.72543641 | F31: ='Revenue Model'!F86 -> 20.220619 | G31: =CHOOSE('Scenario Analysis '!$B$30,'Scenario Analysis '!G31,'Scenario Analysis '!G32,'Scenario Analysis '!G33) -> -0.1 | H31: =CHOOSE('Scenario Analysis '!$B$30,'Scenario Analysis '!H31,'Scenario Analysis '!H32,'Scenario Analysis '!H33) -> -0.1 | I31: =CHOOSE('Scenario Analysis '!$B$30,'Scenario Analysis '!I31,'Scenario Analysis '!I32,'Scenario Analysis '!I33) -> -0.1 | J31: =CHOOSE('Scenario Analysis '!$B$30,'Scenario Analysis '!J31,'Scenario Analysis '!J32,'Scenario Analysis '!J33) -> -0.1 | K31: =CHOOSE('Scenario Analysis '!$B$30,'Scenario Analysis '!K31,'Scenario Analysis '!K32,'Scenario Analysis '!K33) -> -0.1
A33: Other operating income
A34: ='Revenue Model'!A88 -> Other operating income | B34: Explicit | C34: ='Revenue Model'!C88 -> 1327.06 | D34: ='Revenue Model'!D88 -> 3036.74 | E34: ='Revenue Model'!E88 -> 4503.17 | F34: ='Revenue Model'!F88 -> 467.2 | G34: 0 | H34: 0 | I34: 0 | J34: 0 | K34: 0
A37: Cost Model
A39: ='Cost Model '!A5 -> Cost of Music Business
A40: ='Cost Model '!A12 -> Cost of music/Income from music | B40: Constant Average | C40: ='Cost Model '!C12 -> 0.14866215 | D40: ='Cost Model '!D12 -> 0.16563742 | E40: ='Cost Model '!E12 -> 0.17010661 | F40: ='Cost Model '!F12 -> 0.12630644 | G40: =AVERAGE($C$40:$F$40) -> 0.15267816 | H40: =AVERAGE($C$40:$F$40) -> 0.15267816 | I40: =AVERAGE($C$40:$F$40) -> 0.15267816 | J40: =AVERAGE($C$40:$F$40) -> 0.15267816 | K40: =AVERAGE($C$40:$F$40) -> 0.15267816
A42: ='Cost Model '!A15 -> Cost of Films, Tv serials and Digital content (under production and untelecasted)
A43: ='Cost Model '!A21 -> Cost of films and events/Income from films and events | B43: Explicit - with gen AI time and cost of production will reduce eventually | C43: ='Cost Model '!C21 -> 0.72255651 | D43: ='Cost Model '!D21 -> 0.85209774 | E43: ='Cost Model '!E21 -> 0.96749629 | F43: ='Cost Model '!F21 -> 0.9555422 | G43: 0.8 | H43: 0.8 | I43: 0.75 | J43: 0.7 | K43: 0.7
A45: ='Cost Model '!A24 -> Employee benefits expense
A46: ='Cost Model '!A26 -> No. of BOD | C46: ='Cost Model '!C26 -> 0 | D46: ='Cost Model '!D26 -> 8 | E46: ='Cost Model '!E26 -> 7 | F46: ='Cost Model '!F26 -> 8 | G46: 8 | H46: 8 | I46: 8 | J46: 8 | K46: 8
A47: ='Cost Model '!A28 -> YoY Increase in Median Salary of BOD | B47: Constant Average | C47: ='Cost Model '!C28 -> - | D47: ='Cost Model '!D28 -> - | E47: ='Cost Model '!E28 -> 0 | F47: ='Cost Model '!F28 -> 0.7654321 | G47: =AVERAGE($E$47:$F$47) -> 0.38271605 | H47: =AVERAGE($E$47:$F$47) -> 0.38271605 | I47: =AVERAGE($E$47:$F$47) -> 0.38271605 | J47: =AVERAGE($E$47:$F$47) -> 0.38271605 | K47: =AVERAGE($E$47:$F$47) -> 0.38271605
A49: ='Cost Model '!A30 -> No. of KMP (Key Managerial Personell) | C49: ='Cost Model '!C30 -> 3 | D49: ='Cost Model '!D30 -> 3 | E49: ='Cost Model '!E30 -> 3 | F49: ='Cost Model '!F30 -> 3 | G49: 3 | H49: 3 | I49: 3 | J49: 3 | K49: 3
A50: ='Cost Model '!A32 -> YoY Increase in Median Salary of BOD | B50: Rolling average of 3 years | C50: ='Cost Model '!C32 -> - | D50: ='Cost Model '!D32 -> 0.47750211 | E50: ='Cost Model '!E32 -> 0.19687384 | F50: ='Cost Model '!F32 -> 0.1899768 | G50: =AVERAGE(D50:F50) -> 0.28811759 | H50: =AVERAGE(E50:G50) -> 0.22498941 | I50: =AVERAGE(F50:H50) -> 0.23436127 | J50: =AVERAGE(G50:I50) -> 0.24915609 | K50: =AVERAGE(H50:J50) -> 0.23616892
A52: ='Cost Model '!A34 -> Total Number of Employees (Other than BOD and KMP) | C52: ='Cost Model '!C34 -> 407 | D52: ='Cost Model '!D34 -> 372 | E52: ='Cost Model '!E34 -> 454 | F52: ='Cost Model '!F34 -> 396 | G52: =F52+G53 -> 446 | H52: =G52+H53 -> 496 | I52: =H52+I53 -> 546 | J52: =I52+J53 -> 596 | K52: =J52+K53 -> 646
A53: YoY Increase in No. of Employee | B53: Explicit - With Gen AI | D53: =D52-C52 -> -35 | E53: =E52-D52 -> 82 | F53: =F52-E52 -> -58 | G53: 50 | H53: 50 | I53: 50 | J53: 50 | K53: 50
A54: ='Cost Model '!A36 -> YoY Increase in Median Salary of Employee (Other than BOD and KMP) | C54: ='Cost Model '!C36 -> - | D54: ='Cost Model '!D36 -> - | E54: ='Cost Model '!E36 -> -0.042631579 | F54: ='Cost Model '!F36 -> 0.21330401 | G54: 0.3 | H54: 0.3 | I54: 0.3 | J54: 0.3 | K54: 0.3
A56: ='Cost Model '!A39 -> Royalty expenses
A57: ='Cost Model '!A41 -> Royalty Expense / License Income | B57: Constant | C57: ='Cost Model '!C41 -> 0.17379466 | D57: ='Cost Model '!D41 -> 0.15562538 | E57: ='Cost Model '!E41 -> 0.1280958 | F57: ='Cost Model '!F41 -> 0.12683352 | G57: 0.11 | H57: 0.11 | I57: 0.11 | J57: 0.11 | K57: 0.11
A59: ='Cost Model '!A44 -> Advertisement and sales promotion
A60: ='Cost Model '!A46 -> Advertisment and Sales Promotion Expense/ Revenue from operations | B60: Constant Average | C60: ='Cost Model '!C46 -> 0.089650061 | D60: ='Cost Model '!D46 -> 0.10468053 | E60: ='Cost Model '!E46 -> 0.094619828 | F60: ='Cost Model '!F46 -> 0.077185396 | G60: =AVERAGE($C$60:$F$60) -> 0.091533955 | H60: =AVERAGE($C$60:$F$60) -> 0.091533955 | I60: =AVERAGE($C$60:$F$60) -> 0.091533955 | J60: =AVERAGE($C$60:$F$60) -> 0.091533955 | K60: =AVERAGE($C$60:$F$60) -> 0.091533955
A62: ='Cost Model '!A49 -> Other expenses
A63: ='Cost Model '!A51 -> Other Expense/Revenue from Operations | B63: Average | C63: ='Cost Model '!C51 -> 0.10636887 | D63: ='Cost Model '!D51 -> 0.099011677 | E63: ='Cost Model '!E51 -> 0.11706131 | F63: ='Cost Model '!F51 -> 0.07261668 | G63: =AVERAGE(C63:F63) -> 0.098764633 | H63: =AVERAGE(D63:G63) -> 0.096863575 | I63: =AVERAGE(E63:H63) -> 0.09632655 | J63: =AVERAGE(F63:I63) -> 0.091142859 | K63: =AVERAGE(G63:J63) -> 0.095774404
A65: ='Cost Model '!A56 -> Effective Tax Rate | B65: Constant Average | C65: ='Cost Model '!C56 -> 0.25324687 | D65: ='Cost Model '!D56 -> 0.25405669 | E65: ='Cost Model '!E56 -> 0.27042196 | F65: ='Cost Model '!F56 -> 0.26019394 | G65: =AVERAGE($C$65:$F$65) -> 0.25947986 | H65: =AVERAGE($C$65:$F$65) -> 0.25947986 | I65: =AVERAGE($C$65:$F$65) -> 0.25947986 | J65: =AVERAGE($C$65:$F$65) -> 0.25947986 | K65: =AVERAGE($C$65:$F$65) -> 0.25947986
A67: ='Cost Model '!A61 -> Dividend Payout Ratio | B67: Explicit- Due to heavy capex company should retain dividends for 2 years and reinvest | C67: ='Cost Model '!C61 -> 0.37893526 | D67: ='Cost Model '!D61 -> 0.31257609 | E67: ='Cost Model '!E61 -> 0.39038304 | F67: ='Cost Model '!F61 -> 0.42481602 | G67: 0 | H67: 0 | I67: =AVERAGE($C$67:$F$67) -> 0.3766776 | J67: =AVERAGE($C$67:$F$67) -> 0.3766776 | K67: =AVERAGE($C$67:$F$67) -> 0.3766776
A69: Capex Schedule
A71: Buildings - Freehold
A72: ='Capex Schedule '!A17 -> Addition | C72: ='Capex Schedule '!C17 -> 0 | D72: ='Capex Schedule '!D17 -> 0 | E72: ='Capex Schedule '!E17 -> 0 | F72: ='Capex Schedule '!F17 -> 0 | G72: 0 | H72: 0 | I72: 0 | J72: 0 | K72: 0
A73: ='Capex Schedule '!A28 -> Total Useful Life | C73: ='Capex Schedule '!C28 -> 17.301471 | D73: ='Capex Schedule '!D28 -> 17.301471 | E73: ='Capex Schedule '!E28 -> 17.301471 | F73: ='Capex Schedule '!F28 -> 17.301471 | G73: 17.3 | H73: 17.3 | I73: 17.3 | J73: 17.3 | K73: 17.3
A75: Buildings
A76: ='Capex Schedule '!A36 -> Addition | C76: ='Capex Schedule '!C36 -> 0 | D76: ='Capex Schedule '!D36 -> 0 | E76: ='Capex Schedule '!E36 -> 0 | F76: ='Capex Schedule '!F36 -> 0 | G76: 0 | H76: 0 | I76: 0 | J76: 0 | K76: 0
A77: ='Capex Schedule '!A47 -> Total Useful Life | C77: ='Capex Schedule '!C47 -> 47.1375 | D77: ='Capex Schedule '!D47 -> 47.1375 | E77: ='Capex Schedule '!E47 -> 47.1375 | F77: ='Capex Schedule '!F47 -> 47.1375 | G77: 47.1375 | H77: 47.1375 | I77: 47.1375 | J77: 47.1375 | K77: 47.1375
A79: Plant and Equipment
A80: ='Capex Schedule '!A54 -> Addition | C80: ='Capex Schedule '!C54 -> 0 | D80: ='Capex Schedule '!D54 -> 0 | E80: ='Capex Schedule '!E54 -> 0 | F80: ='Capex Schedule '!F54 -> 22.05 | G80: 0 | H80: 0 | I80: 0 | J80: 0 | K80: 0
A81: ='Capex Schedule '!A65 -> Total Useful Life | C81: ='Capex Schedule '!C65 -> 0 | D81: ='Capex Schedule '!D65 -> 0 | E81: ='Capex Schedule '!E65 -> 0 | F81: ='Capex Schedule '!F65 -> 8.2320261 | G81: 8.2320261 | H81: 8.2320261 | I81: 8.2320261 | J81: 8.2320261 | K81: 8.2320261
A83: Furniture and Fixtures
A84: ='Capex Schedule '!A72 -> Addition | B84: Explicit | C84: ='Capex Schedule '!C72 -> 4.99 | D84: ='Capex Schedule '!D72 -> 524.55 | E84: ='Capex Schedule '!E72 -> 251.7 | F84: ='Capex Schedule '!F72 -> 60.94 | G84: 50 | H84: 50 | I84: 50 | J84: 50 | K84: 50
A85: ='Capex Schedule '!A83 -> Total Useful Life | C85: ='Capex Schedule '!C83 -> 10.467626 | D85: ='Capex Schedule '!D83 -> 22.338784 | E85: ='Capex Schedule '!E83 -> 12.245343 | F85: ='Capex Schedule '!F83 -> 10.892394 | G85: 10 | H85: 9.5 | I85: 9 | J85: 8.5 | K85: 8
A87: Office Equipment
A88: ='Capex Schedule '!A90 -> Addition | C88: ='Capex Schedule '!C90 -> 183.15 | D88: ='Capex Schedule '!D90 -> 367.37 | E88: ='Capex Schedule '!E90 -> 273.57 | F88: ='Capex Schedule '!F90 -> 159.88 | G88: =IS!G4*'Assumption Sheet'!G89 -> 408.46944 | H88: =IS!H4*'Assumption Sheet'!H89 -> 457.28129 | I88: =IS!I4*'Assumption Sheet'!I89 -> 449.38723 | J88: =IS!J4*'Assumption Sheet'!J89 -> 489.91107 | K88: =IS!K4*'Assumption Sheet'!K89 -> 639.35042
A89: Addition/Revenue | B89: Rolling Average | C89: =C88/IS!C4 -> 0.0031543454 | D89: =D88/IS!D4 -> 0.0049872309 | E89: =E88/IS!E4 -> 0.0034068323 | F89: =F88/IS!F4 -> 0.001364912 | G89: =AVERAGE(C89:F89) -> 0.0032283301 | H89: =AVERAGE(D89:G89) -> 0.0032468263 | I89: =AVERAGE(E89:H89) -> 0.0028117252 | J89: =AVERAGE(F89:I89) -> 0.0026629484 | K89: =AVERAGE(G89:J89) -> 0.0029874575
A90: ='Capex Schedule '!A101 -> Total Useful Life | B90: Rolling Average | C90: ='Capex Schedule '!C101 -> 7.3768662 | D90: ='Capex Schedule '!D101 -> 7.8146863 | E90: ='Capex Schedule '!E101 -> 6.7643892 | F90: ='Capex Schedule '!F101 -> 7.1069704 | G90: =AVERAGE(C90:F90) -> 7.265728 | H90: =AVERAGE(D90:G90) -> 7.2379435 | I90: =AVERAGE(E90:H90) -> 7.0937578 | J90: =AVERAGE(F90:I90) -> 7.1760999 | K90: =AVERAGE(G90:J90) -> 7.1933823
A92: Vehicles
A93: ='Capex Schedule '!A108 -> Addition | B93: Explicit | C93: ='Capex Schedule '!C108 -> 0 | D93: ='Capex Schedule '!D108 -> 0 | E93: ='Capex Schedule '!E108 -> 4.63 | F93: ='Capex Schedule '!F108 -> 0 | G93: 0 | H93: 0 | I93: 0 | J93: 0 | K93: 0
A94: ='Capex Schedule '!A119 -> Total Useful Life | C94: ='Capex Schedule '!C119 -> 0 | D94: ='Capex Schedule '!D119 -> 0 | E94: ='Capex Schedule '!E119 -> 0 | F94: ='Capex Schedule '!F119 -> 16.913793 | G94: 16.913793 | H94: 16.913793 | I94: 16.913793 | J94: 16.913793 | K94: 16.913793
A96: Copywrite - Music
A97: ='Capex Schedule '!A148 -> Addition | C97: ='Capex Schedule '!C148 -> 5209.07 | D97: ='Capex Schedule '!D148 -> 7200.22 | E97: ='Capex Schedule '!E148 -> 9882.27 | F97: ='Capex Schedule '!F148 -> 17218.87 | G97: =CHOOSE('Scenario Analysis '!$B$35,'Scenario Analysis '!G36,'Scenario Analysis '!G37,'Scenario Analysis '!G38) -> 27593.71 | H97: =CHOOSE('Scenario Analysis '!$B$35,'Scenario Analysis '!H36,'Scenario Analysis '!H37,'Scenario Analysis '!H38) -> 27593.71 | I97: =CHOOSE('Scenario Analysis '!$B$35,'Scenario Analysis '!I36,'Scenario Analysis '!I37,'Scenario Analysis '!I38) -> 27593.71 | J97: =CHOOSE('Scenario Analysis '!$B$35,'Scenario Analysis '!J36,'Scenario Analysis '!J37,'Scenario Analysis '!J38) -> 7486.15 | K97: =CHOOSE('Scenario Analysis '!$B$35,'Scenario Analysis '!K36,'Scenario Analysis '!K37,'Scenario Analysis '!K38) -> 7935.319
A98: ='Capex Schedule '!A161 -> Total Useful Life | B98: Mgmnt Commentary - 1 to 10 years | C98: ='Capex Schedule '!C161 -> 0 | D98: ='Capex Schedule '!D161 -> 8.5160438 | E98: ='Capex Schedule '!E161 -> 8.3339702 | F98: ='Capex Schedule '!F161 -> 8.6206569 | G98: 10 | H98: 10 | I98: 10 | J98: 10 | K98: 10
A100: Computer Software
A101: ='Capex Schedule '!A168 -> Addition | B101: Explicit | C101: ='Capex Schedule '!C168 -> 78.54 | D101: ='Capex Schedule '!D168 -> 5.21 | E101: ='Capex Schedule '!E168 -> 1 | F101: ='Capex Schedule '!F168 -> 566.53 | G101: 400 | H101: 300 | I101: 200 | J101: 100 | K101: 100
A102: ='Capex Schedule '!A181 -> Total Useful Life | B102: Mgmnt Commentary - 3 to 5 years | C102: ='Capex Schedule '!C181 -> 5.1264259 | D102: ='Capex Schedule '!D181 -> 8.7681081 | E102: ='Capex Schedule '!E181 -> 8.6035846 | F102: ='Capex Schedule '!F181 -> 6.6758759 | G102: 10 | H102: 10 | I102: 10 | J102: 10 | K102: 10
A104: Online Platform Rights
A105: ='Capex Schedule '!A188 -> Addition | C105: ='Capex Schedule '!C188 -> 0 | D105: ='Capex Schedule '!D188 -> 0 | E105: ='Capex Schedule '!E188 -> 0 | F105: ='Capex Schedule '!F188 -> 6 | G105: 0 | H105: 0 | I105: 0 | J105: 0 | K105: 0
A106: ='Capex Schedule '!A201 -> Total Useful Life | B106: Mgmnt Commentary - 5 years | C106: ='Capex Schedule '!C201 -> 0 | D106: ='Capex Schedule '!D201 -> 0 | E106: ='Capex Schedule '!E201 -> 11.647557 | F106: ='Capex Schedule '!F201 -> 4.7846745 | G106: 5 | H106: 5 | I106: 5 | J106: 5 | K106: 5
A108: Brand - Filter Copy
A109: ='Capex Schedule '!A239 -> Total Useful Life | B109: Mgmnt Commentary - 10 years | C109: ='Capex Schedule '!C239 -> 0 | D109: ='Capex Schedule '!D239 -> 0 | E109: ='Capex Schedule '!E239 -> 24 | F109: ='Capex Schedule '!F239 -> 10 | G109: 10 | H109: 10 | I109: 10 | J109: 10 | K109: 10
A111: Customer Relationship - Filter Copy
A112: ='Capex Schedule '!A259 -> Total Useful Life | B112: Mgmnt Commentary - 8 years | C112: ='Capex Schedule '!C259 -> 0 | D112: ='Capex Schedule '!D259 -> 0 | E112: ='Capex Schedule '!E259 -> 19.199077 | F112: ='Capex Schedule '!F259 -> 7.9997253 | G112: 7.9997253 | H112: 7.9997253 | I112: 7.9997253 | J112: 7.9997253 | K112: 7.9997253
A114: Customer Relationship - Clout
A115: ='Capex Schedule '!A279 -> Total Useful Life | B115: Mgmnt Commentary - 7 years | C115: ='Capex Schedule '!C279 -> 0 | D115: ='Capex Schedule '!D279 -> 0 | E115: ='Capex Schedule '!E279 -> 16.791444 | F115: ='Capex Schedule '!F279 -> 6.9964349 | G115: 7 | H115: 7 | I115: 7 | J115: 7 | K115: 7
A117: Investment property
A118: ='Capex Schedule '!A312 -> Depreciation charge during the year | B118: Constant | C118: ='Capex Schedule '!C312 -> 5.54 | D118: ='Capex Schedule '!D312 -> 5.54 | E118: ='Capex Schedule '!E312 -> 5.54 | F118: ='Capex Schedule '!F312 -> 5.54 | G118: 5.54 | H118: 5.54 | I118: 5.54 | J118: 5.54 | K118: 5.54
A121: Lease Schedule
A123: Right of Use Asset (ROU)
A124: ='Lease Schedule '!A12 -> Depreciation | B124: Explicit | C124: ='Lease Schedule '!C12 -> 45.52 | D124: ='Lease Schedule '!D12 -> 59.28 | E124: ='Lease Schedule '!E12 -> 95.03 | F124: ='Lease Schedule '!F12 -> 122.24 | G124: 122.4 | H124: 20 | I124: 20 | J124: 20 | K124: 20
A127: Current Lease Liabilty/Total Lease Liability | B127: Constant Average | C127: ='Lease Schedule '!C28/'Lease Schedule '!C27 -> 0.45322692 | D127: ='Lease Schedule '!D28/'Lease Schedule '!D27 -> 0.80659649 | E127: ='Lease Schedule '!E28/'Lease Schedule '!E27 -> 0.40354726 | F127: ='Lease Schedule '!F28/'Lease Schedule '!F27 -> 0.47726769 | G127: =AVERAGE($C$127,$E$127,$F$127) -> 0.44468062 | H127: =AVERAGE($C$127,$E$127,$F$127) -> 0.44468062 | I127: =AVERAGE($C$127,$E$127,$F$127) -> 0.44468062 | J127: =AVERAGE($C$127,$E$127,$F$127) -> 0.44468062 | K127: =AVERAGE($C$127,$E$127,$F$127) -> 0.44468062
A128: ='Lease Schedule '!A31 -> Effective Interest Rate | B128: Explicit | C128: ='Lease Schedule '!C31 -> 0.10152422 | D128: ='Lease Schedule '!D31 -> 0.079502724 | E128: ='Lease Schedule '!E31 -> 0.35480702 | F128: ='Lease Schedule '!F31 -> 0.12010996 | G128: 0.11 | H128: 0.11 | I128: 0.11 | J128: 0.11 | K128: 0.11
A129: ='Lease Schedule '!A32 -> Average life of the lease | B129: Notes of account | G129: 3 | H129: 3 | I129: 3 | J129: 3 | K129: 3
A132: Depreciation & Interest Schedule
A133: ='Depreciation & Finance Cost '!A45 -> Effective Interest Rate | B133: Explicit | C133: ='Depreciation & Finance Cost '!C45 -> 0.011461897 | D133: ='Depreciation & Finance Cost '!D45 -> 0.011003781 | E133: ='Depreciation & Finance Cost '!E45 -> 0.049015284 | F133: ='Depreciation & Finance Cost '!F45 -> 0.010865817 | G133: 0.011 | H133: 0.011 | I133: 0.011 | J133: 0.011 | K133: 0.011
A136: Other Income Schedule
A137: ='Other Income Schedule '!A34 -> Average Interest Yield | B137: Government Security Market - GS Bond 2029 = 6.4% | C137: ='Other Income Schedule '!C34 -> 0 | D137: ='Other Income Schedule '!D34 -> 0.052686481 | E137: ='Other Income Schedule '!E34 -> 0.073778936 | F137: ='Other Income Schedule '!F34 -> 0.08050812 | G137: 0.064 | H137: 0.064 | I137: 0.064 | J137: 0.064 | K137: 0.064
A138: ='Other Income Schedule '!A40 -> Rental Yeild on Closing Gross Block of Non - Current Investments | B138: 2% increase every year | C138: ='Other Income Schedule '!C40 -> 0.074789284 | D138: ='Other Income Schedule '!D40 -> 0.076174271 | E138: ='Other Income Schedule '!E40 -> 0.091844407 | F138: ='Other Income Schedule '!F40 -> 0.10660441 | G138: =F138*(1+2%) -> 0.1087365 | H138: =G138*(1+2%) -> 0.11091123 | I138: =H138*(1+2%) -> 0.11312945 | J138: =I138*(1+2%) -> 0.11539204 | K138: =J138*(1+2%) -> 0.11769988
A141: WC Schedule
A142: ='WC Schedule '!A31 -> Days Inventory Outstanding of Music | B142: Explicit | C142: ='WC Schedule '!C31 -> 41.770324 | D142: ='WC Schedule '!D31 -> 41.691675 | E142: ='WC Schedule '!E31 -> 57.636019 | F142: ='WC Schedule '!F31 -> 81.219502 | G142: 60 | H142: 60 | I142: 60 | J142: 60 | K142: 60
A143: ='WC Schedule '!A37 -> Days Inventory Outstanding of Films, Tv Serials and Digital Content | B143: Explicit- With more focus on short videos and more efforts for generative AI produced vidoes | C143: ='WC Schedule '!C37 -> 1386.7145 | D143: ='WC Schedule '!D37 -> 451.38174 | E143: ='WC Schedule '!E37 -> 829.43939 | F143: ='WC Schedule '!F37 -> 107.89168 | G143: 30 | H143: 30 | I143: 30 | J143: 30 | K143: 30
A144: ='WC Schedule '!A45 -> Days Sales Outstanding | B144: Explicit | C144: ='WC Schedule '!C45 -> 67.767899 | D144: ='WC Schedule '!D45 -> 73.31973 | E144: ='WC Schedule '!E45 -> 72.153186 | F144: ='WC Schedule '!F45 -> 44.626433 | G144: 60 | H144: 60 | I144: 60 | J144: 60 | K144: 60
A145: ='WC Schedule '!A56 -> Days Payable Outstanding | B145: Explicit | C145: ='WC Schedule '!C56 -> 131.36413 | D145: ='WC Schedule '!D56 -> 90.266508 | E145: ='WC Schedule '!E56 -> 115.64432 | F145: ='WC Schedule '!F56 -> 85.580292 | G145: 110 | H145: 100 | I145: 100 | J145: 100 | K145: 100
A148: Valuation Schedule
...

Sheet Balance Sheet
A1: Balance Sheet
A2: Figures in Lakhs ,expect otherwise stated
A3: Particular/Years | B3: Comments | C3: 2021-22 A | D3: 2022-23 A | E3: 2023-24 A | F3: 2024-25 A | G3: 2025-26 E | H3: 2026-27 E | I3: 2027-28 E | J3: 2028-29 E | K3: 2029-30 E
A4: ASSETS
A5: Non-current assets
A6: Property, plant and equipment | B6: Capex Schedule | C6: 21411.36 | D6: 22065.72 | E6: 22382.16 | F6: 22222.07 | G6: ='Capex Schedule '!G135 -> 22219.969 | H6: ='Capex Schedule '!H135 -> 22189.73 | I6: ='Capex Schedule '!I135 -> 22066.614 | J6: ='Capex Schedule '!J135 -> 21905.306 | K6: ='Capex Schedule '!K135 -> 21788.241
A7: Right-of-use assets | B7: Lease Schedule | C7: 125.88 | D7: 66.6 | E7: 334.55 | F7: 212.3 | G7: ='Lease Schedule '!G14 -> 89.9 | H7: ='Lease Schedule '!H14 -> 69.9 | I7: ='Lease Schedule '!I14 -> 49.9 | J7: ='Lease Schedule '!J14 -> 29.9 | K7: ='Lease Schedule '!K14 -> 9.9
A8: Investment property | B8: Capex Schedule | C8: 219.49 | D8: 213.95 | E8: 208.41 | F8: 202.87 | G8: ='Capex Schedule '!G315 -> 197.33 | H8: ='Capex Schedule '!H315 -> 191.79 | I8: ='Capex Schedule '!I315 -> 186.25 | J8: ='Capex Schedule '!J315 -> 180.71 | K8: ='Capex Schedule '!K315 -> 175.17
A9: Intangible assets | B9: Capex Schedule | C9: 6016.67 | D9: 11425.83 | E9: 51299.48 | F9: 60823.32 | G9: ='Capex Schedule '!G297 -> 81430.973 | H9: ='Capex Schedule '!H297 -> 99149.246 | I9: ='Capex Schedule '!I297 -> 113988.15 | J9: ='Capex Schedule '!J297 -> 107905.25 | K9: ='Capex Schedule '!K297 -> 101518.28
A10: Intangible assets under development | B10: Constant | C10: 174.52 | D10: 404.98 | E10: 554.03 | F10: 0 | G10: 0 | H10: 0 | I10: 0 | J10: 0 | K10: 0
A11: Investment accounted using equity method | B11: Constant | C11: 0 | D11: 0 | E11: 0 | F11: 0 | G11: 0 | H11: 0 | I11: 0 | J11: 0 | K11: 0
A12: Other financial assets | B12: Constant | C12: 14725.69 | D12: 5295.59 | E12: 1719.12 | F12: 779.76 | G12: 779.76 | H12: 779.76 | I12: 779.76 | J12: 779.76 | K12: 779.76
A13: Other non-current assets | B13: Constant | C13: 2915.61 | D13: 5734.75 | E13: 4675.37 | F13: 5007.8 | G13: 5007.8 | H13: 5007.8 | I13: 5007.8 | J13: 5007.8 | K13: 5007.8
A14: Total non-current assets | C14: =SUM(C6:C13) -> 45589.22 | D14: =SUM(D6:D13) -> 45207.42 | E14: =SUM(E6:E13) -> 81173.12 | F14: =SUM(F6:F13) -> 89248.12 | G14: =SUM(G6:G13) -> 109725.73 | H14: =SUM(H6:H13) -> 127388.23 | I14: =SUM(I6:I13) -> 142078.47 | J14: =SUM(J6:J13) -> 135808.73 | K14: =SUM(K6:K13) -> 129279.15
A15: Current assets
A16: Inventories | B16: WC Schedule | C16: 10543.83 | D16: 16425.56 | E16: 23925.83 | F16: 24021.48 | G16: ='WC Schedule '!G39 -> 15059.714 | H16: ='WC Schedule '!H39 -> 17079.15 | I16: ='WC Schedule '!I39 -> 19764.118 | J16: ='WC Schedule '!J39 -> 23184.466 | K16: ='WC Schedule '!K39 -> 27448.175
A17: Investments | B17: Constant | C17: 53076.37 | D17: 23877.46 | E17: 11772.39 | F17: 11120.75 | G17: 11120.75 | H17: 11120.75 | I17: 11120.75 | J17: 11120.75 | K17: 11120.75
A18: Trade receivables | B18: WC Schedule | C18: 10780.25 | D18: 14796.95 | E18: 15873.78 | F18: 14321.51 | G18: ='WC Schedule '!G47 -> 20798.883 | H18: ='WC Schedule '!H47 -> 23151.693 | I18: ='WC Schedule '!I47 -> 26272.793 | J18: ='WC Schedule '!J47 -> 30242.165 | K18: ='WC Schedule '!K47 -> 35179.981
A19: Cash and cash equivalents | B19: CFS | C19: 15272.6 | D19: 1670.34 | E19: 5691.91 | F19: 6939.1 | G19: =CFS!G60 -> 13673.698 | H19: =CFS!H60 -> 21073.936 | I19: =CFS!I60 -> 21020.624 | J19: =CFS!J60 -> 46714.392 | K19: =CFS!K60 -> 76591.321
A20: Bank balances (other than cash) | B20: Constant | C20: 17100.96 | D20: 49156.33 | E20: 48517.08 | F20: 47430.52 | G20: 47430.52 | H20: 47430.52 | I20: 47430.52 | J20: 47430.52 | K20: 47430.52
A21: Loans | B21: Constant | C21: 2282.09 | D21: 2621.31 | E21: 2209.22 | F21: 1925.33 | G21: 1925.33 | H21: 1925.33 | I21: 1925.33 | J21: 1925.33 | K21: 1925.33
A22: Other financial assets | B22: Constant | C22: 793.02 | D22: 2195.84 | E22: 311.7 | F22: 326.64 | G22: 326.64 | H22: 326.64 | I22: 326.64 | J22: 326.64 | K22: 326.64
A23: Current tax assets (net) | B23: Constant | C23: 2566.85 | D23: 3013.25 | E23: 2750.12 | F23: 3587.66 | G23: 3587.66 | H23: 3587.66 | I23: 3587.66 | J23: 3587.66 | K23: 3587.66
A24: Other current assets | B24: Constant | C24: 10782.24 | D24: 11446.1 | E24: 11153.33 | F24: 10594.83 | G24: 10594.83 | H24: 10594.83 | I24: 10594.83 | J24: 10594.83 | K24: 10594.83
A25: Total current assets | C25: =SUM(C16:C24) -> 123198.21 | D25: =SUM(D16:D24) -> 125203.14 | E25: =SUM(E16:E24) -> 122205.36 | F25: =SUM(F16:F24) -> 120267.82 | G25: =SUM(G16:G24) -> 124518.02 | H25: =SUM(H16:H24) -> 136290.51 | I25: =SUM(I16:I24) -> 142043.26 | J25: =SUM(J16:J24) -> 175126.75 | K25: =SUM(K16:K24) -> 214205.21
A27: TOTAL ASSETS | C27: =C14+C25 -> 168787.43 | D27: =D14+D25 -> 170410.56 | E27: =E14+E25 -> 203378.48 | F27: =F14+F25 -> 209515.94 | G27: =G14+G25 -> 234243.76 | H27: =H14+H25 -> 263678.74 | I27: =I14+I25 -> 284121.74 | J27: =J14+J25 -> 310935.48 | K27: =K14+K25 -> 343484.35
A29: EQUITY AND LIABILITIES
A30: Equity
A31: Equity share capital | B31: Constant | C31: 1928.09 | D31: 1928.09 | E31: 1928.09 | F31: 1928.09 | G31: 1928.09 | H31: 1928.09 | I31: 1928.09 | J31: 1928.09 | K31: 1928.09
A32: Other equity | B32: Opening + EAESH | C32: 135841.62 | D32: 132282.92 | E32: 144984.18 | F32: 156409.8 | G32: =F32+IS!G21 -> 181535.32 | H32: =G32+IS!H21 -> 208420.08 | I32: =H32+IS!I21 -> 228345.45 | J32: =I32+IS!J21 -> 254315.42 | K32: =J32+IS!K21 -> 284921.66
A33: Equity attributable to owners | C33: =SUM(C31:C32) -> 137769.71 | D33: =SUM(D31:D32) -> 134211.01 | E33: =SUM(E31:E32) -> 146912.27 | F33: =SUM(F31:F32) -> 158337.89 | G33: =SUM(G31:G32) -> 183463.41 | H33: =SUM(H31:H32) -> 210348.17 | I33: =SUM(I31:I32) -> 230273.54 | J33: =SUM(J31:J32) -> 256243.51 | K33: =SUM(K31:K32) -> 286849.75
A34: Non-controlling interest | B34: Constant | C34: 323.42 | D34: 338.52 | E34: 344.58 | F34: 338.22 | G34: 338.22 | H34: 338.22 | I34: 338.22 | J34: 338.22 | K34: 338.22
A35: Total equity | C35: =SUM(C33:C34) -> 138093.13 | D35: =SUM(D33:D34) -> 134549.53 | E35: =SUM(E33:E34) -> 147256.85 | F35: =SUM(F33:F34) -> 158676.11 | G35: =SUM(G33:G34) -> 183801.63 | H35: =SUM(H33:H34) -> 210686.39 | I35: =SUM(I33:I34) -> 230611.76 | J35: =SUM(J33:J34) -> 256581.73 | K35: =SUM(K33:K34) -> 287187.97
A37: Non-current liabilities
A38: Lease liabilities | B38: Lease Schedule | C38: 71.25 | D38: 13.78 | E38: 225.65 | F38: 141.43 | G38: ='Lease Schedule '!G29 -> 105.2835 | H38: ='Lease Schedule '!H29 -> 73.7813 | I38: ='Lease Schedule '!I29 -> 51.70497 | J38: ='Lease Schedule '!J29 -> 36.234168 | K38: ='Lease Schedule '!K29 -> 25.392431
A39: Other financial liabilities | B39: Constant | C39: 0 | D39: 0 | E39: 20895 | F39: 3094 | G39: 3094 | H39: 3094 | I39: 3094 | J39: 3094 | K39: 3094
A40: Provisions | B40: Constant | C40: 418.95 | D40: 414.26 | E40: 569.53 | F40: 586.21 | G40: 586.21 | H40: 586.21 | I40: 586.21 | J40: 586.21 | K40: 586.21
A41: Deferred tax liabilities (net) | B41: Constant | C41: 5616.02 | D41: 4637.73 | E41: 4744.47 | F41: 5182.28 | G41: 5182.28 | H41: 5182.28 | I41: 5182.28 | J41: 5182.28 | K41: 5182.28
A42: Total non-current liabilities | C42: =SUM(C38:C41) -> 6106.22 | D42: =SUM(D38:D41) -> 5065.77 | E42: =SUM(E38:E41) -> 26434.65 | F42: =SUM(F38:F41) -> 9003.92 | G42: =SUM(G38:G41) -> 8967.7735 | H42: =SUM(H38:H41) -> 8936.2713 | I42: =SUM(I38:I41) -> 8914.195 | J42: =SUM(J38:J41) -> 8898.7242 | K42: =SUM(K38:K41) -> 8887.8824
A44: Current liabilities
A45: Borrowings | B45: Constant | C45: 0 | D45: 0 | E45: 165.02 | F45: 0 | G45: 0 | H45: 0 | I45: 0 | J45: 0 | K45: 0
A46: Lease liabilities | B46: Lease Schedule | C46: 59.06 | D46: 57.47 | E46: 152.67 | F46: 129.12 | G46: ='Lease Schedule '!G28 -> 84.307398 | H46: ='Lease Schedule '!H28 -> 59.081523 | I46: ='Lease Schedule '!I28 -> 41.403559 | J46: ='Lease Schedule '!J28 -> 29.015073 | K46: ='Lease Schedule '!K28 -> 20.333384
A47: Trade Payables - MSME & Others | B47: WC Schedule | C47: 6452.39 | D47: 7027.26 | E47: 9335.89 | F47: 12754.61 | G47: ='WC Schedule '!G58 -> 12437.847 | H47: ='WC Schedule '!H58 -> 15044.794 | I47: ='WC Schedule '!I58 -> 15602.173 | J47: ='WC Schedule '!J58 -> 16473.811 | K47: ='WC Schedule '!K58 -> 18435.971
A48: Other financial liabilities | B48: Constant | C48: 4305.57 | D48: 5654.42 | E48: 6098.71 | F48: 8119.96 | G48: 8119.96 | H48: 8119.96 | I48: 8119.96 | J48: 8119.96 | K48: 8119.96
A49: Other current liabilities | B49: Constant | C49: 4661.37 | D49: 8760.65 | E49: 6554.73 | F49: 13187.04 | G49: 13187.04 | H49: 13187.04 | I49: 13187.04 | J49: 13187.04 | K49: 13187.04
A50: Provisions | B50: Constant | C50: 9096.33 | D50: 9206.22 | E50: 6500.43 | F50: 7307.9 | G50: 7307.9 | H50: 7307.9 | I50: 7307.9 | J50: 7307.9 | K50: 7307.9
A51: Current tax liabilities (net) | B51: Constant | C51: 13.36 | D51: 89.24 | E51: 879.53 | F51: 337.3 | G51: 337.3 | H51: 337.3 | I51: 337.3 | J51: 337.3 | K51: 337.3
A52: Total current liabilities | C52: =SUM(C45:C51) -> 24588.08 | D52: =SUM(D45:D51) -> 30795.26 | E52: =SUM(E45:E51) -> 29686.98 | F52: =SUM(F45:F51) -> 41835.93 | G52: =SUM(G45:G51) -> 41474.355 | H52: =SUM(H45:H51) -> 44056.075 | I52: =SUM(I45:I51) -> 44595.777 | J52: =SUM(J45:J51) -> 45455.026 | K52: =SUM(K45:K51) -> 47408.504
A54: TOTAL LIABILITIES | C54: =C42+C52 -> 30694.3 | D54: =D42+D52 -> 35861.03 | E54: =E42+E52 -> 56121.63 | F54: =F42+F52 -> 50839.85 | G54: =G42+G52 -> 50442.128 | H54: =H42+H52 -> 52992.346 | I54: =I42+I52 -> 53509.972 | J54: =J42+J52 -> 54353.75 | K54: =K42+K52 -> 56296.387
A56: TOTAL EQUITY AND LIABILITIES | C56: =C54+C35 -> 168787.43 | D56: =D54+D35 -> 170410.56 | E56: =E54+E35 -> 203378.48 | F56: =F54+F35 -> 209515.96 | G56: =G54+G35 -> 234243.76 | H56: =H54+H35 -> 263678.74 | I56: =I54+I35 -> 284121.74 | J56: =J54+J35 -> 310935.48 | K56: =K54+K35 -> 343484.35
B57: Asset=Liability | G57: =G27=G56 -> TRUE | H57: =H27=H56 -> TRUE | I57: =I27=I56 -> TRUE | J57: =J27=J56 -> TRUE | K57: =K27=K56 -> TRUE
B58: Any difference | G58: =G27-G56 -> 0 | H58: =H27-H56 -> 0 | I58: =I27-I56 -> 0 | J58: =J27-J56 -> 0 | K58: =K27-K56 -> 0

Sheet IS
A1: Income Statement
A2: Figures in Lakhs ,expect otherwise stated
A3: Particular/Years | B3: Comments | C3: 2021-22 A | D3: 2022-23 A | E3: 2023-24 A | F3: 2024-25 A | G3: 2025-26 E | H3: 2026-27 E | I3: 2027-28 E | J3: 2028-29 E | K3: 2029-30 E
A4: Revenue from operations | C4: 58062.76 | D4: 73662.12 | E4: 80300.4 | F4: 117135.76 | G4: ='Revenue Model'!G5 -> 126526.54 | H4: ='Revenue Model'!H5 -> 140839.47 | I4: ='Revenue Model'!I5 -> 159826.15 | J4: ='Revenue Model'!J5 -> 183973.17 | K4: ='Revenue Model'!K5 -> 214011.55
A5: Cost of Music Business | B5: Opening - Transferred from arrangement+Purchase-Closing | C5: ='WC Schedule '!C10 -> 6912.28 | D5: ='WC Schedule '!D10 -> 9090.75 | E5: ='WC Schedule '!E10 -> 10693.99 | F5: ='WC Schedule '!F10 -> 8708.41 | G5: ='Cost Model '!G5 -> 12027.589 | H5: ='Cost Model '!H5 -> 14099.201 | I5: ='Cost Model '!I5 -> 16769.356 | J5: ='Cost Model '!J5 -> 20104.888 | K5: ='Cost Model '!K5 -> 24207.853
A6: Cost of Films, Tv serials and Digital content (under production and untelecasted) | B6: Opening+Purchase-Closing | C6: ='WC Schedule '!C16 -> 7398.35 | D6: ='WC Schedule '!D16 -> 13413.68 | E6: ='WC Schedule '!E16 -> 12510.53 | F6: ='WC Schedule '!F16 -> 45600.27 | G6: ='Cost Model '!G15 -> 38199.306 | H6: ='Cost Model '!H15 -> 38794.86 | I6: ='Cost Model '!I15 -> 37493.608 | J6: ='Cost Model '!J15 -> 36604.174 | K6: ='Cost Model '!K15 -> 38819.732
A7: Employee benefits expense | C7: 7344.7 | D7: 7499.89 | E7: 9316.06 | F7: 10749.67 | G7: ='Cost Model '!G24 -> 8073.2067 | H7: ='Cost Model '!H24 -> 11308.212 | I7: ='Cost Model '!I24 -> 15785.883 | J7: ='Cost Model '!J24 -> 21978.012 | K7: ='Cost Model '!K24 -> 30431.48
A8: Royalty expenses | C8: 6313.76 | D8: 6555.33 | E8: 6126.64 | F8: 6831.37 | G8: ='Cost Model '!G39 -> 7073.924 | H8: ='Cost Model '!H39 -> 8728.8623 | I8: ='Cost Model '!I39 -> 10029.449 | J8: ='Cost Model '!J39 -> 11409.412 | K8: ='Cost Model '!K39 -> 13054.199
A9: Advertisement and sales promotion | C9: 5205.33 | D9: 7710.99 | E9: 7598.01 | F9: 9041.17 | G9: ='Cost Model '!G44 -> 11581.474 | H9: ='Cost Model '!H44 -> 12891.593 | I9: ='Cost Model '!I44 -> 14629.52 | J9: ='Cost Model '!J44 -> 16839.792 | K9: ='Cost Model '!K44 -> 19589.324
A10: Other expenses | C10: 6176.07 | D10: 7293.41 | E10: 9400.07 | F10: 8506.01 | G10: ='Cost Model '!G49 -> 12496.347 | H10: ='Cost Model '!H49 -> 13642.214 | I10: ='Cost Model '!I49 -> 15395.502 | J10: ='Cost Model '!J49 -> 16767.841 | K10: ='Cost Model '!K49 -> 20496.829
A11: Earning Before Interest, Tax, Depriciation and Amortization | C11: =C4-SUM(C5:C10) -> 18712.27 | D11: =D4-SUM(D5:D10) -> 22098.07 | E11: =E4-SUM(E5:E10) -> 24655.1 | F11: =F4-SUM(F5:F10) -> 27698.86 | G11: =G4-SUM(G5:G10) -> 37074.691 | H11: =H4-SUM(H5:H10) -> 41374.525 | I11: =I4-SUM(I5:I10) -> 49722.838 | J11: =J4-SUM(J5:J10) -> 60269.054 | K11: =K4-SUM(K5:K10) -> 67412.135
A12: Depreciation and amortisation expense | C12: 1310.1 | D12: 2081.95 | E12: 3618.18 | F12: 5821.08 | G12: ='Depreciation & Finance Cost '!G29 -> 7974.5866 | H12: ='Depreciation & Finance Cost '!H29 -> 10738.498 | I12: ='Depreciation & Finance Cost '!I29 -> 13602.852 | J12: ='Depreciation & Finance Cost '!J29 -> 14395.803 | K12: ='Depreciation & Finance Cost '!K29 -> 15254.25
A13: Earning Before Interest and Tax (EBIT) | C13: =C11-C12 -> 17402.17 | D13: =D11-D12 -> 20016.12 | E13: =E11-E12 -> 21036.92 | F13: =F11-F12 -> 21877.78 | G13: =G11-G12 -> 29100.105 | H13: =H11-H12 -> 30636.027 | I13: =I11-I12 -> 36119.985 | J13: =J11-J12 -> 45873.251 | K13: =K11-K12 -> 52157.885
A14: Finance costs | C14: 451.94 | D14: 571.48 | E14: 324.21 | F14: 574.15 | G14: ='Depreciation & Finance Cost '!G37 -> 153.11296 | H14: ='Depreciation & Finance Cost '!H37 -> 144.20856 | I14: ='Depreciation & Finance Cost '!I37 -> 137.96847 | J14: ='Depreciation & Finance Cost '!J37 -> 133.5955 | K14: ='Depreciation & Finance Cost '!K37 -> 130.53098
A15: Exceptional Items (Net) | C15: 0 | D15: 0 | E15: 0 | F15: -496.21 | G15: 0 | H15: 0 | I15: 0 | J15: 0 | K15: 0
A16: Other income | C16: 3491.01 | D16: 5363.13 | E16: 6365.86 | F16: 5807.26 | G16: ='Other Income Schedule '!G19 -> 4982.564 | H16: ='Other Income Schedule '!H19 -> 5813.4197 | I16: ='Other Income Schedule '!I19 -> 7185.4836 | J16: ='Other Income Schedule '!J19 -> 10523.207 | K16: ='Other Income Schedule '!K19 -> 14279.788
A17: Earning before Tax (EBT) | C17: =C13-C14-C15+C16 -> 20441.24 | D17: =D13-D14-D15+D16 -> 24807.77 | E17: =E13-E14-E15+E16 -> 27078.57 | F17: =F13-F14-F15+F16 -> 27607.1 | G17: =G13-G14+G15+G16 -> 33929.556 | H17: =H13-H14+H15+H16 -> 36305.238 | I17: =I13-I14+I15+I16 -> 43167.5 | J17: =J13-J14+J15+J16 -> 56262.862 | K17: =K13-K14+K15+K16 -> 66307.142
A18: Tax Expense | C18: 5176.68 | D18: 6302.58 | E18: 7322.64 | F18: 7183.2 | G18: ='Cost Model '!G54 -> 8804.0365 | H18: ='Cost Model '!H54 -> 9420.4782 | I18: ='Cost Model '!I54 -> 11201.097 | J18: ='Cost Model '!J54 -> 14599.08 | K18: ='Cost Model '!K54 -> 17205.368
A19: Profit For the year | C19: =C17-C18 -> 15264.56 | D19: =D17-D18 -> 18505.19 | E19: =E17-E18 -> 19755.93 | F19: =F17-F18 -> 20423.9 | G19: =G17-G18 -> 25125.519 | H19: =H17-H18 -> 26884.76 | I19: =I17-I18 -> 31966.403 | J19: =J17-J18 -> 41663.782 | K19: =K17-K18 -> 49101.774
A20: Dividends | C20: 5784.28 | D20: 5784.28 | E20: 7712.38 | F20: 8676.4 | G20: ='Cost Model '!G59 -> 0 | H20: ='Cost Model '!H59 -> 0 | I20: ='Cost Model '!I59 -> 12041.028 | J20: ='Cost Model '!J59 -> 15693.814 | K20: ='Cost Model '!K59 -> 18495.539
A21: Earnings available to equity shareholders (EAESH) | C21: =C19-C20 -> 9480.28 | D21: =D19-D20 -> 12720.91 | E21: =E19-E20 -> 12043.55 | F21: =F19-F20 -> 11747.5 | G21: =G19-G20 -> 25125.519 | H21: =H19-H20 -> 26884.76 | I21: =I19-I20 -> 19925.375 | J21: =J19-J20 -> 25969.969 | K21: =K19-K20 -> 30606.235
A24: Other comprehensive income
A25: Items that will be reclassified to profit or loss:
A26: (a) Exchange differences on translation of foreign operations | C26: 26.4 | D26: 176.41 | E26: 45.83 | F26: 22.88 | G26: 0 | H26: 0 | I26: 0 | J26: 0 | K26: 0
A27: Items that will not be reclassified subsequently to profit or loss:
A28: (a) Remeasurements of post-employment benefit obligations | C28: 115.37 | D28: 8.02 | E28: -138.23 | F28: -78.2 | G28: 0 | H28: 0 | I28: 0 | J28: 0 | K28: 0
A29: (b) Changes in fair value of equity instruments designated at FVOCI | C29: 3385.69 | D29: 0 | E29: 0 | F29: 0 | G29: 0 | H29: 0 | I29: 0 | J29: 0 | K29: 0
A30: (c) Revaluation gains relating to property, plant and equipment | C30: 959.44 | D30: 0 | E30: 0 | F30: 0 | G30: 0 | H30: 0 | I30: 0 | J30: 0 | K30: 0
A31: (d) Income tax relating to items that will not be reclassified subsequently to profit or loss | C31: -643.37 | D31: -2.02 | E31: 36.42 | F31: 20.75 | G31: 0 | H31: 0 | I31: 0 | J31: 0 | K31: 0
A32: Other comprehensive income for the year, net of tax | C32: =SUM(C26:C31) -> 3843.53 | D32: =SUM(D26:D31) -> 182.41 | E32: =SUM(E26:E31) -> -55.98 | F32: =SUM(F26:F31) -> -34.57 | G32: =SUM(G26:G31) -> 0 | H32: =SUM(H26:H31) -> 0 | I32: =SUM(I26:I31) -> 0 | J32: =SUM(J26:J31) -> 0 | K32: =SUM(K26:K31) -> 0
A34: Total comprehensive income for the year | C34: =C19+C32 -> 19108.09 | D34: =D19+D32 -> 18687.6 | E34: =E19+E32 -> 19699.95 | F34: =F19+F32 -> 20389.33 | G34: =G19+G32 -> 25125.519 | H34: =H19+H32 -> 26884.76 | I34: =I19+I32 -> 31966.403 | J34: =J19+J32 -> 41663.782 | K34: =K19+K32 -> 49101.774

Sheet CFS
A1: Cash Flow Statement
A2: Figures in Lakhs ,expect otherwise stated
A3: Particular/Years | B3: Comments | C3: 2021-22 A | D3: 2022-23 A | E3: 2023-24 A | F3: 2024-25 A | G3: 2025-26 E | H3: 2026-27 E | I3: 2027-28 E | J3: 2028-29 E | K3: 2029-30 E
A5: A. CASH FLOW FROM OPERATING ACTIVITIES
A6: Profit Before Tax | C6: 20441.24 | D6: 24807.77 | E6: 27078.57 | F6: 27607.1 | G6: =IS!G17 -> 33929.556 | H6: =IS!H17 -> 36305.238 | I6: =IS!I17 -> 43167.5 | J6: =IS!J17 -> 56262.862 | K6: =IS!K17 -> 66307.142
A7: Adjustments for:
A8: Depreciation and amortisation expense | C8: 1310.1 | D8: 2081.95 | E8: 3618.18 | F8: 5821.08 | G8: =IS!G12 -> 7974.5866 | H8: =IS!H12 -> 10738.498 | I8: =IS!I12 -> 13602.852 | J8: =IS!J12 -> 14395.803 | K8: =IS!K12 -> 15254.25
A9: Allowance for expected credit loss / provision for doubtful advances | C9: -29.75 | D9: 498.74 | E9: 11.28 | F9: -457.96 | G9: 0 | H9: 0 | I9: 0 | J9: 0 | K9: 0
A10: Finance costs | C10: 451.94 | D10: 571.48 | E10: 324.2 | F10: 574.15 | G10: =IS!G14 -> 153.11296 | H10: =IS!H14 -> 144.20856 | I10: =IS!I14 -> 137.96847 | J10: =IS!J14 -> 133.5955 | K10: =IS!K14 -> 130.53098
A11: Liabilities/Provisions no longer required written back | C11: -28.89 | D11: -2823.59 | E11: -4192.26 | F11: -370.85 | G11: 0 | H11: 0 | I11: 0 | J11: 0 | K11: 0
A12: Intangible assets under development written off | C12: 0 | D12: 0 | E12: 267.43 | F12: 0 | G12: 0 | H12: 0 | I12: 0 | J12: 0 | K12: 0
A13: Interest income | C13: -1840.51 | D13: -2950.35 | E13: -4089.65 | F13: -4188.83 | G13: =-IS!G16 -> -4982.564 | H13: =-IS!H16 -> -5813.4197 | I13: =-IS!I16 -> -7185.4836 | J13: =-IS!J16 -> -10523.207 | K13: =-IS!K16 -> -14279.788
A14: Share based payment expense | C14: 75.7 | D14: 306.75 | E14: 965.76 | F14: 469.07 | G14: 0 | H14: 0 | I14: 0 | J14: 0 | K14: 0
A15: Bad debts/advances written off | C15: 0.69 | D15: 4.21 | E15: 725.81 | F15: 207.22 | G15: 0 | H15: 0 | I15: 0 | J15: 0 | K15: 0
A16: Loss on disposal of Property, plant and equipment | C16: 0 | D16: 0 | E16: 1.88 | F16: 0 | G16: 0 | H16: 0 | I16: 0 | J16: 0 | K16: 0
A17: Profit on sale of Property, plant and equipment | C17: 0 | D17: 0 | E17: 0 | F17: -1.93 | G17: 0 | H17: 0 | I17: 0 | J17: 0 | K17: 0
A18: Profit on sale of Investment in Mutual Fund | C18: -48.3 | D18: -1439.27 | E18: -2134.99 | F18: -1305.82 | G18: 0 | H18: 0 | I18: 0 | J18: 0 | K18: 0
A19: Fair value gain on Mutual fund at FVTPL | C19: -555.76 | D19: -564.69 | E19: 505.31 | F19: -90.34 | G19: 0 | H19: 0 | I19: 0 | J19: 0 | K19: 0
A20: Net Loss on foreign currency transactions/translation | C20: -31.35 | D20: -1.39 | E20: 0.26 | F20: 13.83 | G20: 0 | H20: 0 | I20: 0 | J20: 0 | K20: 0
A21: Exceptional Item | C21: 0 | D21: 0 | E21: 0 | F21: -496.21 | G21: 0 | H21: 0 | I21: 0 | J21: 0 | K21: 0
A22: Dividend income from equity investments designated at FVOCI | C22: -695.29 | D22: 0 | E22: 0 | F22: 0 | G22: 0 | H22: 0 | I22: 0 | J22: 0 | K22: 0
A23: Operating profit before Working Capital Changes | C23: =SUM(C6,C8:C22) -> 19049.82 | D23: =SUM(D6,D8:D22) -> 20491.61 | E23: =SUM(E6,E8:E22) -> 23081.78 | F23: =SUM(F6,F8:F22) -> 27780.51 | G23: =SUM(G6,G8:G22) -> 37074.691 | H23: =SUM(H6,H8:H22) -> 41374.525 | I23: =SUM(I6,I8:I22) -> 49722.838 | J23: =SUM(J6,J8:J22) -> 60269.054 | K23: =SUM(K6,K8:K22) -> 67412.135
A24: Changes in working capital
A25: Decrease in Other current assets, Loans, Other non-current assets, Investments, other financial asset | C25: -4839.15 | D25: -1488.68 | E25: 408.36 | F25: 676.86 | G25: =('Balance Sheet'!F24-'Balance Sheet'!G24)+('Balance Sheet'!F21-'Balance Sheet'!G21)+('Balance Sheet'!F17-'Balance Sheet'!G17)+('Balance Sheet'!F22-'Balance Sheet'!G22) -> 0 | H25: =('Balance Sheet'!G24-'Balance Sheet'!H24)+('Balance Sheet'!G21-'Balance Sheet'!H21)+('Balance Sheet'!G17-'Balance Sheet'!H17)+('Balance Sheet'!G22-'Balance Sheet'!H22) -> 0 | I25: =('Balance Sheet'!H24-'Balance Sheet'!I24)+('Balance Sheet'!H21-'Balance Sheet'!I21)+('Balance Sheet'!H17-'Balance Sheet'!I17)+('Balance Sheet'!H22-'Balance Sheet'!I22) -> 0 | J25: =('Balance Sheet'!I24-'Balance Sheet'!J24)+('Balance Sheet'!I21-'Balance Sheet'!J21)+('Balance Sheet'!I17-'Balance Sheet'!J17)+('Balance Sheet'!I22-'Balance Sheet'!J22) -> 0 | K25: =('Balance Sheet'!J24-'Balance Sheet'!K24)+('Balance Sheet'!J21-'Balance Sheet'!K21)+('Balance Sheet'!J17-'Balance Sheet'!K17)+('Balance Sheet'!J22-'Balance Sheet'!K22) -> 0
A26: Increase / (Decrease) in Other financial liabilities, Provisions, Other current liabilities | C26: 5763.86 | D26: 7829.15 | E26: -3670.29 | F26: 7635.82 | G26: =('Balance Sheet'!G48-'Balance Sheet'!F48)+('Balance Sheet'!G49-'Balance Sheet'!F49)+('Balance Sheet'!G50-'Balance Sheet'!F50) -> 0 | H26: =('Balance Sheet'!H48-'Balance Sheet'!G48)+('Balance Sheet'!H49-'Balance Sheet'!G49)+('Balance Sheet'!H50-'Balance Sheet'!G50) -> 0 | I26: =('Balance Sheet'!I48-'Balance Sheet'!H48)+('Balance Sheet'!I49-'Balance Sheet'!H49)+('Balance Sheet'!I50-'Balance Sheet'!H50) -> 0 | J26: =('Balance Sheet'!J48-'Balance Sheet'!I48)+('Balance Sheet'!J49-'Balance Sheet'!I49)+('Balance Sheet'!J50-'Balance Sheet'!I50) -> 0 | K26: =('Balance Sheet'!K48-'Balance Sheet'!J48)+('Balance Sheet'!K49-'Balance Sheet'!J49)+('Balance Sheet'!K50-'Balance Sheet'!J50) -> 0
A27: Increase in Trade payables | C27: 821.99 | D27: 519.73 | E27: 501.85 | F27: 3392.77 | G27: ='Balance Sheet'!G47-'Balance Sheet'!F47 -> -316.76269 | H27: ='Balance Sheet'!H47-'Balance Sheet'!G47 -> 2606.9462 | I27: ='Balance Sheet'!I47-'Balance Sheet'!H47 -> 557.37971 | J27: ='Balance Sheet'!J47-'Balance Sheet'!I47 -> 871.63758 | K27: ='Balance Sheet'!K47-'Balance Sheet'!J47 -> 1962.1602
A28: Decrease in Trade receivables | C28: -2002.44 | D28: -5002.72 | E28: 403.99 | F28: 1792.59 | G28: ='Balance Sheet'!F18-'Balance Sheet'!G18 -> -6477.373 | H28: ='Balance Sheet'!G18-'Balance Sheet'!H18 -> -2352.8103 | I28: ='Balance Sheet'!H18-'Balance Sheet'!I18 -> -3121.0993 | J28: ='Balance Sheet'!I18-'Balance Sheet'!J18 -> -3969.3728 | K28: ='Balance Sheet'!J18-'Balance Sheet'!K18 -> -4937.8157
A29: (Increase) in Inventories | C29: -3624.52 | D29: -6325.53 | E29: -6261.13 | F29: -95.65 | G29: ='Balance Sheet'!F16-'Balance Sheet'!G16 -> 8961.766 | H29: ='Balance Sheet'!G16-'Balance Sheet'!H16 -> -2019.4358 | I29: ='Balance Sheet'!H16-'Balance Sheet'!I16 -> -2684.9685 | J29: ='Balance Sheet'!I16-'Balance Sheet'!J16 -> -3420.3473 | K29: ='Balance Sheet'!J16-'Balance Sheet'!K16 -> -4263.7089
A30: Income taxes paid (net of refund) | C30: -5716.68 | D30: -6680.53 | E30: -5140.02 | F30: -8063.34 | G30: =-IS!G18 -> -8804.0365 | H30: =-IS!H18 -> -9420.4782 | I30: =-IS!I18 -> -11201.097 | J30: =-IS!J18 -> -14599.08 | K30: =-IS!K18 -> -17205.368
A31: Net cash generated from Operating Activities | C31: 9442.52 | D31: =SUM(D23,D25:D30) -> 9343.03 | E31: =SUM(E23,E25:E30) -> 9324.54 | F31: =SUM(F23,F25:F30) -> 33119.56 | G31: =SUM(G23,G25:G30) -> 30438.285 | H31: =SUM(H23,H25:H30) -> 30188.747 | I31: =SUM(I23,I25:I30) -> 33273.052 | J31: =SUM(J23,J25:J30) -> 39151.891 | K31: =SUM(K23,K25:K30) -> 42967.403
A33: B. CASH FLOW FROM INVESTING ACTIVITIES
A34: Purchase of Property, plant and equipment and intangible assets | C34: -7271.33 | D34: -10314.49 | E34: -9227.49 | F34: -16166.33 | G34: =-'Capex Schedule '!G334 -> -28452.179 | H34: =-'Capex Schedule '!H334 -> -28400.991 | I34: =-'Capex Schedule '!I334 -> -28293.097 | J34: =-'Capex Schedule '!J334 -> -8126.0611 | K34: =-'Capex Schedule '!K334 -> -8724.6694
A35: Sale of Property, plant and equipment | C35: 0 | D35: 0 | E35: 0 | F35: 10.73 | G35: 0 | H35: 0 | I35: 0 | J35: 0 | K35: 0
A36: Consideration paid for business combination | C36: 0 | D36: 0 | E36: -16618.92 | F36: -12747.12 | G36: 0 | H36: 0 | I36: 0 | J36: 0 | K36: 0
A37: Interest received | C37: 677.98 | D37: 1390.25 | E37: 5680.4 | F37: 4341.31 | G37: =IS!G16 -> 4982.564 | H37: =IS!H16 -> 5813.4197 | I37: =IS!I16 -> 7185.4836 | J37: =IS!J16 -> 10523.207 | K37: =IS!K16 -> 14279.788
A38: Investment in Mutual funds | C38: -61310.45 | D38: -39013.58 | E38: -22529.33 | F38: -31894.9 | G38: 0 | H38: 0 | I38: 0 | J38: 0 | K38: 0
A39: Fixed deposits (placed)/matured with banks (with maturity more than 3 months) | C39: -7175.29 | D39: -37092.89 | E39: 7605.28 | F39: 453.41 | G39: 0 | H39: 0 | I39: 0 | J39: 0 | K39: 0
A40: Proceeds from sale of Investment in Mutual funds | C40: 11354.53 | D40: 70216.46 | E40: 36749.48 | F40: 33942.7 | G40: 0 | H40: 0 | I40: 0 | J40: 0 | K40: 0
A41: Net cash used in Investing Activities | C41: -63029.27 | D41: =SUM(D34:D40) -> -14814.25 | E41: =SUM(E34:E40) -> 1659.42 | F41: =SUM(F34:F40) -> -22060.2 | G41: =SUM(G34:G40) -> -23469.615 | H41: =SUM(H34:H40) -> -22587.572 | I41: =SUM(I34:I40) -> -21107.614 | J41: =SUM(J34:J40) -> 2397.1459 | K41: =SUM(K34:K40) -> 5555.1186
A43: C. CASH FLOW FROM FINANCING ACTIVITIES
A44: Proceeds from issue of shares | C44: 185.29 | D44: 0 | E44: 0 | F44: 0 | G44: 0 | H44: 0 | I44: 0 | J44: 0 | K44: 0
A45: Share premium received on issue of shares | C45: 73135.21 | D45: 0 | E45: 0 | F45: 0 | G45: 0 | H45: 0 | I45: 0 | J45: 0 | K45: 0
A46: Proceeds from Short term borrowings | C46: 0 | D46: 0 | E46: 0 | F46: -165.02 | G46: 0 | H46: 0 | I46: 0 | J46: 0 | K46: 0
A47: Repayment of Short term borrowing | C47: 0 | D47: 0 | E47: -140.06 | F47: 0 | G47: 0 | H47: 0 | I47: 0 | J47: 0 | K47: 0
A48: Purchase of Investment by Saregama Welfare Trust | C48: 332.96 | D48: -1607.75 | E48: -219.4 | F48: -790.04 | G48: 0 | H48: 0 | I48: 0 | J48: 0 | K48: 0
A49: Repayment of principal payment of lease liability | C49: -41.85 | D49: -59.06 | E49: -111.14 | F49: -81.3 | G49: =-'Lease Schedule '!G25 -> -80.949104 | H49: =-'Lease Schedule '!H25 -> -56.728074 | I49: =-'Lease Schedule '!I25 -> -39.754293 | J49: =-'Lease Schedule '!J25 -> -27.859289 | K49: =-'Lease Schedule '!K25 -> -19.523426
A50: Interest paid on leased liability | C50: -11.19 | D50: -10.36 | E50: -4.48 | F50: -71.92 | G50: 0 | H50: 0 | I50: 0 | J50: 0 | K50: 0
A51: Interest paid | C51: -94.63 | D51: -62.22 | E51: -298.92 | F51: -88.23 | G51: =-IS!G14 -> -153.11296 | H51: =-IS!H14 -> -144.20856 | I51: =-IS!I14 -> -137.96847 | J51: =-IS!J14 -> -133.5955 | K51: =-IS!K14 -> -130.53098
A52: Interim Dividend paid | C52: -5784.28 | D52: -5784.28 | E52: -7712.38 | F52: -8676.43 | G52: =-IS!G20 -> 0 | H52: =-IS!H20 -> 0 | I52: =-IS!I20 -> -12041.028 | J52: =-IS!J20 -> -15693.814 | K52: =-IS!K20 -> -18495.539
A53: Net cash generated from Financing Activities | C53: =SUM(C44:C52) -> 67721.51 | D53: =SUM(D44:D52) -> -7523.67 | E53: =SUM(E44:E52) -> -8486.38 | F53: =SUM(F44:F52) -> -9872.94 | G53: =SUM(G44:G52) -> -234.06206 | H53: =SUM(H44:H52) -> -200.93663 | I53: =SUM(I44:I52) -> -12218.751 | J53: =SUM(J44:J52) -> -15855.269 | K53: =SUM(K44:K52) -> -18645.593
A55: Net decrease in cash and cash equivalents (A+B+C) | C55: =C53+C41+C31 -> 14134.76 | D55: =D53+D41+D31 -> -12994.89 | E55: =E53+E41+E31 -> 2497.58 | F55: =F53+F41+F31 -> 1186.42 | G55: =G53+G41+G31 -> 6734.6076 | H55: =H53+H41+H31 -> 7400.2385 | I55: =I53+I41+I31 -> -53.31218 | J55: =J53+J41+J31 -> 25693.769 | K55: =K53+K41+K31 -> 29876.928
A56: Cash and Cash Equivalents at the beginning of the year | C56: 1113.49 | D56: 15272.6 | E56: 1670.33 | F56: 5691.91 | G56: =F60 -> 6939.09 | H56: =G60 -> 13673.698 | I56: =H60 -> 21073.936 | J56: =I60 -> 21020.624 | K56: =J60 -> 46714.392
A57: Add: Acquisition through Business Combination | C57: 0 | D57: 0 | E57: 1486.13 | F57: 0 | G57: 0 | H57: 0 | I57: 0 | J57: 0 | K57: 0
A58: Effect of exchange rate on translation of foreign currency cash and cash equivalents | C58: 24.35 | D58: 162.49 | E58: 37.87 | F58: 60.76 | G58: 0 | H58: 0 | I58: 0 | J58: 0 | K58: 0
A59: Less: transferred pursuant to scheme of arrangement | C59: 0 | D59: -769.86 | E59: 0 | F59: 0 | G59: 0 | H59: 0 | I59: 0 | J59: 0 | K59: 0
A60: Cash and Cash Equivalents at the end of the year | C60: =SUM(C55:C59) -> 15272.6 | D60: =SUM(D55:D59) -> 1670.34 | E60: =SUM(E55:E59) -> 5691.91 | F60: =SUM(F55:F59) -> 6939.09 | G60: =SUM(G55:G59) -> 13673.698 | H60: =SUM(H55:H59) -> 21073.936 | I60: =SUM(I55:I59) -> 21020.624 | J60: =SUM(J55:J59) -> 46714.392 | K60: =SUM(K55:K59) -> 76591.321

Sheet Revenue Model
A1: Revene Model
A2: Figures in Lakhs ,expect otherwise stated
A3: Particular/Years | B3: Comments | C3: 2021-22 A | D3: 2022-23 A | E3: 2023-24 A | F3: 2024-25 A | G3: 2025-26 E | H3: 2026-27 E | I3: 2027-28 E | J3: 2028-29 E | K3: 2029-30 E
A5: =IS!A4 -> Revenue from operations | C5: =IS!C4 -> 58062.76 | D5: =IS!D4 -> 73662.12 | E5: =IS!E4 -> 80300.4 | F5: =IS!F4 -> 117135.76 | G5: =SUM(G8:G14) -> 126526.54 | H5: =SUM(H8:H14) -> 140839.47 | I5: =SUM(I8:I14) -> 159826.15 | J5: =SUM(J8:J14) -> 183973.17 | K5: =SUM(K8:K14) -> 214011.55
A7: Segment Wise Revenue Breakup
A8: Sale of product | B8: Carvaan and others | C8: 10167.72 | D8: 12760.93 | E8: 12962 | F8: 8154.52 | G8: =G18 -> 5218.8928 | H8: =H18 -> 3340.0914 | I8: =I18 -> 2137.6585 | J8: =J18 -> 1368.1014 | K8: =K18 -> 875.58492
A9: Sale of service-
A10: License Fees- Music | C10: 36328.85 | D10: 42122.5 | E10: 47828.58 | F10: 53860.92 | G10: =G26 -> 64308.4 | H10: =H26 -> 79353.293 | I10: =I26 -> 91176.806 | J10: =J26 -> 103721.92 | K10: =K26 -> 118674.53
A11: Artist Management | C11: 0 | D11: 0 | E11: 2075.82 | F11: 6931.24 | G11: =G77 -> 9250.114 | H11: =H77 -> 9652.508 | I11: =I77 -> 16520.213 | J11: =J77 -> 26591.471 | K11: =K77 -> 39004.672
A12: Income from videos | B12: Films, Tv and digital content | C12: 10239.13 | D12: 10846.29 | E12: 11586.66 | F12: 19197.76 | G12: =G82 -> 22077.424 | H12: =H82 -> 25389.038 | I12: =I82 -> 29197.393 | J12: =J82 -> 33577.002 | K12: =K82 -> 38613.553
A13: Income from events | C13: 0 | D13: 4895.66 | E13: 1344.17 | F13: 28524.12 | G13: =G85 -> 25671.708 | H13: =H85 -> 23104.537 | I13: =I85 -> 20794.083 | J13: =J85 -> 18714.675 | K13: =K85 -> 16843.208
A14: Other operating income | B14: Amount written back | C14: =884.21+442.85 -> 1327.06 | D14: 3036.74 | E14: 4503.17 | F14: 467.2 | G14: =G88 -> 0 | H14: =H88 -> 0 | I14: =I88 -> 0 | J14: =J88 -> 0 | K14: =K88 -> 0
A16: Sale of Product-
A18: =A8 -> Sale of product | C18: =C8 -> 10167.72 | D18: =D8 -> 12760.93 | E18: =E8 -> 12962 | F18: =F8 -> 8154.52 | G18: =G19*G20 -> 5218.8928 | H18: =H19*H20 -> 3340.0914 | I18: =I19*I20 -> 2137.6585 | J18: =J19*J20 -> 1368.1014 | K18: =K19*K20 -> 875.58492
A19: Carvaan Sale ( In Lakhs) | C19: 4.01 | D19: 5.61 | E19: 6.86 | F19: 4.34 | G19: =F19*(1+G21) -> 3.472 | H19: =G19*(1+H21) -> 2.7776 | I19: =H19*(1+I21) -> 2.22208 | J19: =I19*(1+J21) -> 1.777664 | K19: =J19*(1+K21) -> 1.4221312
A20: Average Selling Price (In Rs.) | C20: =C8/C19 -> 2535.591 | D20: =D8/D19 -> 2274.6756 | E20: =E8/E19 -> 1889.5044 | F20: =F8/F19 -> 1878.9217 | G20: =F20*(1+G22) -> 1503.1373 | H20: =G20*(1+H22) -> 1202.5099 | I20: =H20*(1+I22) -> 962.00789 | J20: =I20*(1+J22) -> 769.60631 | K20: =J20*(1+K22) -> 615.68505
A21: Y-o-Y Growth in Sale in Quantity of Products | C21: - | D21: =D19/C19-1 -> 0.39900249 | E21: =E19/D19-1 -> 0.2228164 | F21: =F19/E19-1 -> -0.36734694 | G21: ='Assumption Sheet'!G8 -> -0.2 | H21: ='Assumption Sheet'!H8 -> -0.2 | I21: ='Assumption Sheet'!I8 -> -0.2 | J21: ='Assumption Sheet'!J8 -> -0.2 | K21: ='Assumption Sheet'!K8 -> -0.2
A22: Y-o-Y Growth in Average Selling Price of Products | C22: - | D22: =D20/C20-1 -> -0.10290123 | E22: =E20/D20-1 -> -0.16933017 | F22: =F20/E20-1 -> -0.0056007884 | G22: ='Assumption Sheet'!G9 -> -0.2 | H22: ='Assumption Sheet'!H9 -> -0.2 | I22: ='Assumption Sheet'!I9 -> -0.2 | J22: ='Assumption Sheet'!J9 -> -0.2 | K22: ='Assumption Sheet'!K9 -> -0.2
A24: Sale of Service-
A26: =A10 -> License Fees- Music | C26: =C10 -> 36328.85 | D26: =D10 -> 42122.5 | E26: =E10 -> 47828.58 | F26: =F10 -> 53860.92 | G26: =SUM(G36:G40) -> 64308.4 | H26: =SUM(H36:H40) -> 79353.293 | I26: =SUM(I36:I40) -> 91176.806 | J26: =SUM(J36:J40) -> 103721.92 | K26: =SUM(K36:K40) -> 118674.53
A28: Era wise Segment (Revenue in %)
A29: 2021-2024 | C29: 0 | D29: 0.27 | E29: 0.33 | F29: 0.4
A30: 2001-2020 | C30: 0.4 | D30: 0.207 | E30: 0.19 | F30: 0.16
A31: 1981-2000 | C31: 0.26 | D31: 0.207 | E31: 0.2 | F31: 0.18
A32: 1961-1980 | C32: 0.31 | D32: 0.29 | E32: 0.25 | F32: 0.23
A33: Till 1960 | C33: 0.03 | D33: 0.026 | E33: 0.03 | F33: 0.03
A35: Era wise Segment (Revenue in Number in Lakhs )
A36: 2021-2024 | C36: =C29*C$26 -> 0 | D36: =D29*D$26 -> 11373.075 | E36: =E29*E$26 -> 15783.431 | F36: =F29*F$26 -> 21544.368 | G36: =G58*G69 -> 30085.171 | H36: =H58*H69 -> 43110.28 | I36: =I58*I69 -> 52794.166 | J36: =J58*J69 -> 63072.676 | K36: =K58*K69 -> 75624.139
A37: 2001-2020 | C37: =C30*C$26 -> 14531.54 | D37: =D30*D$26 -> 8719.3575 | E37: =E30*E$26 -> 9087.4302 | F37: =F30*F$26 -> 8617.7472 | G37: =F37*(1+G44) -> 9134.812 | H37: =G37*(1+H44) -> 9682.9008 | I37: =H37*(1+I44) -> 10263.875 | J37: =I37*(1+J44) -> 10879.707 | K37: =J37*(1+K44) -> 11532.49
A38: 1981-2000 | C38: =C31*C$26 -> 9445.501 | D38: =D31*D$26 -> 8719.3575 | E38: =E31*E$26 -> 9565.716 | F38: =F31*F$26 -> 9694.9656 | G38: =F38*(1+G45) -> 10276.664 | H38: =G38*(1+H45) -> 10893.263 | I38: =H38*(1+I45) -> 11546.859 | J38: =I38*(1+J45) -> 12239.671 | K38: =J38*(1+K45) -> 12974.051
A39: 1961-1980 | C39: =C32*C$26 -> 11261.943 | D39: =D32*D$26 -> 12215.525 | E39: =E32*E$26 -> 11957.145 | F39: =F32*F$26 -> 12388.012 | G39: =F39*(1+G46) -> 13131.292 | H39: =G39*(1+H46) -> 13919.17 | I39: =H39*(1+I46) -> 14754.32 | J39: =I39*(1+J46) -> 15639.579 | K39: =J39*(1+K46) -> 16577.954
A40: Till 1960 | C40: =C33*C$26 -> 1089.8655 | D40: =D33*D$26 -> 1095.185 | E40: =E33*E$26 -> 1434.8574 | F40: =F33*F$26 -> 1615.8276 | G40: =F40*(1+G47) -> 1680.4607 | H40: =G40*(1+H47) -> 1747.6791 | I40: =H40*(1+I47) -> 1817.5863 | J40: =I40*(1+J47) -> 1890.2897 | K40: =J40*(1+K47) -> 1965.9013
A42: Era wise Segment (YoY Growth in Revenue)
A43: 2021-2024 | C43: - | D43: - | E43: =E36/D36-1 -> 0.38778927 | F43: =F36/E36-1 -> 0.364999
A44: 2001-2020 | C44: - | D44: =D37/C37-1 -> -0.39997017 | E44: =E37/D37-1 -> 0.042213282 | F44: =F37/E37-1 -> -0.051684909 | G44: ='Assumption Sheet'!G13 -> 0.06 | H44: ='Assumption Sheet'!H13 -> 0.06 | I44: ='Assumption Sheet'!I13 -> 0.06 | J44: ='Assumption Sheet'!J13 -> 0.06 | K44: ='Assumption Sheet'!K13 -> 0.06
A45: 1981-2000 | C45: - | D45: =D38/C38-1 -> -0.076877182 | E45: =E38/D38-1 -> 0.097066613 | F45: =F38/E38-1 -> 0.013511754 | G45: ='Assumption Sheet'!G14 -> 0.06 | H45: ='Assumption Sheet'!H14 -> 0.06 | I45: ='Assumption Sheet'!I14 -> 0.06 | J45: ='Assumption Sheet'!J14 -> 0.06 | K45: ='Assumption Sheet'!K14 -> 0.06
A46: 1961-1980 | C46: - | D46: =D39/C39-1 -> 0.084672907 | E46: =E39/D39-1 -> -0.021151772 | F46: =F39/E39-1 -> 0.036034237 | G46: ='Assumption Sheet'!G15 -> 0.06 | H46: ='Assumption Sheet'!H15 -> 0.06 | I46: ='Assumption Sheet'!I15 -> 0.06 | J46: ='Assumption Sheet'!J15 -> 0.06 | K46: ='Assumption Sheet'!K15 -> 0.06
A47: Till 1960 | C47: - | D47: =D40/C40-1 -> 0.0048808775 | E47: =E40/D40-1 -> 0.31015071 | F47: =F40/E40-1 -> 0.12612417 | G47: ='Assumption Sheet'!G16 -> 0.04 | H47: ='Assumption Sheet'!H16 -> 0.04 | I47: ='Assumption Sheet'!I16 -> 0.04 | J47: ='Assumption Sheet'!J16 -> 0.04 | K47: ='Assumption Sheet'!K16 -> 0.04
A49: Era wise Segment (Count in %)
A50: 2021-2024 | C50: 0 | D50: 0.08 | E50: 0.14 | F50: 0.16
A51: 2001-2020 | C51: 0.29 | D51: 0.25 | E51: 0.22 | F51: 0.21
A52: 1981-2000 | C52: 0.29 | D52: 0.26 | E52: 0.235 | F52: 0.24
A53: 1961-1980 | C53: 0.27 | D53: 0.25 | E53: 0.235 | F53: 0.23
A54: Till 1960 | C54: 0.15 | D54: 0.16 | E54: 0.17 | F54: 0.16
A55: Total | C55: =SUM(C50:C54) -> 1 | D55: =SUM(D50:D54) -> 1 | E55: =SUM(E50:E54) -> 1 | F55: =SUM(F50:F54) -> 1
A57: Era wise Segment (Count in Number in Lakhs )
A58: 2021-2024 | C58: =C50*C$63 -> 0 | D58: =D50*D$63 -> 0.12 | E58: =E50*E$63 -> 0.224 | F58: =F50*F$63 -> 0.28 | G58: =F58+G65 -> 0.34 | H58: =G58+H65 -> 0.406 | I58: =H58+I65 -> 0.452 | J58: =I58+J65 -> 0.5 | K58: =J58+K65 -> 0.55
A59: 2001-2020 | C59: =C51*C$63 -> 0.4118 | D59: =D51*D$63 -> 0.375 | E59: =E51*E$63 -> 0.352 | F59: =F51*F$63 -> 0.3675
A60: 1981-2000 | C60: =C52*C$63 -> 0.4118 | D60: =D52*D$63 -> 0.39 | E60: =E52*E$63 -> 0.376 | F60: =F52*F$63 -> 0.42
A61: 1961-1980 | C61: =C53*C$63 -> 0.3834 | D61: =D53*D$63 -> 0.375 | E61: =E53*E$63 -> 0.376 | F61: =F53*F$63 -> 0.4025
A62: Till 1960 | C62: =C54*C$63 -> 0.213 | D62: =D54*D$63 -> 0.24 | E62: =E54*E$63 -> 0.272 | F62: =F54*F$63 -> 0.28
A63: Total Songs | C63: 1.42 | D63: 1.5 | E63: 1.6 | F63: 1.75
A65: Y-o-Y Increase in Number of Songs After 2021 | C65: - | D65: =D58-C58 -> 0.12 | E65: =E58-D58 -> 0.104 | F65: =F58-E58 -> 0.056 | G65: ='Assumption Sheet'!G18 -> 0.06 | H65: ='Assumption Sheet'!H18 -> 0.066 | I65: ='Assumption Sheet'!I18 -> 0.046 | J65: ='Assumption Sheet'!J18 -> 0.048 | K65: ='Assumption Sheet'!K18 -> 0.05
A68: Era wise Segment (Revenue per song in actual figures )
A69: 2021-2024 | C69: - | D69: =D36/D58 -> 94775.625 | E69: =E36/E58 -> 70461.747 | F69: =F36/F58 -> 76944.171 | G69: =F69*(1+G75) -> 88485.797 | H69: =G69*(1+H75) -> 106182.96 | I69: =H69*(1+I75) -> 116801.25 | J69: =I69*(1+J75) -> 126145.35 | K69: =J69*(1+K75) -> 137498.43
A70: 2001-2020 | C70: =C37/C59 -> 35287.858 | D70: =D37/D59 -> 23251.62 | E70: =E37/E59 -> 25816.563 | F70: =F37/F59 -> 23449.652
A71: 1981-2000 | C71: =C38/C60 -> 22937.108 | D71: =D38/D60 -> 22357.327 | E71: =E38/E60 -> 25440.734 | F71: =F38/F60 -> 23083.251
A72: 1961-1980 | C72: =C39/C61 -> 29373.875 | D72: =D39/D61 -> 32574.733 | E72: =E39/E61 -> 31800.918 | F72: =F39/F61 -> 30777.669
A73: Till 1960 | C73: =C40/C62 -> 5116.7394 | D73: =D40/D62 -> 4563.2708 | E73: =E40/E62 -> 5275.211 | F73: =F40/F62 -> 5770.8129
A75: Y-o-Y Increase in Revenue per song of Songs After 2021 | E75: =E69/D69-1 -> -0.25654146 | F75: =F69/E69-1 -> 0.091999196 | G75: ='Assumption Sheet'!G22 -> 0.15 | H75: ='Assumption Sheet'!H22 -> 0.2 | I75: ='Assumption Sheet'!I22 -> 0.1 | J75: ='Assumption Sheet'!J22 -> 0.08 | K75: ='Assumption Sheet'!K22 -> 0.09
A77: =A11 -> Artist Management | C77: =C11 -> 0 | D77: =D11 -> 0 | E77: =E11 -> 2075.82 | F77: =F11 -> 6931.24 | G77: =G78-G80 -> 9250.114 | H77: =H78-H80 -> 9652.508 | I77: =I78-I80 -> 16520.213 | J77: =J78-J80 -> 26591.471 | K77: =K78-K80 -> 39004.672
A78: Music Segment | B78: Consists of License Fees and Artist Management | C78: =C10+C11 -> 36328.85 | D78: =D10+D11 -> 42122.5 | E78: =E10+E11 -> 49904.4 | F78: =F10+F11 -> 60792.16 | G78: =F78*(1+G79) -> 73558.514 | H78: =G78*(1+H79) -> 89005.801 | I78: =H78*(1+I79) -> 107697.02 | J78: =I78*(1+J79) -> 130313.39 | K78: =J78*(1+K79) -> 157679.21
A79: Y-o-Y Growth in music Segment | D79: =D78/C78-1 -> 0.15947794 | E79: =E78/D78-1 -> 0.1847445 | F79: =F78/E78-1 -> 0.21817235 | G79: ='Assumption Sheet'!G25 -> 0.21 | H79: ='Assumption Sheet'!H25 -> 0.21 | I79: ='Assumption Sheet'!I25 -> 0.21 | J79: ='Assumption Sheet'!J25 -> 0.21 | K79: ='Assumption Sheet'!K25 -> 0.21
A80: =A10 -> License Fees- Music | C80: =C10 -> 36328.85 | D80: =D10 -> 42122.5 | E80: =E10 -> 47828.58 | F80: =F10 -> 53860.92 | G80: =G10 -> 64308.4 | H80: =H10 -> 79353.293 | I80: =I10 -> 91176.806 | J80: =J10 -> 103721.92 | K80: =K10 -> 118674.53
A82: =A12 -> Income from videos | C82: =C12 -> 10239.13 | D82: =D12 -> 10846.29 | E82: =E12 -> 11586.66 | F82: =F12 -> 19197.76 | G82: =F82*(1+G83) -> 22077.424 | H82: =G82*(1+H83) -> 25389.038 | I82: =H82*(1+I83) -> 29197.393 | J82: =I82*(1+J83) -> 33577.002 | K82: =J82*(1+K83) -> 38613.553
A83: Y-o-Y Growth in Video Segment | C83: - | D83: =D82/C82-1 -> 0.059298007 | E83: =E82/D82-1 -> 0.068260207 | F83: =F82/E82-1 -> 0.65688473 | G83: ='Assumption Sheet'!G28 -> 0.15 | H83: ='Assumption Sheet'!H28 -> 0.15 | I83: ='Assumption Sheet'!I28 -> 0.15 | J83: ='Assumption Sheet'!J28 -> 0.15 | K83: ='Assumption Sheet'!K28 -> 0.15
A85: =A13 -> Income from events | C85: =C13 -> 0 | D85: =D13 -> 4895.66 | E85: =E13 -> 1344.17 | F85: =F13 -> 28524.12 | G85: =F85*(1+G86) -> 25671.708 | H85: =G85*(1+H86) -> 23104.537 | I85: =H85*(1+I86) -> 20794.083 | J85: =I85*(1+J86) -> 18714.675 | K85: =J85*(1+K86) -> 16843.208
A86: Y-o-Y Growth in Events Segment | E86: =E85/D85-1 -> -0.72543641 | F86: =F85/E85-1 -> 20.220619 | G86: ='Assumption Sheet'!G31 -> -0.1 | H86: ='Assumption Sheet'!H31 -> -0.1 | I86: ='Assumption Sheet'!I31 -> -0.1 | J86: ='Assumption Sheet'!J31 -> -0.1 | K86: ='Assumption Sheet'!K31 -> -0.1
A88: =A14 -> Other operating income | C88: =C14 -> 1327.06 | D88: =D14 -> 3036.74 | E88: =E14 -> 4503.17 | F88: =F14 -> 467.2 | G88: ='Assumption Sheet'!G34 -> 0 | H88: ='Assumption Sheet'!H34 -> 0 | I88: ='Assumption Sheet'!I34 -> 0 | J88: ='Assumption Sheet'!J34 -> 0 | K88: ='Assumption Sheet'!K34 -> 0

Sheet Cost Model 
A1: Cost Model
A2: Figures in Lakhs ,expect otherwise stated
A3: Particular/Years | B3: Comments | C3: 2021-22 A | D3: 2022-23 A | E3: 2023-24 A | F3: 2024-25 A | G3: 2025-26 E | H3: 2026-27 E | I3: 2027-28 E | J3: 2028-29 E | K3: 2029-30 E
A5: =IS!A5 -> Cost of Music Business | C5: =IS!C5 -> 6912.28 | D5: =IS!D5 -> 9090.75 | E5: =IS!E5 -> 10693.99 | F5: =IS!F5 -> 8708.41 | G5: =G10*G12 -> 12027.589 | H5: =H10*H12 -> 14099.201 | I5: =I10*I12 -> 16769.356 | J5: =J10*J12 -> 20104.888 | K5: =K10*K12 -> 24207.853
A7: ='Revenue Model'!A8 -> Sale of product | C7: ='Revenue Model'!C8 -> 10167.72 | D7: ='Revenue Model'!D8 -> 12760.93 | E7: ='Revenue Model'!E8 -> 12962 | F7: ='Revenue Model'!F8 -> 8154.52 | G7: ='Revenue Model'!G8 -> 5218.8928 | H7: ='Revenue Model'!H8 -> 3340.0914 | I7: ='Revenue Model'!I8 -> 2137.6585 | J7: ='Revenue Model'!J8 -> 1368.1014 | K7: ='Revenue Model'!K8 -> 875.58492
A8: ='Revenue Model'!A10 -> License Fees- Music | C8: ='Revenue Model'!C10 -> 36328.85 | D8: ='Revenue Model'!D10 -> 42122.5 | E8: ='Revenue Model'!E10 -> 47828.58 | F8: ='Revenue Model'!F10 -> 53860.92 | G8: ='Revenue Model'!G10 -> 64308.4 | H8: ='Revenue Model'!H10 -> 79353.293 | I8: ='Revenue Model'!I10 -> 91176.806 | J8: ='Revenue Model'!J10 -> 103721.92 | K8: ='Revenue Model'!K10 -> 118674.53
A9: ='Revenue Model'!A11 -> Artist Management | C9: ='Revenue Model'!C11 -> 0 | D9: ='Revenue Model'!D11 -> 0 | E9: ='Revenue Model'!E11 -> 2075.82 | F9: ='Revenue Model'!F11 -> 6931.24 | G9: ='Revenue Model'!G11 -> 9250.114 | H9: ='Revenue Model'!H11 -> 9652.508 | I9: ='Revenue Model'!I11 -> 16520.213 | J9: ='Revenue Model'!J11 -> 26591.471 | K9: ='Revenue Model'!K11 -> 39004.672
A10: Total Income from Music | C10: =SUM(C7:C9) -> 46496.57 | D10: =SUM(D7:D9) -> 54883.43 | E10: =SUM(E7:E9) -> 62866.4 | F10: =SUM(F7:F9) -> 68946.68 | G10: =SUM(G7:G9) -> 78777.406 | H10: =SUM(H7:H9) -> 92345.893 | I10: =SUM(I7:I9) -> 109834.68 | J10: =SUM(J7:J9) -> 131681.5 | K10: =SUM(K7:K9) -> 158554.79
A12: Cost of music/Income from music | C12: =C5/C10 -> 0.14866215 | D12: =D5/D10 -> 0.16563742 | E12: =E5/E10 -> 0.17010661 | F12: =F5/F10 -> 0.12630644 | G12: ='Assumption Sheet'!G40 -> 0.15267816 | H12: ='Assumption Sheet'!H40 -> 0.15267816 | I12: ='Assumption Sheet'!I40 -> 0.15267816 | J12: ='Assumption Sheet'!J40 -> 0.15267816 | K12: ='Assumption Sheet'!K40 -> 0.15267816
A15: =IS!A6 -> Cost of Films, Tv serials and Digital content (under production and untelecasted) | C15: =IS!C6 -> 7398.35 | D15: =IS!D6 -> 13413.68 | E15: =IS!E6 -> 12510.53 | F15: =IS!F6 -> 45600.27 | G15: =G19*G21 -> 38199.306 | H15: =H19*H21 -> 38794.86 | I15: =I19*I21 -> 37493.608 | J15: =J19*J21 -> 36604.174 | K15: =K19*K21 -> 38819.732
A17: ='Revenue Model'!A12 -> Income from videos | C17: ='Revenue Model'!C12 -> 10239.13 | D17: ='Revenue Model'!D12 -> 10846.29 | E17: ='Revenue Model'!E12 -> 11586.66 | F17: ='Revenue Model'!F12 -> 19197.76 | G17: ='Revenue Model'!G12 -> 22077.424 | H17: ='Revenue Model'!H12 -> 25389.038 | I17: ='Revenue Model'!I12 -> 29197.393 | J17: ='Revenue Model'!J12 -> 33577.002 | K17: ='Revenue Model'!K12 -> 38613.553
A18: ='Revenue Model'!A13 -> Income from events | C18: ='Revenue Model'!C13 -> 0 | D18: ='Revenue Model'!D13 -> 4895.66 | E18: ='Revenue Model'!E13 -> 1344.17 | F18: ='Revenue Model'!F13 -> 28524.12 | G18: ='Revenue Model'!G13 -> 25671.708 | H18: ='Revenue Model'!H13 -> 23104.537 | I18: ='Revenue Model'!I13 -> 20794.083 | J18: ='Revenue Model'!J13 -> 18714.675 | K18: ='Revenue Model'!K13 -> 16843.208
A19: Total Income from Films and events | C19: =SUM(C17:C18) -> 10239.13 | D19: =SUM(D17:D18) -> 15741.95 | E19: =SUM(E17:E18) -> 12930.83 | F19: =SUM(F17:F18) -> 47721.88 | G19: =SUM(G17:G18) -> 47749.132 | H19: =SUM(H17:H18) -> 48493.575 | I19: =SUM(I17:I18) -> 49991.477 | J19: =SUM(J17:J18) -> 52291.677 | K19: =SUM(K17:K18) -> 55456.76
A21: Cost of films and events/Income from films and events | C21: =C15/C19 -> 0.72255651 | D21: =D15/D19 -> 0.85209774 | E21: =E15/E19 -> 0.96749629 | F21: =F15/F19 -> 0.9555422 | G21: ='Assumption Sheet'!G43 -> 0.8 | H21: ='Assumption Sheet'!H43 -> 0.8 | I21: ='Assumption Sheet'!I43 -> 0.75 | J21: ='Assumption Sheet'!J43 -> 0.7 | K21: ='Assumption Sheet'!K43 -> 0.7
A24: =IS!A7 -> Employee benefits expense | C24: =IS!C7 -> 7344.7 | D24: =IS!D7 -> 7499.89 | E24: =IS!E7 -> 9316.06 | F24: =IS!F7 -> 10749.67 | G24: =(G26*G27)+(G30*G31)+(G34*G35) -> 8073.2067 | H24: =(H26*H27)+(H30*H31)+(H34*H35) -> 11308.212 | I24: =(I26*I27)+(I30*I31)+(I34*I35) -> 15785.883 | J24: =(J26*J27)+(J30*J31)+(J34*J35) -> 21978.012 | K24: =(K26*K27)+(K30*K31)+(K34*K35) -> 30431.48
A26: No. of BOD | D26: 8 | E26: 7 | F26: 8 | G26: ='Assumption Sheet'!G46 -> 8 | H26: ='Assumption Sheet'!H46 -> 8 | I26: ='Assumption Sheet'!I46 -> 8 | J26: ='Assumption Sheet'!J46 -> 8 | K26: ='Assumption Sheet'!K46 -> 8
A27: Median Salary BOD | C27: - | D27: - | E27: =AVERAGE(2.95,1.1) -> 2.025 | F27: =AVERAGE(5.15,2) -> 3.575 | G27: =F27*(1+G28) -> 4.9432099 | H27: =G27*(1+H28) -> 6.8350556 | I27: =H27*(1+I28) -> 9.4509411 | J27: =I27*(1+J28) -> 13.067968 | K27: =J27*(1+K28) -> 18.069289
A28: YoY Increase in Median Salary of BOD | C28: - | D28: - | E28: 0 | F28: =F27/E27-1 -> 0.7654321 | G28: ='Assumption Sheet'!G47 -> 0.38271605 | H28: ='Assumption Sheet'!H47 -> 0.38271605 | I28: ='Assumption Sheet'!I47 -> 0.38271605 | J28: ='Assumption Sheet'!J47 -> 0.38271605 | K28: ='Assumption Sheet'!K47 -> 0.38271605
A30: No. of KMP (Key Managerial Personell) | C30: 3 | D30: 3 | E30: 3 | F30: 3 | G30: ='Assumption Sheet'!G49 -> 3 | H30: ='Assumption Sheet'!H49 -> 3 | I30: ='Assumption Sheet'!I49 -> 3 | J30: ='Assumption Sheet'!J49 -> 3 | K30: ='Assumption Sheet'!K49 -> 3
A31: Median Salary KMP | C31: =MEDIAN(937.83,201.13,16.65) -> 201.13 | D31: =AVERAGE(587.02,7.32) -> 297.17 | E31: =AVERAGE(698.79,12.56) -> 355.675 | F31: =AVERAGE(832.02,14.47) -> 423.245 | G31: =F31*(1+G32) -> 545.18933 | H31: =G31*(1+H32) -> 667.85115 | I31: =H31*(1+I32) -> 824.3696 | J31: =I31*(1+J32) -> 1029.7663 | K31: =J31*(1+K32) -> 1272.9651
A32: YoY Increase in Median Salary of BOD | C32: - | D32: =D31/C31-1 -> 0.47750211 | E32: =E31/D31-1 -> 0.19687384 | F32: =F31/E31-1 -> 0.1899768 | G32: ='Assumption Sheet'!G50 -> 0.28811759 | H32: ='Assumption Sheet'!H50 -> 0.22498941 | I32: ='Assumption Sheet'!I50 -> 0.23436127 | J32: ='Assumption Sheet'!J50 -> 0.24915609 | K32: ='Assumption Sheet'!K50 -> 0.23616892
A34: Total Number of Employees (Other than BOD and KMP) | B34: Permanent + Other than permanent | C34: 407 | D34: 372 | E34: 454 | F34: 396 | G34: =F34+'Assumption Sheet'!G53 -> 446 | H34: =G34+'Assumption Sheet'!H53 -> 496 | I34: =H34+'Assumption Sheet'!I53 -> 546 | J34: =I34+'Assumption Sheet'!J53 -> 596 | K34: =J34+'Assumption Sheet'!K53 -> 646
A35: Median Salary Employee | D35: =AVERAGE(9.5,9.5) -> 9.5 | E35: =AVERAGE(10.19,8) -> 9.095 | F35: =AVERAGE(12.08,9.99) -> 11.035 | G35: =F35*(1+G36) -> 14.3455 | H35: =G35*(1+H36) -> 18.64915 | I35: =H35*(1+I36) -> 24.243895 | J35: =I35*(1+J36) -> 31.517064 | K35: =J35*(1+K36) -> 40.972183
A36: YoY Increase in Median Salary of Employee (Other than BOD and KMP) | C36: - | D36: - | E36: =E35/D35-1 -> -0.042631579 | F36: =F35/E35-1 -> 0.21330401 | G36: ='Assumption Sheet'!G54 -> 0.3 | H36: ='Assumption Sheet'!H54 -> 0.3 | I36: ='Assumption Sheet'!I54 -> 0.3 | J36: ='Assumption Sheet'!J54 -> 0.3 | K36: ='Assumption Sheet'!K54 -> 0.3
A39: =IS!A8 -> Royalty expenses | C39: =IS!C8 -> 6313.76 | D39: =IS!D8 -> 6555.33 | E39: =IS!E8 -> 6126.64 | F39: =IS!F8 -> 6831.37 | G39: =G40*G41 -> 7073.924 | H39: =H40*H41 -> 8728.8623 | I39: =I40*I41 -> 10029.449 | J39: =J40*J41 -> 11409.412 | K39: =K40*K41 -> 13054.199
A40: ='Revenue Model'!A26 -> License Fees- Music | C40: ='Revenue Model'!C26 -> 36328.85 | D40: ='Revenue Model'!D26 -> 42122.5 | E40: ='Revenue Model'!E26 -> 47828.58 | F40: ='Revenue Model'!F26 -> 53860.92 | G40: ='Revenue Model'!G26 -> 64308.4 | H40: ='Revenue Model'!H26 -> 79353.293 | I40: ='Revenue Model'!I26 -> 91176.806 | J40: ='Revenue Model'!J26 -> 103721.92 | K40: ='Revenue Model'!K26 -> 118674.53
A41: Royalty Expense / License Income | C41: =C39/C40 -> 0.17379466 | D41: =D39/D40 -> 0.15562538 | E41: =E39/E40 -> 0.1280958 | F41: =F39/F40 -> 0.12683352 | G41: ='Assumption Sheet'!G57 -> 0.11 | H41: ='Assumption Sheet'!H57 -> 0.11 | I41: ='Assumption Sheet'!I57 -> 0.11 | J41: ='Assumption Sheet'!J57 -> 0.11 | K41: ='Assumption Sheet'!K57 -> 0.11
A44: =IS!A9 -> Advertisement and sales promotion | C44: =IS!C9 -> 5205.33 | D44: =IS!D9 -> 7710.99 | E44: =IS!E9 -> 7598.01 | F44: =IS!F9 -> 9041.17 | G44: =G45*G46 -> 11581.474 | H44: =H45*H46 -> 12891.593 | I44: =I45*I46 -> 14629.52 | J44: =J45*J46 -> 16839.792 | K44: =K45*K46 -> 19589.324
A45: =IS!A4 -> Revenue from operations | C45: =IS!C4 -> 58062.76 | D45: =IS!D4 -> 73662.12 | E45: =IS!E4 -> 80300.4 | F45: =IS!F4 -> 117135.76 | G45: =IS!G4 -> 126526.54 | H45: =IS!H4 -> 140839.47 | I45: =IS!I4 -> 159826.15 | J45: =IS!J4 -> 183973.17 | K45: =IS!K4 -> 214011.55
A46: Advertisment and Sales Promotion Expense/ Revenue from operations | C46: =C44/C45 -> 0.089650061 | D46: =D44/D45 -> 0.10468053 | E46: =E44/E45 -> 0.094619828 | F46: =F44/F45 -> 0.077185396 | G46: ='Assumption Sheet'!G60 -> 0.091533955 | H46: ='Assumption Sheet'!H60 -> 0.091533955 | I46: ='Assumption Sheet'!I60 -> 0.091533955 | J46: ='Assumption Sheet'!J60 -> 0.091533955 | K46: ='Assumption Sheet'!K60 -> 0.091533955
A49: =IS!A10 -> Other expenses | C49: =IS!C10 -> 6176.07 | D49: =IS!D10 -> 7293.41 | E49: =IS!E10 -> 9400.07 | F49: =IS!F10 -> 8506.01 | G49: =G50*G51 -> 12496.347 | H49: =H50*H51 -> 13642.214 | I49: =I50*I51 -> 15395.502 | J49: =J50*J51 -> 16767.841 | K49: =K50*K51 -> 20496.829
A50: =IS!A4 -> Revenue from operations | C50: =IS!C4 -> 58062.76 | D50: =IS!D4 -> 73662.12 | E50: =IS!E4 -> 80300.4 | F50: =IS!F4 -> 117135.76 | G50: =IS!G4 -> 126526.54 | H50: =IS!H4 -> 140839.47 | I50: =IS!I4 -> 159826.15 | J50: =IS!J4 -> 183973.17 | K50: =IS!K4 -> 214011.55
A51: Other Expense/Revenue from Operations | C51: =C49/C50 -> 0.10636887 | D51: =D49/D50 -> 0.099011677 | E51: =E49/E50 -> 0.11706131 | F51: =F49/F50 -> 0.07261668 | G51: ='Assumption Sheet'!G63 -> 0.098764633 | H51: ='Assumption Sheet'!H63 -> 0.096863575 | I51: ='Assumption Sheet'!I63 -> 0.09632655 | J51: ='Assumption Sheet'!J63 -> 0.091142859 | K51: ='Assumption Sheet'!K63 -> 0.095774404
A54: =IS!A18 -> Tax Expense | C54: =IS!C18 -> 5176.68 | D54: =IS!D18 -> 6302.58 | E54: =IS!E18 -> 7322.64 | F54: =IS!F18 -> 7183.2 | G54: =G55*G56 -> 8804.0365 | H54: =H55*H56 -> 9420.4782 | I54: =I55*I56 -> 11201.097 | J54: =J55*J56 -> 14599.08 | K54: =K55*K56 -> 17205.368
A55: =IS!A17 -> Earning before Tax (EBT) | C55: =IS!C17 -> 20441.24 | D55: =IS!D17 -> 24807.77 | E55: =IS!E17 -> 27078.57 | F55: =IS!F17 -> 27607.1 | G55: =IS!G17 -> 33929.556 | H55: =IS!H17 -> 36305.238 | I55: =IS!I17 -> 43167.5 | J55: =IS!J17 -> 56262.862 | K55: =IS!K17 -> 66307.142
A56: Effective Tax Rate | C56: =C54/C55 -> 0.25324687 | D56: =D54/D55 -> 0.25405669 | E56: =E54/E55 -> 0.27042196 | F56: =F54/F55 -> 0.26019394 | G56: ='Assumption Sheet'!G65 -> 0.25947986 | H56: ='Assumption Sheet'!H65 -> 0.25947986 | I56: ='Assumption Sheet'!I65 -> 0.25947986 | J56: ='Assumption Sheet'!J65 -> 0.25947986 | K56: ='Assumption Sheet'!K65 -> 0.25947986
A59: =IS!A20 -> Dividends | C59: =IS!C20 -> 5784.28 | D59: =IS!D20 -> 5784.28 | E59: =IS!E20 -> 7712.38 | F59: =IS!F20 -> 8676.4 | G59: =G60*G61 -> 0 | H59: =H60*H61 -> 0 | I59: =I60*I61 -> 12041.028 | J59: =J60*J61 -> 15693.814 | K59: =K60*K61 -> 18495.539
A60: =IS!A19 -> Profit For the year | C60: =IS!C19 -> 15264.56 | D60: =IS!D19 -> 18505.19 | E60: =IS!E19 -> 19755.93 | F60: =IS!F19 -> 20423.9 | G60: =IS!G19 -> 25125.519 | H60: =IS!H19 -> 26884.76 | I60: =IS!I19 -> 31966.403 | J60: =IS!J19 -> 41663.782 | K60: =IS!K19 -> 49101.774
A61: Dividend Payout Ratio | C61: =C59/C60 -> 0.37893526 | D61: =D59/D60 -> 0.31257609 | E61: =E59/E60 -> 0.39038304 | F61: =F59/F60 -> 0.42481602 | G61: ='Assumption Sheet'!G67 -> 0 | H61: ='Assumption Sheet'!H67 -> 0 | I61: ='Assumption Sheet'!I67 -> 0.3766776 | J61: ='Assumption Sheet'!J67 -> 0.3766776 | K61: ='Assumption Sheet'!K67 -> 0.3766776

Sheet Capex Schedule 
A1: Capex Schedule
A2: Figures in Lakhs ,expect otherwise stated
A3: Particular/Years | B3: Comments | C3: 2021-22 A | D3: 2022-23 A | E3: 2023-24 A | F3: 2024-25 A | G3: 2025-26 E | H3: 2026-27 E | I3: 2027-28 E | J3: 2028-29 E | K3: 2029-30 E
A5: Land - Freehold
A6: Opening Gross Carrying Amount | C6: 20007.76 | D6: 20967.2 | E6: 20967.2 | F6: 20967.2 | G6: =F10 -> 20967.2 | H6: =G10 -> 20967.2 | I6: =H10 -> 20967.2 | J6: =I10 -> 20967.2 | K6: =J10 -> 20967.2
A7: Acquisition through buisness combination | C7: 0 | D7: 0 | E7: 0 | F7: 0 | G7: 0 | H7: 0 | I7: 0 | J7: 0 | K7: 0
A8: Addition | C8: 959.44 | D8: 0 | E8: 0 | F8: 0 | G8: 0 | H8: 0 | I8: 0 | J8: 0 | K8: 0
A9: Deletion | C9: 0 | D9: 0 | E9: 0 | F9: 0 | G9: 0 | H9: 0 | I9: 0 | J9: 0 | K9: 0
A10: Closing Gross Carrying Amount | C10: 20967.2 | D10: 20967.2 | E10: 20967.2 | F10: 20967.2 | G10: =SUM(G6:G9) -> 20967.2 | H10: =SUM(H6:H9) -> 20967.2 | I10: =SUM(I6:I9) -> 20967.2 | J10: =SUM(J6:J9) -> 20967.2 | K10: =SUM(K6:K9) -> 20967.2
A12: Net Block Carrying Amount | C12: 20967.2 | D12: 20967.2 | E12: 20967.2 | F12: 20967.2 | G12: =G10 -> 20967.2 | H12: =H10 -> 20967.2 | I12: =I10 -> 20967.2 | J12: =J10 -> 20967.2 | K12: =K10 -> 20967.2
A14: Buildings - Freehold
A15: Opening Gross Carrying Amount | C15: 70.59 | D15: 70.59 | E15: 70.59 | F15: 70.59 | G15: =F19 -> 70.59 | H15: =G19 -> 70.59 | I15: =H19 -> 70.59 | J15: =I19 -> 70.59 | K15: =J19 -> 70.59
A16: Acquisition through buisness combination | C16: 0 | D16: 0 | E16: 0 | F16: 0 | G16: 0 | H16: 0 | I16: 0 | J16: 0 | K16: 0
A17: Addition | C17: 0 | D17: 0 | E17: 0 | F17: 0 | G17: ='Assumption Sheet'!G72 -> 0 | H17: ='Assumption Sheet'!H72 -> 0 | I17: ='Assumption Sheet'!I72 -> 0 | J17: ='Assumption Sheet'!J72 -> 0 | K17: ='Assumption Sheet'!K72 -> 0
A18: Deletion | C18: 0 | D18: 0 | E18: 0 | F18: 0 | G18: 0 | H18: 0 | I18: 0 | J18: 0 | K18: 0
A19: Closing Gross Carrying Amount | C19: 70.59 | D19: 70.59 | E19: 70.59 | F19: 70.59 | G19: =SUM(G15:G18) -> 70.59 | H19: =SUM(H15:H18) -> 70.59 | I19: =SUM(I15:I18) -> 70.59 | J19: =SUM(J15:J18) -> 70.59 | K19: =SUM(K15:K18) -> 70.59
A21: Opening Accumulated Depriciation | C21: 31.72 | D21: 35.8 | E21: 39.88 | F21: 43.96 | G21: =F24 -> 48.04 | H21: =G24 -> 52.120347 | I21: =H24 -> 56.200694 | J21: =I24 -> 60.28104 | K21: =J24 -> 64.361387
A22: Depriciation for the year | C22: 4.08 | D22: 4.08 | E22: 4.08 | F22: 4.08 | G22: =G19/G28 -> 4.0803468 | H22: =H19/H28 -> 4.0803468 | I22: =I19/I28 -> 4.0803468 | J22: =J19/J28 -> 4.0803468 | K22: =K19/K28 -> 4.0803468
A23: Deduction Adjustment | C23: 0 | D23: 0 | E23: 0 | F23: 0 | G23: 0 | H23: 0 | I23: 0 | J23: 0 | K23: 0
A24: Closing Accumulated Depriciation | C24: 35.8 | D24: 39.88 | E24: 43.96 | F24: 48.04 | G24: =SUM(G21:G23) -> 52.120347 | H24: =SUM(H21:H23) -> 56.200694 | I24: =SUM(I21:I23) -> 60.28104 | J24: =SUM(J21:J23) -> 64.361387 | K24: =SUM(K21:K23) -> 68.441734
A26: Net Block Carrying Amount | C26: 34.79 | D26: 30.71 | E26: 26.63 | F26: 22.55 | G26: =G19-G24 -> 18.469653 | H26: =H19-H24 -> 14.389306 | I26: =I19-I24 -> 10.30896 | J26: =J19-J24 -> 6.2286127 | K26: =K19-K24 -> 2.1482659
A28: Total Useful Life | C28: =C19/C22 -> 17.301471 | D28: =D19/D22 -> 17.301471 | E28: =E19/E22 -> 17.301471 | F28: =F19/F22 -> 17.301471 | G28: ='Assumption Sheet'!G73 -> 17.3 | H28: ='Assumption Sheet'!H73 -> 17.3 | I28: ='Assumption Sheet'!I73 -> 17.3 | J28: ='Assumption Sheet'!J73 -> 17.3 | K28: ='Assumption Sheet'!K73 -> 17.3
A29: Age of the Asset | C29: =C24/C22 -> 8.7745098 | D29: =D24/D22 -> 9.7745098 | E29: =E24/E22 -> 10.77451 | F29: =F24/F22 -> 11.77451 | G29: =G24/G22 -> 12.773509 | H29: =H24/H22 -> 13.773509 | I29: =I24/I22 -> 14.773509 | J29: =J24/J22 -> 15.773509 | K29: =K24/K22 -> 16.773509
A30: Remaining Life of the Asset | C30: =C26/C22 -> 8.5269608 | D30: =D26/D22 -> 7.5269608 | E30: =E26/E22 -> 6.5269608 | F30: =F26/F22 -> 5.5269608 | G30: =G26/G22 -> 4.526491 | H30: =H26/H22 -> 3.526491 | I30: =I26/I22 -> 2.526491 | J30: =J26/J22 -> 1.526491 | K30: =K26/K22 -> 0.526491
A33: Buildings
A34: Opening Gross Carrying Amount | C34: 37.71 | D34: 37.71 | E34: 37.71 | F34: 37.71 | G34: =F38 -> 37.71 | H34: =G38 -> 37.71 | I34: =H38 -> 37.71 | J34: =I38 -> 37.71 | K34: =J38 -> 37.71
A35: Acquisition through buisness combination | C35: 0 | D35: 0 | E35: 0 | F35: 0 | G35: 0 | H35: 0 | I35: 0 | J35: 0 | K35: 0
A36: Addition | C36: 0 | D36: 0 | E36: 0 | F36: 0 | G36: ='Assumption Sheet'!G76 -> 0 | H36: ='Assumption Sheet'!H76 -> 0 | I36: ='Assumption Sheet'!I76 -> 0 | J36: ='Assumption Sheet'!J76 -> 0 | K36: ='Assumption Sheet'!K76 -> 0
A37: Deletion | C37: 0 | D37: 0 | E37: 0 | F37: 0 | G37: 0 | H37: 0 | I37: 0 | J37: 0 | K37: 0
A38: Closing Gross Carrying Amount | C38: 37.71 | D38: 37.71 | E38: 37.71 | F38: 37.71 | G38: =SUM(G34:G37) -> 37.71 | H38: =SUM(H34:H37) -> 37.71 | I38: =SUM(I34:I37) -> 37.71 | J38: =SUM(J34:J37) -> 37.71 | K38: =SUM(K34:K37) -> 37.71
A40: Opening Accumulated Depriciation | C40: 4 | D40: 4.8 | E40: 5.6 | F40: 6.4 | G40: =F43 -> 7.2 | H40: =G43 -> 8 | I40: =H43 -> 8.8 | J40: =I43 -> 9.6 | K40: =J43 -> 10.4
A41: Depriciation for the year | C41: 0.8 | D41: 0.8 | E41: 0.8 | F41: 0.8 | G41: =G38/G47 -> 0.8 | H41: =H38/H47 -> 0.8 | I41: =I38/I47 -> 0.8 | J41: =J38/J47 -> 0.8 | K41: =K38/K47 -> 0.8
A42: Deduction Adjustment | C42: 0 | D42: 0 | E42: 0 | F42: 0 | G42: 0 | H42: 0 | I42: 0 | J42: 0 | K42: 0
A43: Closing Accumulated Depriciation | C43: 4.8 | D43: 5.6 | E43: 6.4 | F43: 7.2 | G43: =SUM(G40:G42) -> 8 | H43: =SUM(H40:H42) -> 8.8 | I43: =SUM(I40:I42) -> 9.6 | J43: =SUM(J40:J42) -> 10.4 | K43: =SUM(K40:K42) -> 11.2
A45: Net Block Carrying Amount | C45: 32.91 | D45: 32.11 | E45: 31.31 | F45: 30.51 | G45: =G38-G43 -> 29.71 | H45: =H38-H43 -> 28.91 | I45: =I38-I43 -> 28.11 | J45: =J38-J43 -> 27.31 | K45: =K38-K43 -> 26.51
A47: Total Useful Life | C47: =C38/C41 -> 47.1375 | D47: =D38/D41 -> 47.1375 | E47: =E38/E41 -> 47.1375 | F47: =F38/F41 -> 47.1375 | G47: ='Assumption Sheet'!G77 -> 47.1375 | H47: ='Assumption Sheet'!H77 -> 47.1375 | I47: ='Assumption Sheet'!I77 -> 47.1375 | J47: ='Assumption Sheet'!J77 -> 47.1375 | K47: ='Assumption Sheet'!K77 -> 47.1375
A48: Age of the Asset | C48: =C43/C41 -> 6 | D48: =D43/D41 -> 7 | E48: =E43/E41 -> 8 | F48: =F43/F41 -> 9 | G48: =G43/G41 -> 10 | H48: =H43/H41 -> 11 | I48: =I43/I41 -> 12 | J48: =J43/J41 -> 13 | K48: =K43/K41 -> 14
A49: Remaining Life of the Asset | C49: =C45/C41 -> 41.1375 | D49: =D45/D41 -> 40.1375 | E49: =E45/E41 -> 39.1375 | F49: =F45/F41 -> 38.1375 | G49: =G45/G41 -> 37.1375 | H49: =H45/H41 -> 36.1375 | I49: =I45/I41 -> 35.1375 | J49: =J45/J41 -> 34.1375 | K49: =K45/K41 -> 33.1375
A51: Plant and Equipment
A52: Opening Gross Carrying Amount | C52: 3.14 | D52: 3.14 | E52: 3.14 | F52: 3.14 | G52: =F56 -> 25.19 | H52: =G56 -> 25.19 | I52: =H56 -> 25.19 | J52: =I56 -> 25.19 | K52: =J56 -> 25.19
A53: Acquisition through buisness combination | C53: 0 | D53: 0 | E53: 0 | F53: 0 | G53: 0 | H53: 0 | I53: 0 | J53: 0 | K53: 0
A54: Addition | C54: 0 | D54: 0 | E54: 0 | F54: 22.05 | G54: ='Assumption Sheet'!G80 -> 0 | H54: ='Assumption Sheet'!H80 -> 0 | I54: ='Assumption Sheet'!I80 -> 0 | J54: ='Assumption Sheet'!J80 -> 0 | K54: ='Assumption Sheet'!K80 -> 0
A55: Deletion | C55: 0 | D55: 0 | E55: 0 | F55: 0 | G55: 0 | H55: 0 | I55: 0 | J55: 0 | K55: 0
A56: Closing Gross Carrying Amount | C56: 3.14 | D56: 3.14 | E56: 3.14 | F56: 25.19 | G56: =SUM(G52:G55) -> 25.19 | H56: =SUM(H52:H55) -> 25.19 | I56: =SUM(I52:I55) -> 25.19 | J56: =SUM(J52:J55) -> 25.19 | K56: =SUM(K52:K55) -> 25.19
A58: Opening Accumulated Depriciation | C58: 3.14 | D58: 3.14 | E58: 3.14 | F58: 3.14 | G58: =F61 -> 6.2 | H58: =G61 -> 9.26 | I58: =H61 -> 12.32 | J58: =I61 -> 15.38 | K58: =J61 -> 18.44
A59: Depriciation for the year | C59: 0 | D59: 0 | E59: 0 | F59: 3.06 | G59: =G56/G65 -> 3.06 | H59: =H56/H65 -> 3.06 | I59: =I56/I65 -> 3.06 | J59: =J56/J65 -> 3.06 | K59: =K56/K65 -> 3.06
A60: Deduction Adjustment | C60: 0 | D60: 0 | E60: 0 | F60: 0 | G60: 0 | H60: 0 | I60: 0 | J60: 0 | K60: 0
A61: Closing Accumulated Depriciation | C61: 3.14 | D61: 3.14 | E61: 3.14 | F61: 6.2 | G61: =SUM(G58:G60) -> 9.26 | H61: =SUM(H58:H60) -> 12.32 | I61: =SUM(I58:I60) -> 15.38 | J61: =SUM(J58:J60) -> 18.44 | K61: =SUM(K58:K60) -> 21.5
A63: Net Block Carrying Amount | C63: 0 | D63: 0 | E63: 0 | F63: 18.99 | G63: =G56-G61 -> 15.93 | H63: =H56-H61 -> 12.87 | I63: =I56-I61 -> 9.81 | J63: =J56-J61 -> 6.75 | K63: =K56-K61 -> 3.69
A65: Total Useful Life | C65: 0 | D65: 0 | E65: 0 | F65: =F56/F59 -> 8.2320261 | G65: ='Assumption Sheet'!G81 -> 8.2320261 | H65: ='Assumption Sheet'!H81 -> 8.2320261 | I65: ='Assumption Sheet'!I81 -> 8.2320261 | J65: ='Assumption Sheet'!J81 -> 8.2320261 | K65: ='Assumption Sheet'!K81 -> 8.2320261
A66: Age of the Asset | C66: 0 | D66: 0 | E66: 0 | F66: =F61/F59 -> 2.0261438 | G66: =G61/G59 -> 3.0261438 | H66: =H61/H59 -> 4.0261438 | I66: =I61/I59 -> 5.0261438 | J66: =J61/J59 -> 6.0261438 | K66: =K61/K59 -> 7.0261438
A67: Remaining Life of the Asset | C67: 0 | D67: 0 | E67: 0 | F67: =F63/F59 -> 6.2058824 | G67: =G63/G59 -> 5.2058824 | H67: =H63/H59 -> 4.2058824 | I67: =I63/I59 -> 3.2058824 | J67: =J63/J59 -> 2.2058824 | K67: =K63/K59 -> 1.2058824
A69: Furniture and Fixtures
A70: Opening Gross Carrying Amount | C70: 475.66 | D70: 480.15 | E70: 969.95 | F70: 1275.23 | G70: =F74 -> 1336.17 | H70: =G74 -> 1386.17 | I70: =H74 -> 1436.17 | J70: =I74 -> 1486.17 | K70: =J74 -> 1536.17
A71: Acquisition through buisness combination | C71: 0 | D71: 0 | E71: 53.58 | F71: 0 | G71: 0 | H71: 0 | I71: 0 | J71: 0 | K71: 0
A72: Addition | C72: 4.99 | D72: 524.55 | E72: 251.7 | F72: 60.94 | G72: ='Assumption Sheet'!G84 -> 50 | H72: ='Assumption Sheet'!H84 -> 50 | I72: ='Assumption Sheet'!I84 -> 50 | J72: ='Assumption Sheet'!J84 -> 50 | K72: ='Assumption Sheet'!K84 -> 50
A73: Deletion | C73: -0.5 | D73: -34.75 | E73: 0 | F73: 0 | G73: 0 | H73: 0 | I73: 0 | J73: 0 | K73: 0
A74: Closing Gross Carrying Amount | C74: 480.15 | D74: 969.95 | E74: 1275.23 | F74: 1336.17 | G74: =SUM(G70:G73) -> 1386.17 | H74: =SUM(H70:H73) -> 1436.17 | I74: =SUM(I70:I73) -> 1486.17 | J74: =SUM(J70:J73) -> 1536.17 | K74: =SUM(K70:K73) -> 1586.17
A76: Opening Accumulated Depriciation | C76: 304.65 | D76: 350.02 | E76: 363.27 | F76: 467.41 | G76: =F79 -> 590.08 | H76: =G79 -> 728.697 | I76: =H79 -> 879.87279 | J76: =I79 -> 1045.0028 | K76: =J79 -> 1225.7287
A77: Depriciation for the year | C77: 45.87 | D77: 43.42 | E77: 104.14 | F77: 122.67 | G77: =G74/G83 -> 138.617 | H77: =H74/H83 -> 151.17579 | I77: =I74/I83 -> 165.13 | J77: =J74/J83 -> 180.72588 | K77: =K74/K83 -> 198.27125
A78: Deduction Adjustment | C78: -0.5 | D78: -30.17 | E78: 0 | F78: 0 | G78: 0 | H78: 0 | I78: 0 | J78: 0 | K78: 0
A79: Closing Accumulated Depriciation | C79: 350.02 | D79: 363.27 | E79: 467.41 | F79: 590.08 | G79: =SUM(G76:G78) -> 728.697 | H79: =SUM(H76:H78) -> 879.87279 | I79: =SUM(I76:I78) -> 1045.0028 | J79: =SUM(J76:J78) -> 1225.7287 | K79: =SUM(K76:K78) -> 1423.9999
A81: Net Block Carrying Amount | C81: 130.13 | D81: 606.68 | E81: 807.82 | F81: 746.09 | G81: =G74-G79 -> 657.473 | H81: =H74-H79 -> 556.29721 | I81: =I74-I79 -> 441.16721 | J81: =J74-J79 -> 310.44133 | K81: =K74-K79 -> 162.17008
A83: Total Useful Life | C83: =C74/C77 -> 10.467626 | D83: =D74/D77 -> 22.338784 | E83: =E74/E77 -> 12.245343 | F83: =F74/F77 -> 10.892394 | G83: ='Assumption Sheet'!G85 -> 10 | H83: ='Assumption Sheet'!H85 -> 9.5 | I83: ='Assumption Sheet'!I85 -> 9 | J83: ='Assumption Sheet'!J85 -> 8.5 | K83: ='Assumption Sheet'!K85 -> 8
A84: Age of the Asset | C84: =C79/C77 -> 7.6306954 | D84: =D79/D77 -> 8.366421 | E84: =E79/E77 -> 4.488285 | F84: =F79/F77 -> 4.8103041 | G84: =G79/G77 -> 5.2569093 | H84: =H79/H77 -> 5.8201964 | I84: =I79/I77 -> 6.3283643 | J84: =J79/J77 -> 6.7822531 | K84: =K79/K77 -> 7.1820797
A85: Remaining Life of the Asset | C85: =C81/C77 -> 2.8369305 | D85: =D81/D77 -> 13.972363 | E85: =E81/E77 -> 7.7570578 | F85: =F81/F77 -> 6.0820902 | G85: =G81/G77 -> 4.7430907 | H85: =H81/H77 -> 3.6798036 | I85: =I81/I77 -> 2.6716357 | J85: =J81/J77 -> 1.7177469 | K85: =K81/K77 -> 0.81792029
A87: Office Equipment
A88: Opening Gross Carrying Amount | C88: 874.25 | D88: 1057.4 | E88: 1373.9 | F88: 1746.43 | G88: =F92 -> 1868.92 | H88: =G92 -> 2277.3894 | I88: =H92 -> 2734.6707 | J88: =I92 -> 3184.058 | K88: =J92 -> 3673.969
A89: Acquisition through buisness combination | C89: 0 | D89: 0 | E89: 102.04 | F89: 0 | G89: 0 | H89: 0 | I89: 0 | J89: 0 | K89: 0
A90: Addition | C90: 183.15 | D90: 367.37 | E90: 273.57 | F90: 159.88 | G90: ='Assumption Sheet'!G88 -> 408.46944 | H90: ='Assumption Sheet'!H88 -> 457.28129 | I90: ='Assumption Sheet'!I88 -> 449.38723 | J90: ='Assumption Sheet'!J88 -> 489.91107 | K90: ='Assumption Sheet'!K88 -> 639.35042
A91: Deletion | C91: 0 | D91: -50.87 | E91: -3.08 | F91: -37.39 | G91: 0 | H91: 0 | I91: 0 | J91: 0 | K91: 0
A92: Closing Gross Carrying Amount | C92: 1057.4 | D92: 1373.9 | E92: 1746.43 | F92: 1868.92 | G92: =SUM(G88:G91) -> 2277.3894 | H92: =SUM(H88:H91) -> 2734.6707 | I92: =SUM(I88:I91) -> 3184.058 | J92: =SUM(J88:J91) -> 3673.969 | K92: =SUM(K88:K91) -> 4313.3194
A94: Opening Accumulated Depriciation | C94: 667.73 | D94: 811.07 | E94: 944.88 | F94: 1201.85 | G94: =F97 -> 1436.23 | H94: =G97 -> 1749.6727 | I94: =H97 -> 2127.497 | J94: =I97 -> 2576.3505 | K94: =J97 -> 3088.3234
A95: Depriciation for the year | C95: 143.34 | D95: 175.81 | E95: 258.18 | F95: 262.97 | G95: =G92/G101 -> 313.4427 | H95: =H92/H101 -> 377.82427 | I95: =I92/I101 -> 448.85349 | J95: =J92/J101 -> 511.97295 | K95: =K92/K101 -> 599.62327
A96: Deduction Adjustment | C96: 0 | D96: -42 | E96: -1.21 | F96: -28.59 | G96: 0 | H96: 0 | I96: 0 | J96: 0 | K96: 0
A97: Closing Accumulated Depriciation | C97: 811.07 | D97: 944.88 | E97: 1201.85 | F97: 1436.23 | G97: =SUM(G94:G96) -> 1749.6727 | H97: =SUM(H94:H96) -> 2127.497 | I97: =SUM(I94:I96) -> 2576.3505 | J97: =SUM(J94:J96) -> 3088.3234 | K97: =SUM(K94:K96) -> 3687.9467
A99: Net Block Carrying Amount | C99: 246.3 | D99: 429.02 | E99: 544.58 | F99: 432.69 | G99: =G92-G97 -> 527.71673 | H99: =H92-H97 -> 607.17375 | I99: =I92-I97 -> 607.70749 | J99: =J92-J97 -> 585.64561 | K99: =K92-K97 -> 625.37275
A101: Total Useful Life | C101: =C92/C95 -> 7.3768662 | D101: =D92/D95 -> 7.8146863 | E101: =E92/E95 -> 6.7643892 | F101: =F92/F95 -> 7.1069704 | G101: ='Assumption Sheet'!G90 -> 7.265728 | H101: ='Assumption Sheet'!H90 -> 7.2379435 | I101: ='Assumption Sheet'!I90 -> 7.0937578 | J101: ='Assumption Sheet'!J90 -> 7.1760999 | K101: ='Assumption Sheet'!K90 -> 7.1933823
A102: Age of the Asset | C102: =C97/C95 -> 5.6583647 | D102: =D97/D95 -> 5.3744383 | E102: =E97/E95 -> 4.6550856 | F102: =F97/F95 -> 5.4615736 | G102: =G97/G95 -> 5.5821133 | H102: =H97/H95 -> 5.6309166 | I102: =I97/I95 -> 5.7398472 | J102: =J97/J95 -> 6.0322004 | K102: =K97/K95 -> 6.1504395
A103: Remaining Life of the Asset | C103: =C99/C95 -> 1.7182922 | D103: =D99/D95 -> 2.440248 | E103: =E99/E95 -> 2.1093036 | F103: =F99/F95 -> 1.6453968 | G103: =G99/G95 -> 1.6836147 | H103: =H99/H95 -> 1.6070269 | I103: =I99/I95 -> 1.3539106 | J103: =J99/J95 -> 1.1438995 | K103: =K99/K95 -> 1.0429428
A105: Vehicles
A106: Opening Gross Carrying Amount | C106: 5.18 | D106: 5.18 | E106: 5.18 | F106: 9.81 | G106: =F110 -> 9.81 | H106: =G110 -> 9.81 | I106: =H110 -> 9.81 | J106: =I110 -> 9.81 | K106: =J110 -> 9.81
A107: Acquisition through buisness combination | C107: 0 | D107: 0 | E107: 0 | F107: 0 | G107: 0 | H107: 0 | I107: 0 | J107: 0 | K107: 0
A108: Addition | C108: 0 | D108: 0 | E108: 4.63 | F108: 0 | G108: ='Assumption Sheet'!G93 -> 0 | H108: ='Assumption Sheet'!H93 -> 0 | I108: ='Assumption Sheet'!I93 -> 0 | J108: ='Assumption Sheet'!J93 -> 0 | K108: ='Assumption Sheet'!K93 -> 0
A109: Deletion | C109: 0 | D109: 0 | E109: 0 | F109: 0 | G109: 0 | H109: 0 | I109: 0 | J109: 0 | K109: 0
A110: Closing Gross Carrying Amount | C110: 5.18 | D110: 5.18 | E110: 9.81 | F110: 9.81 | G110: =SUM(G106:G109) -> 9.81 | H110: =SUM(H106:H109) -> 9.81 | I110: =SUM(I106:I109) -> 9.81 | J110: =SUM(J106:J109) -> 9.81 | K110: =SUM(K106:K109) -> 9.81
A112: Opening Accumulated Depriciation | C112: 5.18 | D112: 5.18 | E112: 5.18 | F112: 5.18 | G112: =F115 -> 5.76 | H112: =G115 -> 6.34 | I112: =H115 -> 6.92 | J112: =I115 -> 7.5 | K112: =J115 -> 8.08
A113: Depriciation for the year | C113: 0 | D113: 0 | E113: 0 | F113: 0.58 | G113: =G110/G119 -> 0.58 | H113: =H110/H119 -> 0.58 | I113: =I110/I119 -> 0.58 | J113: =J110/J119 -> 0.58 | K113: =K110/K119 -> 0.58
A114: Deduction Adjustment | C114: 0 | D114: 0 | E114: 0 | F114: 0 | G114: 0 | H114: 0 | I114: 0 | J114: 0 | K114: 0
A115: Closing Accumulated Depriciation | C115: 5.18 | D115: 5.18 | E115: 5.18 | F115: 5.76 | G115: =SUM(G112:G114) -> 6.34 | H115: =SUM(H112:H114) -> 6.92 | I115: =SUM(I112:I114) -> 7.5 | J115: =SUM(J112:J114) -> 8.08 | K115: =SUM(K112:K114) -> 8.66
A117: Net Block Carrying Amount | C117: 0 | D117: 0 | E117: 4.63 | F117: 4.05 | G117: =G110-G115 -> 3.47 | H117: =H110-H115 -> 2.89 | I117: =I110-I115 -> 2.31 | J117: =J110-J115 -> 1.73 | K117: =K110-K115 -> 1.15
A119: Total Useful Life | C119: 0 | D119: 0 | E119: 0 | F119: =F110/F113 -> 16.913793 | G119: ='Assumption Sheet'!G94 -> 16.913793 | H119: ='Assumption Sheet'!H94 -> 16.913793 | I119: ='Assumption Sheet'!I94 -> 16.913793 | J119: ='Assumption Sheet'!J94 -> 16.913793 | K119: ='Assumption Sheet'!K94 -> 16.913793
A120: Age of the Asset | C120: 0 | D120: 0 | E120: 0 | F120: =F115/F113 -> 9.9310345 | G120: =G115/G113 -> 10.931034 | H120: =H115/H113 -> 11.931034 | I120: =I115/I113 -> 12.931034 | J120: =J115/J113 -> 13.931034 | K120: =K115/K113 -> 14.931034
A121: Remaining Life of the Asset | C121: 0 | D121: 0 | E121: 0 | F121: =F117/F113 -> 6.9827586 | G121: =G117/G113 -> 5.9827586 | H121: =H117/H113 -> 4.9827586 | I121: =I117/I113 -> 3.9827586 | J121: =J117/J113 -> 2.9827586 | K121: =K117/K113 -> 1.9827586
A123: TOTAL
A124: Opening Gross Carrying Amount | C124: =C6+C15+C34+C52+C70+C88+C106 -> 21474.29 | D124: =D6+D15+D34+D52+D70+D88+D106 -> 22621.37 | E124: =E6+E15+E34+E52+E70+E88+E106 -> 23427.67 | F124: =F6+F15+F34+F52+F70+F88+F106 -> 24110.11 | G124: =G6+G15+G34+G52+G70+G88+G106 -> 24315.59 | H124: =H6+H15+H34+H52+H70+H88+H106 -> 24774.059 | I124: =I6+I15+I34+I52+I70+I88+I106 -> 25281.341 | J124: =J6+J15+J34+J52+J70+J88+J106 -> 25780.728 | K124: =K6+K15+K34+K52+K70+K88+K106 -> 26320.639
A125: Acquisition through buisness combination | C125: =C7+C16+C35+C53+C71+C89+C107 -> 0 | D125: =D7+D16+D35+D53+D71+D89+D107 -> 0 | E125: =E7+E16+E35+E53+E71+E89+E107 -> 155.62 | F125: =F7+F16+F35+F53+F71+F89+F107 -> 0 | G125: =G7+G16+G35+G53+G71+G89+G107 -> 0 | H125: =H7+H16+H35+H53+H71+H89+H107 -> 0 | I125: =I7+I16+I35+I53+I71+I89+I107 -> 0 | J125: =J7+J16+J35+J53+J71+J89+J107 -> 0 | K125: =K7+K16+K35+K53+K71+K89+K107 -> 0
A126: Addition | C126: =C8+C17+C36+C54+C72+C90+C108 -> 1147.58 | D126: =D8+D17+D36+D54+D72+D90+D108 -> 891.92 | E126: =E8+E17+E36+E54+E72+E90+E108 -> 529.9 | F126: =F8+F17+F36+F54+F72+F90+F108 -> 242.87 | G126: =G8+G17+G36+G54+G72+G90+G108 -> 458.46944 | H126: =H8+H17+H36+H54+H72+H90+H108 -> 507.28129 | I126: =I8+I17+I36+I54+I72+I90+I108 -> 499.38723 | J126: =J8+J17+J36+J54+J72+J90+J108 -> 539.91107 | K126: =K8+K17+K36+K54+K72+K90+K108 -> 689.35042
A127: Deletion | C127: =C9+C18+C37+C55+C73+C91+C109 -> -0.5 | D127: =D9+D18+D37+D55+D73+D91+D109 -> -85.62 | E127: =E9+E18+E37+E55+E73+E91+E109 -> -3.08 | F127: =F9+F18+F37+F55+F73+F91+F109 -> -37.39 | G127: =G9+G18+G37+G55+G73+G91+G109 -> 0 | H127: =H9+H18+H37+H55+H73+H91+H109 -> 0 | I127: =I9+I18+I37+I55+I73+I91+I109 -> 0 | J127: =J9+J18+J37+J55+J73+J91+J109 -> 0 | K127: =K9+K18+K37+K55+K73+K91+K109 -> 0
A128: Closing Gross Carrying Amount | C128: =C10+C19+C38+C56+C74+C92+C110 -> 22621.37 | D128: =D10+D19+D38+D56+D74+D92+D110 -> 23427.67 | E128: =E10+E19+E38+E56+E74+E92+E110 -> 24110.11 | F128: =F10+F19+F38+F56+F74+F92+F110 -> 24315.59 | G128: =G10+G19+G38+G56+G74+G92+G110 -> 24774.059 | H128: =H10+H19+H38+H56+H74+H92+H110 -> 25281.341 | I128: =I10+I19+I38+I56+I74+I92+I110 -> 25780.728 | J128: =J10+J19+J38+J56+J74+J92+J110 -> 26320.639 | K128: =K10+K19+K38+K56+K74+K92+K110 -> 27009.989
...

Sheet Depreciation & Finance Cost 
A1: Depreciation & Interest Schedule
A2: Figures in Lakhs ,expect otherwise stated
A3: Particular/Years | B3: Comments | C3: 2021-22 A | D3: 2022-23 A | E3: 2023-24 A | F3: 2024-25 A | G3: 2025-26 E | H3: 2026-27 E | I3: 2027-28 E | J3: 2028-29 E | K3: 2029-30 E
A5: Depreciation on PPE
A6: Land - Freehold
A7: Buildings - Freehold | C7: ='Capex Schedule '!C22 -> 4.08 | D7: ='Capex Schedule '!D22 -> 4.08 | E7: ='Capex Schedule '!E22 -> 4.08 | F7: ='Capex Schedule '!F22 -> 4.08 | G7: ='Capex Schedule '!G22 -> 4.0803468 | H7: ='Capex Schedule '!H22 -> 4.0803468 | I7: ='Capex Schedule '!I22 -> 4.0803468 | J7: ='Capex Schedule '!J22 -> 4.0803468 | K7: ='Capex Schedule '!K22 -> 4.0803468
A8: Buildings | C8: ='Capex Schedule '!C41 -> 0.8 | D8: ='Capex Schedule '!D41 -> 0.8 | E8: ='Capex Schedule '!E41 -> 0.8 | F8: ='Capex Schedule '!F41 -> 0.8 | G8: ='Capex Schedule '!G41 -> 0.8 | H8: ='Capex Schedule '!H41 -> 0.8 | I8: ='Capex Schedule '!I41 -> 0.8 | J8: ='Capex Schedule '!J41 -> 0.8 | K8: ='Capex Schedule '!K41 -> 0.8
A9: Plant and Equipment | C9: ='Capex Schedule '!C59 -> 0 | D9: ='Capex Schedule '!D59 -> 0 | E9: ='Capex Schedule '!E59 -> 0 | F9: ='Capex Schedule '!F59 -> 3.06 | G9: ='Capex Schedule '!G59 -> 3.06 | H9: ='Capex Schedule '!H59 -> 3.06 | I9: ='Capex Schedule '!I59 -> 3.06 | J9: ='Capex Schedule '!J59 -> 3.06 | K9: ='Capex Schedule '!K59 -> 3.06
A10: Furniture and Fixtures | C10: ='Capex Schedule '!C77 -> 45.87 | D10: ='Capex Schedule '!D77 -> 43.42 | E10: ='Capex Schedule '!E77 -> 104.14 | F10: ='Capex Schedule '!F77 -> 122.67 | G10: ='Capex Schedule '!G77 -> 138.617 | H10: ='Capex Schedule '!H77 -> 151.17579 | I10: ='Capex Schedule '!I77 -> 165.13 | J10: ='Capex Schedule '!J77 -> 180.72588 | K10: ='Capex Schedule '!K77 -> 198.27125
A11: Office Equipment | C11: ='Capex Schedule '!C95 -> 143.34 | D11: ='Capex Schedule '!D95 -> 175.81 | E11: ='Capex Schedule '!E95 -> 258.18 | F11: ='Capex Schedule '!F95 -> 262.97 | G11: ='Capex Schedule '!G95 -> 313.4427 | H11: ='Capex Schedule '!H95 -> 377.82427 | I11: ='Capex Schedule '!I95 -> 448.85349 | J11: ='Capex Schedule '!J95 -> 511.97295 | K11: ='Capex Schedule '!K95 -> 599.62327
A12: Vehicles | C12: ='Capex Schedule '!C113 -> 0 | D12: ='Capex Schedule '!D113 -> 0 | E12: ='Capex Schedule '!E113 -> 0 | F12: ='Capex Schedule '!F113 -> 0.58 | G12: ='Capex Schedule '!G113 -> 0.58 | H12: ='Capex Schedule '!H113 -> 0.58 | I12: ='Capex Schedule '!I113 -> 0.58 | J12: ='Capex Schedule '!J113 -> 0.58 | K12: ='Capex Schedule '!K113 -> 0.58
A13: Total | C13: ='Capex Schedule '!C131 -> 194.09 | D13: ='Capex Schedule '!D131 -> 224.11 | E13: ='Capex Schedule '!E131 -> 367.2 | F13: ='Capex Schedule '!F131 -> 394.16 | G13: ='Capex Schedule '!G131 -> 460.58005 | H13: ='Capex Schedule '!H131 -> 537.52041 | I13: ='Capex Schedule '!I131 -> 622.50384 | J13: ='Capex Schedule '!J131 -> 701.21918 | K13: ='Capex Schedule '!K131 -> 806.41487
A15: Amortization on Intangible Asset
A16: Copywrite - Music | C16: ='Capex Schedule '!C154 -> 1043.91 | D16: ='Capex Schedule '!D154 -> 1774.52 | E16: ='Capex Schedule '!E154 -> 2999.07 | F16: ='Capex Schedule '!F154 -> 4870.63 | G16: ='Capex Schedule '!G154 -> 6958.174 | H16: ='Capex Schedule '!H154 -> 9717.545 | I16: ='Capex Schedule '!I154 -> 12476.916 | J16: ='Capex Schedule '!J154 -> 13225.531 | K16: ='Capex Schedule '!K154 -> 14019.063
A17: Computer Software | C17: ='Capex Schedule '!C174 -> 21.04 | D17: ='Capex Schedule '!D174 -> 18.5 | E17: ='Capex Schedule '!E174 -> 18.97 | F17: ='Capex Schedule '!F174 -> 109.31 | G17: ='Capex Schedule '!G174 -> 112.974 | H17: ='Capex Schedule '!H174 -> 142.974 | I17: ='Capex Schedule '!I174 -> 162.974 | J17: ='Capex Schedule '!J174 -> 172.974 | K17: ='Capex Schedule '!K174 -> 182.974
A18: Online Platform Rights | C18: ='Capex Schedule '!C194 -> 0 | D18: ='Capex Schedule '!D194 -> 0 | E18: ='Capex Schedule '!E194 -> 40.12 | F18: ='Capex Schedule '!F194 -> 98.92 | G18: ='Capex Schedule '!G194 -> 94.66 | H18: ='Capex Schedule '!H194 -> 94.66 | I18: ='Capex Schedule '!I194 -> 94.66 | J18: ='Capex Schedule '!J194 -> 50.28 | K18: ='Capex Schedule '!K194 -> 0
A19: Brand - Filter Copy | C19: ='Capex Schedule '!C232 -> 0 | D19: ='Capex Schedule '!D232 -> 0 | E19: ='Capex Schedule '!E232 -> 21.75 | F19: ='Capex Schedule '!F232 -> 52.2 | G19: ='Capex Schedule '!G232 -> 52.2 | H19: ='Capex Schedule '!H232 -> 52.2 | I19: ='Capex Schedule '!I232 -> 52.2 | J19: ='Capex Schedule '!J232 -> 52.2 | K19: ='Capex Schedule '!K232 -> 52.2
A20: Customer Relationship - Filter Copy | C20: ='Capex Schedule '!C252 -> 0 | D20: ='Capex Schedule '!D252 -> 0 | E20: ='Capex Schedule '!E252 -> 60.68 | F20: ='Capex Schedule '!F252 -> 145.63 | G20: ='Capex Schedule '!G252 -> 145.63 | H20: ='Capex Schedule '!H252 -> 145.63 | I20: ='Capex Schedule '!I252 -> 145.63 | J20: ='Capex Schedule '!J252 -> 145.63 | K20: ='Capex Schedule '!K252 -> 145.63
A21: Customer Relationship - Clout | C21: ='Capex Schedule '!C272 -> 0 | D21: ='Capex Schedule '!D272 -> 0 | E21: ='Capex Schedule '!E272 -> 9.35 | F21: ='Capex Schedule '!F272 -> 22.44 | G21: ='Capex Schedule '!G272 -> 22.428571 | H21: ='Capex Schedule '!H272 -> 22.428571 | I21: ='Capex Schedule '!I272 -> 22.428571 | J21: ='Capex Schedule '!J272 -> 22.428571 | K21: ='Capex Schedule '!K272 -> 22.428571
A22: Total | C22: ='Capex Schedule '!C292 -> 1064.95 | D22: ='Capex Schedule '!D292 -> 1793.02 | E22: ='Capex Schedule '!E292 -> 3149.94 | F22: ='Capex Schedule '!F292 -> 5299.13 | G22: ='Capex Schedule '!G292 -> 7386.0666 | H22: ='Capex Schedule '!H292 -> 10175.438 | I22: ='Capex Schedule '!I292 -> 12954.809 | J22: ='Capex Schedule '!J292 -> 13669.044 | K22: ='Capex Schedule '!K292 -> 14422.295
A24: Depreciation & Amortization
A25: Depreciation on PPE | C25: =C13 -> 194.09 | D25: =D13 -> 224.11 | E25: =E13 -> 367.2 | F25: =F13 -> 394.16 | G25: =G13 -> 460.58005 | H25: =H13 -> 537.52041 | I25: =I13 -> 622.50384 | J25: =J13 -> 701.21918 | K25: =K13 -> 806.41487
A26: Depreciation on right-of-use assets | C26: ='Lease Schedule '!C12 -> 45.52 | D26: ='Lease Schedule '!D12 -> 59.28 | E26: ='Lease Schedule '!E12 -> 95.03 | F26: ='Lease Schedule '!F12 -> 122.24 | G26: ='Lease Schedule '!G12 -> 122.4 | H26: ='Lease Schedule '!H12 -> 20 | I26: ='Lease Schedule '!I12 -> 20 | J26: ='Lease Schedule '!J12 -> 20 | K26: ='Lease Schedule '!K12 -> 20
A27: Depreciation on investment properties | C27: ='Capex Schedule '!C312 -> 5.54 | D27: ='Capex Schedule '!D312 -> 5.54 | E27: ='Capex Schedule '!E312 -> 5.54 | F27: ='Capex Schedule '!F312 -> 5.54 | G27: ='Capex Schedule '!G312 -> 5.54 | H27: ='Capex Schedule '!H312 -> 5.54 | I27: ='Capex Schedule '!I312 -> 5.54 | J27: ='Capex Schedule '!J312 -> 5.54 | K27: ='Capex Schedule '!K312 -> 5.54
A28: Amortisation on Intangible asset | C28: =C22 -> 1064.95 | D28: =D22 -> 1793.02 | E28: =E22 -> 3149.94 | F28: =F22 -> 5299.13 | G28: =G22 -> 7386.0666 | H28: =H22 -> 10175.438 | I28: =I22 -> 12954.809 | J28: =J22 -> 13669.044 | K28: =K22 -> 14422.295
A29: Total depreciation and amortisation expense | C29: =SUM(C25:C28) -> 1310.1 | D29: =SUM(D25:D28) -> 2081.95 | E29: =SUM(E25:E28) -> 3617.71 | F29: =SUM(F25:F28) -> 5821.07 | G29: =SUM(G25:G28) -> 7974.5866 | H29: =SUM(H25:H28) -> 10738.498 | I29: =SUM(I25:I28) -> 13602.852 | J29: =SUM(J25:J28) -> 14395.803 | K29: =SUM(K25:K28) -> 15254.25
A33: Finance Cost
A34: On loans , others and Other Borrowing cost | C34: 49.35 | D34: 62.22 | E34: 298.93 | F34: 88.23 | G34: =G44*G45 -> 123.35356 | H34: =H44*H45 -> 123.35356 | I34: =I44*I45 -> 123.35356 | J34: =J44*J45 -> 123.35356 | K34: =K44*K45 -> 123.35356
A35: Unwinding of discount on financial liabilities/provision | C35: 391.4 | D35: 498.9 | E35: 0 | F35: 414 | G35: 0 | H35: 0 | I35: 0 | J35: 0 | K35: 0
A36: On lease liabilities | C36: 11.19 | D36: 10.36 | E36: 25.28 | F36: 71.92 | G36: ='Lease Schedule '!G24 -> 29.7594 | H36: ='Lease Schedule '!H24 -> 20.854999 | I36: ='Lease Schedule '!I24 -> 14.61491 | J36: ='Lease Schedule '!J24 -> 10.241938 | K36: ='Lease Schedule '!K24 -> 7.1774164
A37: Total Finance Cost | C37: 451.94 | D37: 571.48 | E37: 324.21 | F37: 574.15 | G37: =SUM(G34:G36) -> 153.11296 | H37: =SUM(H34:H36) -> 144.20856 | I37: =SUM(I34:I36) -> 137.96847 | J37: =SUM(J34:J36) -> 133.5955 | K37: =SUM(K34:K36) -> 130.53098
A39: ='Balance Sheet'!A37 -> Non-current liabilities
A40: ='Balance Sheet'!A39 -> Other financial liabilities | B40: Includes deferred consideration | C40: ='Balance Sheet'!C39 -> 0 | D40: ='Balance Sheet'!D39 -> 0 | E40: ='Balance Sheet'!E39 -> 20895 | F40: ='Balance Sheet'!F39 -> 3094 | G40: ='Balance Sheet'!G39 -> 3094 | H40: ='Balance Sheet'!H39 -> 3094 | I40: ='Balance Sheet'!I39 -> 3094 | J40: ='Balance Sheet'!J39 -> 3094 | K40: ='Balance Sheet'!K39 -> 3094
A41: ='Balance Sheet'!A44 -> Current liabilities
A42: ='Balance Sheet'!A45 -> Borrowings | B42: Includes loan Repayable on demand from bank | C42: ='Balance Sheet'!C45 -> 0 | D42: ='Balance Sheet'!D45 -> 0 | E42: ='Balance Sheet'!E45 -> 165.02 | F42: ='Balance Sheet'!F45 -> 0 | G42: ='Balance Sheet'!G45 -> 0 | H42: ='Balance Sheet'!H45 -> 0 | I42: ='Balance Sheet'!I45 -> 0 | J42: ='Balance Sheet'!J45 -> 0 | K42: ='Balance Sheet'!K45 -> 0
A43: ='Balance Sheet'!A48 -> Other financial liabilities | C43: ='Balance Sheet'!C48 -> 4305.57 | D43: ='Balance Sheet'!D48 -> 5654.42 | E43: ='Balance Sheet'!E48 -> 6098.71 | F43: ='Balance Sheet'!F48 -> 8119.96 | G43: ='Balance Sheet'!G48 -> 8119.96 | H43: ='Balance Sheet'!H48 -> 8119.96 | I43: ='Balance Sheet'!I48 -> 8119.96 | J43: ='Balance Sheet'!J48 -> 8119.96 | K43: ='Balance Sheet'!K48 -> 8119.96
A44: Total | C44: =C40+C42+C43 -> 4305.57 | D44: =D40+D42+D43 -> 5654.42 | E44: =E40+E42+E43 -> 27158.73 | F44: =F40+F42+F43 -> 11213.96 | G44: =G40+G42+G43 -> 11213.96 | H44: =H40+H42+H43 -> 11213.96 | I44: =I40+I42+I43 -> 11213.96 | J44: =J40+J42+J43 -> 11213.96 | K44: =K40+K42+K43 -> 11213.96
A45: Effective Interest Rate | C45: =C34/C43 -> 0.011461897 | D45: =D34/D43 -> 0.011003781 | E45: =E34/E43 -> 0.049015284 | F45: =F34/F43 -> 0.010865817 | G45: ='Assumption Sheet'!G133 -> 0.011 | H45: ='Assumption Sheet'!H133 -> 0.011 | I45: ='Assumption Sheet'!I133 -> 0.011 | J45: ='Assumption Sheet'!J133 -> 0.011 | K45: ='Assumption Sheet'!K133 -> 0.011

Sheet WC Schedule 
A1: Working Capital Schedule
A2: Figures in Lakhs ,expect otherwise stated
A3: Particular/Years | B3: Comments | C3: 2021-22 A | D3: 2022-23 A | E3: 2023-24 A | F3: 2024-25 A | G3: 2025-26 E | H3: 2026-27 E | I3: 2027-28 E | J3: 2028-29 E | K3: 2029-30 E
A5: Music (Carvaan and Music Rights)
A6: Opening Inventory | C6: 4513.73 | D6: 5472.9 | E6: 6615.28 | F6: 10635.92
A7: Less:Transferred pursuant to the scheme of arrangement | C7: 0 | D7: 444.79 | E7: 0 | F7: 0
A8: Add:Purchase Of inventory | C8: 7871.45 | D8: 10678.5 | E8: 14716.83 | F8: 13518.41
A9: Less:Closing Inventory | C9: 5472.9 | D9: 6615.86 | E9: 10638.12 | F9: 15445.92
A10: COGS -Music | C10: =C6-C7+C8-C9 -> 6912.28 | D10: =D6-D7+D8-D9 -> 9090.75 | E10: =E6-E7+E8-E9 -> 10693.99 | F10: =F6-F7+F8-F9 -> 8708.41
A12: Films, Tv serials and Digital content (under production and untelecasted)
A13: Opening Inventory | C13: 2383.39 | D13: 5041.79 | E13: 11048.86 | F13: 13289.91
A14: Add:Purchase Of inventory | C14: 10056.75 | D14: 18181.59 | E14: 14749.38 | F14: 40880.01
A15: Less:Closing Inventory | C15: 5041.79 | D15: 9809.7 | E15: 13287.71 | F15: 8569.65
A16: COGS - Films, Tv serials and Digital content | C16: =C13+C14-C15 -> 7398.35 | D16: =D13+D14-D15 -> 13413.68 | E16: =E13+E14-E15 -> 12510.53 | F16: =F13+F14-F15 -> 45600.27
A18: ='Revenue Model'!A7 -> Segment Wise Revenue Breakup
A19: ='Revenue Model'!A8 -> Sale of product | C19: ='Revenue Model'!C8 -> 10167.72 | D19: ='Revenue Model'!D8 -> 12760.93 | E19: ='Revenue Model'!E8 -> 12962 | F19: ='Revenue Model'!F8 -> 8154.52 | G19: ='Revenue Model'!G8 -> 5218.8928 | H19: ='Revenue Model'!H8 -> 3340.0914 | I19: ='Revenue Model'!I8 -> 2137.6585 | J19: ='Revenue Model'!J8 -> 1368.1014 | K19: ='Revenue Model'!K8 -> 875.58492
A20: ='Revenue Model'!A9 -> Sale of service-
A21: ='Revenue Model'!A10 -> License Fees- Music | C21: ='Revenue Model'!C10 -> 36328.85 | D21: ='Revenue Model'!D10 -> 42122.5 | E21: ='Revenue Model'!E10 -> 47828.58 | F21: ='Revenue Model'!F10 -> 53860.92 | G21: ='Revenue Model'!G10 -> 64308.4 | H21: ='Revenue Model'!H10 -> 79353.293 | I21: ='Revenue Model'!I10 -> 91176.806 | J21: ='Revenue Model'!J10 -> 103721.92 | K21: ='Revenue Model'!K10 -> 118674.53
A22: ='Revenue Model'!A11 -> Artist Management | C22: ='Revenue Model'!C11 -> 0 | D22: ='Revenue Model'!D11 -> 0 | E22: ='Revenue Model'!E11 -> 2075.82 | F22: ='Revenue Model'!F11 -> 6931.24 | G22: ='Revenue Model'!G11 -> 9250.114 | H22: ='Revenue Model'!H11 -> 9652.508 | I22: ='Revenue Model'!I11 -> 16520.213 | J22: ='Revenue Model'!J11 -> 26591.471 | K22: ='Revenue Model'!K11 -> 39004.672
A23: ='Revenue Model'!A12 -> Income from videos | C23: ='Revenue Model'!C12 -> 10239.13 | D23: ='Revenue Model'!D12 -> 10846.29 | E23: ='Revenue Model'!E12 -> 11586.66 | F23: ='Revenue Model'!F12 -> 19197.76 | G23: ='Revenue Model'!G12 -> 22077.424 | H23: ='Revenue Model'!H12 -> 25389.038 | I23: ='Revenue Model'!I12 -> 29197.393 | J23: ='Revenue Model'!J12 -> 33577.002 | K23: ='Revenue Model'!K12 -> 38613.553
A24: ='Revenue Model'!A13 -> Income from events | C24: ='Revenue Model'!C13 -> 0 | D24: ='Revenue Model'!D13 -> 4895.66 | E24: ='Revenue Model'!E13 -> 1344.17 | F24: ='Revenue Model'!F13 -> 28524.12 | G24: ='Revenue Model'!G13 -> 25671.708 | H24: ='Revenue Model'!H13 -> 23104.537 | I24: ='Revenue Model'!I13 -> 20794.083 | J24: ='Revenue Model'!J13 -> 18714.675 | K24: ='Revenue Model'!K13 -> 16843.208
A25: ='Revenue Model'!A14 -> Other operating income | C25: ='Revenue Model'!C14 -> 1327.06 | D25: ='Revenue Model'!D14 -> 3036.74 | E25: ='Revenue Model'!E14 -> 4503.17 | F25: ='Revenue Model'!F14 -> 467.2 | G25: ='Revenue Model'!G14 -> 0 | H25: ='Revenue Model'!H14 -> 0 | I25: ='Revenue Model'!I14 -> 0 | J25: ='Revenue Model'!J14 -> 0 | K25: ='Revenue Model'!K14 -> 0
A26: Total | C26: =SUM(C19:C25) -> 58062.76 | D26: =SUM(D19:D25) -> 73662.12 | E26: =SUM(E19:E25) -> 80300.4 | F26: =SUM(F19:F25) -> 117135.76 | G26: =SUM(G19:G25) -> 126526.54 | H26: =SUM(H19:H25) -> 140839.47 | I26: =SUM(I19:I25) -> 159826.15 | J26: =SUM(J19:J25) -> 183973.17 | K26: =SUM(K19:K25) -> 214011.55
A28: Total Music Revenue | B28: Product, License Fees, Artist Management and others | C28: =C19+C21+C22+C25 -> 47823.63 | D28: =D19+D21+D22+D25 -> 57920.17 | E28: =E19+E21+E22+E25 -> 67369.57 | F28: =F19+F21+F22+F25 -> 69413.88 | G28: =G19+G21+G22+G25 -> 78777.406 | H28: =H19+H21+H22+H25 -> 92345.893 | I28: =I19+I21+I22+I25 -> 109834.68 | J28: =J19+J21+J22+J25 -> 131681.5 | K28: =K19+K21+K22+K25 -> 158554.79
A29: Closing Inventory of Music | C29: =C9 -> 5472.9 | D29: =D9 -> 6615.86 | E29: =E9 -> 10638.12 | F29: =F9 -> 15445.92 | G29: =G28/G30 -> 12949.711 | H29: =H28/H30 -> 15180.147 | I29: =I28/I30 -> 18055.016 | J29: =J28/J30 -> 21646.273 | K29: =K28/K30 -> 26063.801
A30: Inventory turnover ratio for music | C30: =C28/C29 -> 8.7382613 | D30: =D28/D29 -> 8.7547454 | E30: =E28/E29 -> 6.3328455 | F30: =F28/F29 -> 4.4939945 | G30: =365/G31 -> 6.0833333 | H30: =365/H31 -> 6.0833333 | I30: =365/I31 -> 6.0833333 | J30: =365/J31 -> 6.0833333 | K30: =365/K31 -> 6.0833333
A31: Days Inventory Outstanding of Music | C31: =365/C30 -> 41.770324 | D31: =365/D30 -> 41.691675 | E31: =365/E30 -> 57.636019 | F31: =365/F30 -> 81.219502 | G31: ='Assumption Sheet'!G142 -> 60 | H31: ='Assumption Sheet'!H142 -> 60 | I31: ='Assumption Sheet'!I142 -> 60 | J31: ='Assumption Sheet'!J142 -> 60 | K31: ='Assumption Sheet'!K142 -> 60
A34: Total Revenue from Films, Tv Serials and Digital Content | B34: Also contains revenue from events | C34: =SUM(C24:C25) -> 1327.06 | D34: =SUM(D24:D25) -> 7932.4 | E34: =SUM(E24:E25) -> 5847.34 | F34: =SUM(F24:F25) -> 28991.32 | G34: =SUM(G24:G25) -> 25671.708 | H34: =SUM(H24:H25) -> 23104.537 | I34: =SUM(I24:I25) -> 20794.083 | J34: =SUM(J24:J25) -> 18714.675 | K34: =SUM(K24:K25) -> 16843.208
A35: Closing Inventory of Films, Tv Serials and Digital Content | C35: =C15 -> 5041.79 | D35: =D15 -> 9809.7 | E35: =E15 -> 13287.71 | F35: =F15 -> 8569.65 | G35: =G34/G36 -> 2110.0034 | H35: =H34/H36 -> 1899.0031 | I35: =I34/I36 -> 1709.1028 | J35: =J34/J36 -> 1538.1925 | K35: =K34/K36 -> 1384.3732
A36: Inventory turnover ratio for Films, Tv Serials and Digital Content | C36: =C34/C35 -> 0.26321207 | D36: =D34/D35 -> 0.80862819 | E36: =E34/E35 -> 0.44005626 | F36: =F34/F35 -> 3.3830226 | G36: =365/G37 -> 12.166667 | H36: =365/H37 -> 12.166667 | I36: =365/I37 -> 12.166667 | J36: =365/J37 -> 12.166667 | K36: =365/K37 -> 12.166667
A37: Days Inventory Outstanding of Films, Tv Serials and Digital Content | C37: =365/C36 -> 1386.7145 | D37: =365/D36 -> 451.38174 | E37: =365/E36 -> 829.43939 | F37: =365/F36 -> 107.89168 | G37: ='Assumption Sheet'!G143 -> 30 | H37: ='Assumption Sheet'!H143 -> 30 | I37: ='Assumption Sheet'!I143 -> 30 | J37: ='Assumption Sheet'!J143 -> 30 | K37: ='Assumption Sheet'!K143 -> 30
A39: Total Inventory | C39: =C35+C29 -> 10514.69 | D39: =D35+D29 -> 16425.56 | E39: =E35+E29 -> 23925.83 | F39: =F35+F29 -> 24015.57 | G39: =G35+G29 -> 15059.714 | H39: =H35+H29 -> 17079.15 | I39: =I35+I29 -> 19764.118 | J39: =J35+J29 -> 23184.466 | K39: =K35+K29 -> 27448.175
A42: =IS!A4 -> Revenue from operations | C42: =IS!C4 -> 58062.76 | D42: =IS!D4 -> 73662.12 | E42: =IS!E4 -> 80300.4 | F42: =IS!F4 -> 117135.76 | G42: =IS!G4 -> 126526.54 | H42: =IS!H4 -> 140839.47 | I42: =IS!I4 -> 159826.15 | J42: =IS!J4 -> 183973.17 | K42: =IS!K4 -> 214011.55
A43: ='Balance Sheet'!A18 -> Trade receivables | C43: ='Balance Sheet'!C18 -> 10780.25 | D43: ='Balance Sheet'!D18 -> 14796.95 | E43: ='Balance Sheet'!E18 -> 15873.78 | F43: ='Balance Sheet'!F18 -> 14321.51 | G43: =G42/G44 -> 20798.883 | H43: =H42/H44 -> 23151.693 | I43: =I42/I44 -> 26272.793 | J43: =J42/J44 -> 30242.165 | K43: =K42/K44 -> 35179.981
A44: Trade receivables turnover ratio | C44: =C42/C43 -> 5.3860309 | D44: =D42/D43 -> 4.9781962 | E44: =E42/E43 -> 5.0586817 | F44: =F42/F43 -> 8.1790091 | G44: =365/G45 -> 6.0833333 | H44: =365/H45 -> 6.0833333 | I44: =365/I45 -> 6.0833333 | J44: =365/J45 -> 6.0833333 | K44: =365/K45 -> 6.0833333
A45: Days Sales Outstanding | C45: =365/C44 -> 67.767899 | D45: =365/D44 -> 73.31973 | E45: =365/E44 -> 72.153186 | F45: =365/F44 -> 44.626433 | G45: ='Assumption Sheet'!G144 -> 60 | H45: ='Assumption Sheet'!H144 -> 60 | I45: ='Assumption Sheet'!I144 -> 60 | J45: ='Assumption Sheet'!J144 -> 60 | K45: ='Assumption Sheet'!K144 -> 60
A47: =A43 -> Trade receivables | C47: =C43 -> 10780.25 | D47: =D43 -> 14796.95 | E47: =E43 -> 15873.78 | F47: =F43 -> 14321.51 | G47: =G43 -> 20798.883 | H47: =H43 -> 23151.693 | I47: =I43 -> 26272.793 | J47: =J43 -> 30242.165 | K47: =K43 -> 35179.981
A49: Opening Inventory | C49: =C6+C13 -> 6897.12 | D49: =D6+D13 -> 10514.69 | E49: =E6+E13 -> 17664.14 | F49: =F6+F13 -> 23925.83 | G49: =F51 -> 24015.57 | H49: =G51 -> 15059.714 | I49: =H51 -> 17079.15 | J49: =I51 -> 19764.118 | K49: =J51 -> 23184.466
A50: COGS | C50: =IS!C5+IS!C6 -> 14310.63 | D50: =IS!D5+IS!D6 -> 22504.43 | E50: =IS!E5+IS!E6 -> 23204.52 | F50: =IS!F5+IS!F6 -> 54308.68 | G50: =IS!G5+IS!G6 -> 50226.895 | H50: =IS!H5+IS!H6 -> 52894.06 | I50: =IS!I5+IS!I6 -> 54262.964 | J50: =IS!J5+IS!J6 -> 56709.062 | K50: =IS!K5+IS!K6 -> 63027.585
A51: Closing Inventory | C51: =C39 -> 10514.69 | D51: =D39 -> 16425.56 | E51: =E39 -> 23925.83 | F51: =F39 -> 24015.57 | G51: =G39 -> 15059.714 | H51: =H39 -> 17079.15 | I51: =I39 -> 19764.118 | J51: =J39 -> 23184.466 | K51: =K39 -> 27448.175
A52: Purchases | B52: Closing + COGS - Opening | C52: =C51+C50-C49 -> 17928.2 | D52: =D51+D50-D49 -> 28415.3 | E52: =E51+E50-E49 -> 29466.21 | F52: =F51+F50-F49 -> 54398.42 | G52: =G51+G50-G49 -> 41271.039 | H52: =H51+H50-H49 -> 54913.496 | I52: =I51+I50-I49 -> 56947.932 | J52: =J51+J50-J49 -> 60129.409 | K52: =K51+K50-K49 -> 67291.294
A54: ='Balance Sheet'!A47 -> Trade Payables - MSME & Others | C54: ='Balance Sheet'!C47 -> 6452.39 | D54: ='Balance Sheet'!D47 -> 7027.26 | E54: ='Balance Sheet'!E47 -> 9335.89 | F54: ='Balance Sheet'!F47 -> 12754.61 | G54: =G52/G55 -> 12437.847 | H54: =H52/H55 -> 15044.794 | I54: =I52/I55 -> 15602.173 | J54: =J52/J55 -> 16473.811 | K54: =K52/K55 -> 18435.971
A55: Trade Payable Turnover Ratio | C55: =C52/C54 -> 2.7785363 | D55: =D52/D54 -> 4.0435817 | E55: =E52/E54 -> 3.1562293 | F55: =F52/F54 -> 4.2650007 | G55: =365/G56 -> 3.3181818 | H55: =365/H56 -> 3.65 | I55: =365/I56 -> 3.65 | J55: =365/J56 -> 3.65 | K55: =365/K56 -> 3.65
A56: Days Payable Outstanding | C56: =365/C55 -> 131.36413 | D56: =365/D55 -> 90.266508 | E56: =365/E55 -> 115.64432 | F56: =365/F55 -> 85.580292 | G56: ='Assumption Sheet'!G145 -> 110 | H56: ='Assumption Sheet'!H145 -> 100 | I56: ='Assumption Sheet'!I145 -> 100 | J56: ='Assumption Sheet'!J145 -> 100 | K56: ='Assumption Sheet'!K145 -> 100
A58: =A54 -> Trade Payables - MSME & Others | C58: =C54 -> 6452.39 | D58: =D54 -> 7027.26 | E58: =E54 -> 9335.89 | F58: =F54 -> 12754.61 | G58: =G54 -> 12437.847 | H58: =H54 -> 15044.794 | I58: =I54 -> 15602.173 | J58: =J54 -> 16473.811 | K58: =K54 -> 18435.971

Sheet Lease Schedule 
A1: Lease Schedule
A2: Figures in Lakhs ,expect otherwise stated
A3: Particular/Years | B3: Comments | C3: 2021-22 A | D3: 2022-23 A | E3: 2023-24 A | F3: 2024-25 A | G3: 2025-26 E | H3: 2026-27 E | I3: 2027-28 E | J3: 2028-29 E | K3: 2029-30 E
A5: Right of Use Asset (ROU)
A7: Opening Balance | C7: 109.46 | D7: 125.88 | E7: 66.6 | F7: 334.54 | G7: =F14 -> 212.3 | H7: =G14 -> 89.9 | I7: =H14 -> 69.9 | J7: =I14 -> 49.9 | K7: =J14 -> 29.9
A8: Acquisition through business combination | D8: 0 | E8: 362.97 | F8: 0 | G8: 0 | H8: 0 | I8: 0 | J8: 0 | K8: 0
A9: Addition | C9: 61.94 | D9: 0 | E9: 0 | F9: 0 | G9: 0 | H9: 0 | I9: 0 | J9: 0 | K9: 0
A10: Deletion | C10: 0 | D10: 0 | E10: 0 | F10: 0 | G10: 0 | H10: 0 | I10: 0 | J10: 0 | K10: 0
A12: Depreciation | C12: 45.52 | D12: 59.28 | E12: 95.03 | F12: 122.24 | G12: ='Assumption Sheet'!G124 -> 122.4 | H12: ='Assumption Sheet'!H124 -> 20 | I12: ='Assumption Sheet'!I124 -> 20 | J12: ='Assumption Sheet'!J124 -> 20 | K12: ='Assumption Sheet'!K124 -> 20
A14: Closing Balance | C14: 125.88 | D14: 66.6 | E14: 334.54 | F14: 212.3 | G14: =SUM(G7:G10)-G12 -> 89.9 | H14: =SUM(H7:H10)-H12 -> 69.9 | I14: =SUM(I7:I10)-I12 -> 49.9 | J14: =SUM(J7:J10)-J12 -> 29.9 | K14: =SUM(K7:K10)-K12 -> 9.9
A16: Lease Liability - Leasehold premises and vehicles
A18: Opening Balance | C18: 110.22 | D18: 130.31 | E18: 71.25 | F18: 378.32 | G18: =F27 -> 270.54 | H18: =G27 -> 189.5909 | I18: =H27 -> 132.86282 | J18: =I27 -> 93.108529 | K18: =J27 -> 65.24924
A19: Acquisition through business combination | C19: 0 | D19: 0 | E19: 397.41 | F19: 0 | G19: 0 | H19: 0 | I19: 0 | J19: 0 | K19: 0
A20: Addition | C20: 61.94 | D20: 0 | E20: 0 | F20: 0 | G20: 0 | H20: 0 | I20: 0 | J20: 0 | K20: 0
A21: Deletion | C21: 0 | D21: 0 | E21: 0 | F21: 0 | G21: 0 | H21: 0 | I21: 0 | J21: 0 | K21: 0
A23: Payment | C23: =SUM(C24:C25) -> 64.23 | D23: =SUM(D24:D25) -> 79.78 | E23: =SUM(E24:E25) -> 140.9 | F23: =SUM(F24:F25) -> 198.66 | G23: =PMT(G31,G32,-G18) -> 110.7085 | H23: =PMT(H31,H32,-H18) -> 77.583073 | I23: =PMT(I31,I32,-I18) -> 54.369203 | J23: =PMT(J31,J32,-J18) -> 38.101227 | K23: =PMT(K31,K32,-K18) -> 26.700842
A24: Payment towards Interest | C24: 11.19 | D24: 10.36 | E24: 25.28 | F24: 45.44 | G24: =G18*G31 -> 29.7594 | H24: =H18*H31 -> 20.854999 | I24: =I18*I31 -> 14.61491 | J24: =J18*J31 -> 10.241938 | K24: =K18*K31 -> 7.1774164
A25: Payment towards Principal | C25: 53.04 | D25: 69.42 | E25: 115.62 | F25: 153.22 | G25: =G23-G24 -> 80.949104 | H25: =H23-H24 -> 56.728074 | I25: =I23-I24 -> 39.754293 | J25: =J23-J24 -> 27.859289 | K25: =K23-K24 -> 19.523426
A27: Closing Balance | C27: 130.31 | D27: 71.25 | E27: 378.32 | F27: 270.54 | G27: =G18+G19+G20-G21-G25 -> 189.5909 | H27: =H18+H19+H20-H21-H25 -> 132.86282 | I27: =I18+I19+I20-I21-I25 -> 93.108529 | J27: =J18+J19+J20-J21-J25 -> 65.24924 | K27: =K18+K19+K20-K21-K25 -> 45.725815
A28: Towards Current | C28: 59.06 | D28: 57.47 | E28: 152.67 | F28: 129.12 | G28: =G27*'Assumption Sheet'!G127 -> 84.307398 | H28: =H27*'Assumption Sheet'!H127 -> 59.081523 | I28: =I27*'Assumption Sheet'!I127 -> 41.403559 | J28: =J27*'Assumption Sheet'!J127 -> 29.015073 | K28: =K27*'Assumption Sheet'!K127 -> 20.333384
A29: Towards Non-Current | C29: 71.25 | D29: 13.78 | E29: 225.65 | F29: 141.43 | G29: =G27-G28 -> 105.2835 | H29: =H27-H28 -> 73.7813 | I29: =I27-I28 -> 51.70497 | J29: =J27-J28 -> 36.234168 | K29: =K27-K28 -> 25.392431
A31: Effective Interest Rate | C31: =C24/C18 -> 0.10152422 | D31: =D24/D18 -> 0.079502724 | E31: =E24/E18 -> 0.35480702 | F31: =F24/F18 -> 0.12010996 | G31: ='Assumption Sheet'!G128 -> 0.11 | H31: ='Assumption Sheet'!H128 -> 0.11 | I31: ='Assumption Sheet'!I128 -> 0.11 | J31: ='Assumption Sheet'!J128 -> 0.11 | K31: ='Assumption Sheet'!K128 -> 0.11
A32: Average life of the lease | G32: ='Assumption Sheet'!G129 -> 3 | H32: ='Assumption Sheet'!H129 -> 3 | I32: ='Assumption Sheet'!I129 -> 3 | J32: ='Assumption Sheet'!J129 -> 3 | K32: ='Assumption Sheet'!K129 -> 3

Sheet Other Income Schedule 
A1: Other Income Schedule
A2: Figures in Lakhs ,expect otherwise stated
A3: Particular/Years | B3: Comments | C3: 2021-22 A | D3: 2022-23 A | E3: 2023-24 A | F3: 2024-25 A | G3: 2025-26 E | H3: 2026-27 E | I3: 2027-28 E | J3: 2028-29 E | K3: 2029-30 E
A5: Liabilities/Provisions no longer required written back | C5: 28.89 | D5: 1.37 | E5: 394.08 | F5: 128.69 | G5: 0 | H5: 0 | I5: 0 | J5: 0 | K5: 0
A6: Allowance for expected credit loss written back | C6: 39.48 | D6: 0 | E6: 88.08 | F6: 0 | G6: 0 | H6: 0 | I6: 0 | J6: 0 | K6: 0
A7: Provision for Long term Investment write back | C7: 0 | D7: 0 | E7: 0 | F7: 0 | G7: 0 | H7: 0 | I7: 0 | J7: 0 | K7: 0
A8: Interest income under effective interest method | C8: 1840.51 | D8: 2950.35 | E8: 4089.6 | F8: 4188.83 | G8: - | H8: - | I8: - | J8: - | K8: -
A9: Dividend income from equity investments designated at FVOCI | C9: 695.29 | D9: 0 | E9: 0 | F9: 0 | G9: 0 | H9: 0 | I9: 0 | J9: 0 | K9: 0
A10: Profit on sale of property. plant and equipment | C10: 0 | D10: 0 | E10: 0 | F10: 1.94 | G10: 0 | H10: 0 | I10: 0 | J10: 0 | K10: 0
A11: Profit on sale of investment in mutual fund | C11: 48.3 | D11: 1439.27 | E11: 2134.99 | F11: 1305.82 | G11: - | H11: - | I11: - | J11: - | K11: -
A12: Fair value gain on mutual fund at FVTPL | C12: 555.76 | D12: 564.69 | E12: -505.31 | F12: 90.34 | G12: - | H12: - | I12: - | J12: - | K12: -
A13: Gain on sale/ fair valuation of current investments (net) | C13: 0 | D13: 0 | E13: 1629.68 | F13: 1396.16 | G13: 0 | H13: 0 | I13: 0 | J13: 0 | K13: 0
A14: Rent Income | C14: 18.9 | D14: 19.25 | E14: 23.21 | F14: 26.94 | G14: =G38 -> 27.4788 | H14: =H38 -> 28.028376 | I14: =I38 -> 28.588944 | J14: =J38 -> 29.160722 | K14: =K38 -> 29.743937
A15: Net gain on foreign currency transactions | C15: 89.68 | D15: 264.9 | E15: 0 | F15: 33.45 | G15: 0 | H15: 0 | I15: 0 | J15: 0 | K15: 0
A16: Insurance claim | C16: 164.04 | D16: 87.14 | E16: 0 | F16: 13.42 | G16: 0 | H16: 0 | I16: 0 | J16: 0 | K16: 0
A17: Other non-operating income | C17: 10.16 | D17: 36.16 | E17: 141.21 | F17: 17.83 | G17: 17.83 | H17: 17.83 | I17: 17.83 | J17: 17.83 | K17: 17.83
A18: Interest Income Calculated Below | B18: Combined entry for Interest income under effective interest method, Profit on sale of investment in mutual fund, Fair value gain on mutual fund at FVTPL | C18: - | D18: - | E18: - | F18: - | G18: =G22 -> 4937.2552 | H18: =H22 -> 5767.5613 | I18: =I22 -> 7139.0647 | J18: =J22 -> 10476.216 | K18: =K22 -> 14232.214
A19: Total | C19: 3497.01 | D19: 5363.13 | E19: 6365.86 | F19: 5807.26 | G19: =SUM(G5:G18) -> 4982.564 | H19: =SUM(H5:H18) -> 5813.4197 | I19: =SUM(I5:I18) -> 7185.4836 | J19: =SUM(J5:J18) -> 10523.207 | K19: =SUM(K5:K18) -> 14279.788
A22: Interest income under effective interest method , Profit on sale of investment in mutual fund, Fair value gain on mutual fund at FVTPL, | C22: =C8+C11+C12 -> 2444.57 | D22: =D8+D11+D12 -> 4954.31 | E22: =E8+E11+E12 -> 5719.28 | F22: =F8+F11+F12 -> 5584.99 | G22: =G33*G34 -> 4937.2552 | H22: =H33*H34 -> 5767.5613 | I22: =I33*I34 -> 7139.0647 | J22: =J33*J34 -> 10476.216 | K22: =K33*K34 -> 14232.214
A24: Interest Earning Investments-
A25: ='Balance Sheet'!A5 -> Non-current assets
A26: ='Balance Sheet'!A12 -> Other financial assets | B26: Security deposits. Bank deposits with remaining maturity more than 12 months, Contractual investment rights | C26: ='Balance Sheet'!C12 -> 14725.69 | D26: ='Balance Sheet'!D12 -> 5295.59 | E26: ='Balance Sheet'!E12 -> 1719.12 | F26: ='Balance Sheet'!F12 -> 779.76
A27: ='Balance Sheet'!A15 -> Current assets
A28: ='Balance Sheet'!A17 -> Investments | B28: Units of Mutual funds | C28: ='Balance Sheet'!C17 -> 53076.37 | D28: ='Balance Sheet'!D17 -> 23877.46 | E28: ='Balance Sheet'!E17 -> 11772.39 | F28: ='Balance Sheet'!F17 -> 11120.75
A29: ='Balance Sheet'!A19 -> Cash and cash equivalents | C29: ='Balance Sheet'!C19 -> 15272.6 | D29: ='Balance Sheet'!D19 -> 1670.34 | E29: ='Balance Sheet'!E19 -> 5691.91 | F29: ='Balance Sheet'!F19 -> 6939.1
A30: ='Balance Sheet'!A20 -> Bank balances (other than cash) | C30: ='Balance Sheet'!C20 -> 17100.96 | D30: ='Balance Sheet'!D20 -> 49156.33 | E30: ='Balance Sheet'!E20 -> 48517.08 | F30: ='Balance Sheet'!F20 -> 47430.52
A31: ='Balance Sheet'!A21 -> Loans | B31: Loans to Employee | C31: ='Balance Sheet'!C21 -> 2282.09 | D31: ='Balance Sheet'!D21 -> 2621.31 | E31: ='Balance Sheet'!E21 -> 2209.22 | F31: ='Balance Sheet'!F21 -> 1925.33
A32: ='Balance Sheet'!A22 -> Other financial assets | B32: Security Deposits, Interest accured, other receivable | C32: ='Balance Sheet'!C22 -> 793.02 | D32: ='Balance Sheet'!D22 -> 2195.84 | E32: ='Balance Sheet'!E22 -> 311.7 | F32: ='Balance Sheet'!F22 -> 326.64
A33: Total | C33: =SUM(C26:C32) -> 103250.73 | D33: =SUM(D26:D32) -> 84816.87 | E33: =SUM(E26:E32) -> 70221.42 | F33: =SUM(F26:F32) -> 68522.1 | G33: =F33-'Capex Schedule '!G334+IS!G11 -> 77144.612 | H33: =G33-'Capex Schedule '!H334+IS!H11 -> 90118.146 | I33: =H33-'Capex Schedule '!I334+IS!I11 -> 111547.89 | J33: =I33-'Capex Schedule '!J334+IS!J11 -> 163690.88 | K33: =J33-'Capex Schedule '!K334+IS!K11 -> 222378.34
A34: Average Interest Yield | C34: 0 | D34: =D22/((D33+C33)/2) -> 0.052686481 | E34: =E22/((E33+D33)/2) -> 0.073778936 | F34: =F22/((F33+E33)/2) -> 0.08050812 | G34: ='Assumption Sheet'!G137 -> 0.064 | H34: ='Assumption Sheet'!H137 -> 0.064 | I34: ='Assumption Sheet'!I137 -> 0.064 | J34: ='Assumption Sheet'!J137 -> 0.064 | K34: ='Assumption Sheet'!K137 -> 0.064
A38: =A14 -> Rent Income | C38: =C14 -> 18.9 | D38: =D14 -> 19.25 | E38: =E14 -> 23.21 | F38: =F14 -> 26.94 | G38: =G39*G40 -> 27.4788 | H38: =H39*H40 -> 28.028376 | I38: =I39*I40 -> 28.588944 | J38: =J39*J40 -> 29.160722 | K38: =K39*K40 -> 29.743937
A39: Closing Gross Block of Non- Current Investment | B39: Comprises a number of residential properties that are leased to third parties | C39: ='Capex Schedule '!C308 -> 252.71 | D39: ='Capex Schedule '!D308 -> 252.71 | E39: ='Capex Schedule '!E308 -> 252.71 | F39: ='Capex Schedule '!F308 -> 252.71 | G39: ='Capex Schedule '!G308 -> 252.71 | H39: ='Capex Schedule '!H308 -> 252.71 | I39: ='Capex Schedule '!I308 -> 252.71 | J39: ='Capex Schedule '!J308 -> 252.71 | K39: ='Capex Schedule '!K308 -> 252.71
A40: Rental Yeild on Closing Gross Block of Non - Current Investments | C40: =C38/C39 -> 0.074789284 | D40: =D38/D39 -> 0.076174271 | E40: =E38/E39 -> 0.091844407 | F40: =F38/F39 -> 0.10660441 | G40: ='Assumption Sheet'!G138 -> 0.1087365 | H40: ='Assumption Sheet'!H138 -> 0.11091123 | I40: ='Assumption Sheet'!I138 -> 0.11312945 | J40: ='Assumption Sheet'!J138 -> 0.11539204 | K40: ='Assumption Sheet'!K138 -> 0.11769988

Sheet Notes
A1: Notes
A12: Artist Management
A13: Clout -
A14: 1.artiste and influencer management division of Pocket Aces, has emerged as a leading force in the digital entertainment ecosystem
A15: 2.Clout operates on a commission based model during the exclusivity period, ensuring transparency and fostering shared value creation for both talent and partners
A16: 3.100% growth since FY 2023-24
A18: Saregama’s Talent and Exclusive Artiste
A19: 1.Dedicated vertical focussed on identifying, nurturing, and scaling emerging musical talents. This initiative showcases new artistes through music releases, offering them a launchpad to reach wider audiences.
A20: 2.Under an agreed revenue-sharing model, Saregama earns a percentage of the artiste’s income during the exclusivity period, aligning the Company’s success directly with the artiste’s career growth.
A32: Film - Yodell
A33: 1.produces a diverse slate of regionally driven content, expanding Saregama’s footprint across theatrical, digital, and satellite platforms
A34: 2.In addition to theatrical revenues, films are licensed to digital platforms and TV channels through fixed-fee, period-based agreements, ensuring upfront revenue while fully retaining IP ownership for future monetisation cycles. This ensures upfront guaranteed revenue while preserving full ownership of IP assets, allowing Saregama to monetise content across multiple life cycles and formats.
... A98: Concall
A99: 46054 | B99: 1.we have also taken the impact on account of the new Labour Code of around INR 7 crores, which is a one-time non-cash exceptional item.
B100: 2.Overall, our spend for the new content this year will be in the space at INR 275 crores to INR 300 crores.
B101: 3.company made a strategic investment in Bhansali Productions through a significant minority ownership, with valuation that is linked to the financial performance of Bhansali Productions over the next 3 years
B102: 4.We continue with the guidance of a 5-year payback period for all new music content that we're acquiring. And after that, another 55 to 75 years of returns on the same music
B103: 5. Music segment Y-o-Y growth -This year, the number may be closer to 18%, 19%, but next year onwards, we should be back to 21% to 23%
B104: 6.We continue with our guidance of 21% to 23% growth in the medium to long term in music segment and an annual adjusted EBITDA guidance of 32% to 33%
B105: 7.So, you will have a breakeven year going there. Post that, I am expecting right now that the Pocket Aces part of the business, which is a combination of artist management and some amount of video content should be growing at a 25% CAGR.
B106: 8.Over the last 1 year, we have brought down Carvaan dramatically. We are now bringing down films business dramatically, but live events business is going up.
B107: 9. So, we are continuing at this juncture with the adjusted EBITDA guidance of 30% to 33%, medium- to long-term guidance for our business at a consolidated level.
B108: 10. I want to clarify is our music investment on newer content, we have given a guidance of around INR 1,000 crores over financial year '25, '26 and '27. So we will continue investing, but the increase in the content spend is not going to be so steep as you have seen over these 3 years. It will then start moving at the rate of inflation maybe, which will be anything between 6% to 8% to 10% every year, not this 30% to 40%, at times 50% jump that you have seen over the last 3 years
B109: 11.I said this in my opening statement that what we are winding down is our films business, but we will continue with a focus on the video side on short-format content, which goes under FilterCopy and medium-sized content, which goes on as web series or TV series. That part of the business is a stable part of the business, profitable part of the business that will continue
B110: 12.Regarding your last point on the majority stake, do we want to go out there and take or not? That's a call Board will be taking at the end of the 3 years. We have the right, not the obligation, to go out there and do that.
B111: 13.. If anything, subscription is going to be ensuring as subscription goes up, that the yield per view or a stream is going to go up
... B113: 15.The industry grows at 6% to 8%. So the older content will continue growing at that particular pace and remaining growth is going to come because of the newer content investments that we people are making.
A116: 45962 | B116: 1.We have created a new cell which actually resides within our video team, but that cell is helping us create latest music videos for the older songs that Saregama owns, using the Generative AI video generation tools. As I'm sure all of you guys will know that Saregama doesn't own the video rights of the songs that were released in the 20th century. We only have the audio rights. And to capitalize on the demand for these songs on YouTube,
B117: 2.Whenever subscription goes up for the platforms, they share around 50% of whatever they make with music labels, the content owners
B118: 3.Artiste management, the new vertical under music monetization, where artistes are made popular through our IP releases, and then we monetize these artistes by booking them for live events, weddings and brand endorsements from which Saregama gets a share
B119: 4. And with digital advertising growing at 14% to 15% per annum, we believe both the content these artistes are making, and the artistes themselves are going to be a large beneficiary of this increase in digital advertising spends.
B120: 5.We had projected growth rate of 30% at consolidated company level for revenue, excluding Carvaan, between financial year '24 to financial year '27, and we hold on to that number. We also maintain our annual adjusted EBITDA guidance of 32% to 33%.
B121: 6.Festive season ends up getting higher advertising on YouTube. And since we get a 55% share of all advertising revenue that comes on our content, so we do get the benefit.
B122: 7.When we buy a song, there are 2 rights that pass across to us. One is called the master right or the sound recording right. That's a right of the song. And you are correct. The Copyright Act says that our ownership is there for 60 years from the release of the song. But there is one more second right that also gets transferred across to us, it's called publishing rights. That's a right of the lyrics of the song and the right of the tune of the song. These are separate rights. According to Indian Copyright Act, the lyrics rights stay with us for 60 years from the death of the artist who wrote the song. And composition rights, the tune rights are valid with us for 60 years from the death of the composer. So we still have a very, very long way to go for many of our superhit songs even a song one right would have come outside 60 years, the other rights are still sitting there with us only
B123: 8.Yes. See, in our case, things like YouTube revenues are completely dependent on new music releases, they jump there, and you immediately see an impact on it.
B124: 9.Unlike the music business, which keeps on growing on a steady basis because songs are being listen on Spotify and YouTube on daily basis. Movies and series you prepare for a period of a few quarters and then you release it in the quarter that it gets released, is where the revenue gets booked.
B125: 10.we have given the guidance that at any particular time, total capital invested in video and live will not exceed more than 18% of the capital employed. We are far lower than that
A128: 45901 | B128: 1.Let's start with the first vertical, music, which comprises of licensingnand artiste management. This segment grew by 12% on a year-on-year basis. We are confident of achieving 22% to 23% annual growth on a medium-term basis under the music vertical. We have been maintaining that position in the past, and we continue maintaining this position.
B129: 2.Overall, our spend for the new content for this year will be somewhere between INR 350 crores to INR 380 crores
B130: 3.So sir, we have been stating that we want to get -- acquire 25% to 30% of all new content that comes out. We believe that with this INR 700 crores, we will reach that level. At this moment, we have no intent to increase our market share of new content beyond 30%
A132: 45778 | B132: 1.Our investment on content this year was INR316 crores, which was 62% higher than that of financial year
B133: 2.What I can tell you is that if I have a subscription deal going on with their platform, on an average, the platform shares 50% of whatever they make. So if there's a platform X who are making INR100 net in a month, on an average, they will share INR50, what is called as a content pool. This money gets divided equally amongst all the songs into the number of times the songs are heard during the month.
B134: 3.Hopefully, we should be upwards of 20% -- on specific segments of their right now, they're all part of the larger Saregama company. Saregama company music business is going to be growing at 23%, while Video business is going to be growing at 25% on a medium-term basis.

Sheet Template 
A1: Sheet Name
A2: Figures in Lakhs ,expect otherwise stated
A3: Particular/Years | B3: Comments | C3: 2021-22 A | D3: 2022-23 A | E3: 2023-24 A | F3: 2024-25 A | G3: 2025-26 E | H3: 2026-27 E | I3: 2027-28 E | J3: 2028-29 E | K3: 2029-30 E
